Workbook

Sheet כללי (0)
B4: כללי
B5: שם הגוף המונחה | C5: המרכז למיפוי ישראל (מפ"י)
B6: שם פרויקט | C6: פורטל לקוחות מפ"י — הוכחת היתכנות (POC)
B7: בעל המידע (Data Owner) הגורם אשר הוסמך לאוסף/ליצור ולעבד את המידע במערכת ואחראי באופן חוקי על שמירה והגנה על המידע בהתאם לתקנות החוקיות ורגולטוריות הנוגעות למידע | C7: מפ"י — אגף מיפוי וממ"ג ואגף גבולות בינלאומיים (לאישור סופי על ידי מפ"י)
B8: אחראי פרויקט (אדמיניסטרטיבי) | C8: להשלמה על ידי מפ"י
B9: סוג המערכת | C9: פורטל אינטרנטי ציבורי (Web) להנגשת מידע גאוגרפי, הזמנת מוצרים ופניות שירות
B10: תיאור קצר של התהליכים העסקיים שהמערכת ומידע משרתים | C10: הצגת קטלוג המוצרים והשירותים של מפ"י לציבור; הזמנה מקוונת של מפות נייר ומפות היסטוריות; פנייה לקבלת מידע מאגף הגבולות הבינלאומיים; מעקב הזמנות; וממשק ניהול תוכן ומוצרים (CMS) לעובדי מפ"י.
B12: גורמים מאשרים את ממצאי תהליך ניהול הסיכונים
B13: אישור מנחה
B14: ממונה תמ"ק
B15: יועץ משפטי
B16: ממונה הגנת פרטיות
B17: מנהל מערכות מידע (מנמ"ר)
B18: תאריך האישור
B19: מזהה חישוב (אוטומטי) | C19: =" מחשבון סיווג דאטה עבור " &C6&" "&TEXT(NOW(),"DD-MM-YYYY-HH:MM") -> מחשבון סיווג דאטה עבור 06-01-2025-11:00
B21: גורמים מאשרים את ממצאי תהליך ניהול הסיכונים

Sheet כשירות ארגונית (1)
B3: כשירות ארגונית לגופי תמ"ק
D4: תשובה | F4: ציון | G4: ציון מקסימלי | H4: תשובה 1 | I4: תשובה 2 | J4: תשובה 3 | K4: תשובה 4
B5: אסטרטגיה | C5: האם הנהלת הארגון מודעת לתהליך המעבר לענן? | D5: ההנהלה מודעת לתהליך הארגון של המעבר לענן, אך לא הוצגה בפניה תוכנית העבודה למעבר לענן | F5: =IF(D5=H5,0,IF(D5=I5,1,IF(D5=J5,2,"ERROR"))) -> 1 | G5: 2 | H5: הוצגה להנהלה תוכנית העבודה הארגוית של המעבר לענן | I5: ההנהלה מודעת לתהליך הארגון של המעבר לענן, אך לא הוצגה בפניה תוכנית העבודה למעבר לענן | J5: ההנהלה לא מוערבת בתהליך הארגון של המעבר לענן
C6: האם הוגדרה אסטאטגיה ארגונית למעבר לענן? | D6: כן | F6: =IF(D6=H6,0,IF(D6=I6,1,"ERROR")) -> 0 | G6: 1 | H6: כן | I6: לא
D8: תשובה
B9: ניהול סיכונים | C9: האם הארגון הריחיב את מתודולוגיית לניהול סיכוני סייבר בענן? | D9: כן, קיימת מתודלוגיה לניהול סיכונים בארגון שנבחנה ויש צוות ייעודי לניהול הסיכונים | F9: =IF(D9=H9,0,IF(D9=I9,1,IF(D9=J9,2,IF(D9=K9,3,"ERROR")))) -> 0 | G9: 3 | H9: כן, קיימת מתודלוגיה לניהול סיכונים בארגון שנבחנה ויש צוות ייעודי לניהול הסיכונים | I9: כן, קיימת מתודלוגיה לניהול סיכונים בארגון שנבחנה בפועל | J9: קיימת מתודלוגיה לניהול סיכונים בארגון, בשלבי בדיקה ראשוניים | K9: לא קיימת מתודולוגיית ניהול סיכונים בארגון
C10: כמות מערכות בארגון עלו לענן? | D10: בין 2-5 | F10: =IF(D10=H10,0,IF(D10=I10,1,IF(D10=J10,2,IF(D10=K10,10,"ERROR")))) -> 1 | G10: 10 | H10: מעל 5 | I10: בין 2-5 | J10: מערכת אחת | K10: זוהי המערכת הראשונה
D12: תשובה
B13: משאבי כ"א בתחום הענן | C13: האם ממונה התמ"ק עבר הכשרות לתחום הענן? | D13: לא | F13: =IF(D13=H13,0,IF(D13=I13,1,"ERROR")) -> 1 | G13: 1 | H13: כן | I13: לא
D15: תשובה
B16: ניהול פיננסי | C16: האם הוגדרה מדיניות כלכלת ענן בארגון בדגש אבטחת הסייבר? | D16: אין היכרות עם מדיניות כלכלת הענן | F16: =IF(D16=H16,0,IF(D16=I16,1,IF(D16=J16,2,IF(D16=K16,3,"ERROR")))) -> 3 | G16: 3 | H16: מדיניות כלכלת ענן ממומשת במלואה | I16: מדיניות כלכלת ענן נמצאת בשלבי יישום | J16: מדיניות כלכלת הענן נמצאת בשלבי למידה | K16: אין היכרות עם מדיניות כלכלת הענן
C17: האם לארגון הוגדר תקציב ייעודי להעלאת מערכת לענן הכוללת את התחומים הבאים: עלות כוח אדם, ארכיטקטורת הפרויקט, היבטי אבטחה, עלות שירותי הענן ושימוש בו? | D17: אין הקצאת תקציבים כלל לצורך מעבר\הקמת המערכת בענן | F17: =IF(D17=H17,0,IF(D17=I17,1,IF(D17=J17,2,"ERROR"))) -> 2 | G17: 2 | H17: קיים תקציב ייעודי למעבר\הקמת המערכת לענן | I17: לא קיים תקציב ייעודי, אך מוקצה תקציב בעת הצורך, באופן נקודתי | J17: אין הקצאת תקציבים כלל לצורך מעבר\הקמת המערכת בענן
D19: תשובה
B20: תהליכים ארגוניים נוספים לענן | C20: האם לארגון יש תשתיות לניטור ותפעול בתחום אבטחת מידע לסביבת הענן? | D20: קיים ניטור בארגון כולל חיבור לסוק | F20: =IF(D20=H20,0,IF(D20=I20,0,IF(D20=J20,0,IF(D20=K20,1,"ERROR")))) -> 0 | G20: 1 | H20: קיים מערכות ניטור פנימיות | I20: קיים ניטור צד ג' ( ספק חיצוני) | J20: קיים ניטור בארגון כולל חיבור לסוק | K20: לא קיים מערכת לניטור סביבת המערכת בענן

Sheet פרופיל מערכת (2)
C3: פרטי המערכת
D4: תשובה | F4: ציון | G4: ציון מקסימלי | H4: תשובה 1 | I4: תשובה 2 | J4: תשובה 3 | K4: תשובה 4
A5: Q2.1 | B5: מאפייני מידע | C5: מה אופן השימוש המתוכנן בנתונים בענן? | D5: הנגשת מידע ואפשרות לעדכון (עם יכולת אחסון מידע או גיבוי המידע) | F5: =IF(D5=H5,0,IF(D5=I5,1,IF(D5=J5,2,IF(D5=K5,3,"ERROR")))) -> 1 | G5: 3 | H5: הנגשת המידע להצגה בלבד | I5: הנגשת מידע ואפשרות לעדכון (עם יכולת אחסון מידע או גיבוי המידע) | J5: עדכון ואחסון המידע (או גיבוי המידע) בשילוב לימוד מכונה ML | K5: עדכון ואחסון המידע (או גיבוי המידע) בשילוב עיבוד המידע בזמן אמת או לימוד מכונה
A6: Q2.2 | C6: מה הוא סוג הנתונים במערכת? | D6: פיתוח או בדיקות (נתוני דמה) | F6: =IF(D6=H6,0,IF(D6=I6,1,IF(D6=J6,5,IF(D6=K6,3,"ERROR")))) -> 1 | G6: 5 | H6: פיתוח (נתוני דמה) | I6: פיתוח או בדיקות (נתוני דמה) | J6: פיתוח או בדיקות (נתוני אמת) | K6: בדיקות או ייצור (נתוני אמת)
A7: Q2.3 | C7: האם המידע ישמר בישראל? | D7: לא | F7: =IF(D7=H7,0,IF(D7=I7,1,IF(D7=J7,2,"ERROR"))) -> 0 | G7: 2 | H7: כן | I7: לא | J7: משולב בארץ ובחו"ל
A8: Q2.4 | C8: האם המידע יעובד בישראל | D8: לא | F8: =IF(D8=H8,0,IF(D8=I8,1,IF(D8=J8,2,"ERROR"))) -> 0 | G8: 2 | H8: כן | I8: לא | J8: משולב בארץ ובחו"ל
A9: Q2.5 | C9: משך האחסון המקסימלי של מידע בענן? | D9: אחסון ארוך תווך מעל 6 חודשים | F9: =IF(D9=H9,0,IF(D9=I9,1,IF(D9=J9,2,IF(D9=K9,3,"ERROR")))) -> 1 | G9: 3 | H9: אחסון לצורך עיבוד בלבד (עד יום) | I9: אחסון לתווך זמן קצר (ימים בודדים) | J9: אחסון לתווך בינוני (מספר שבועות עד 6 חודשים) | K9: אחסון ארוך תווך מעל 6 חודשים
A10: Q2.6 | C10: האם המידע יוצפן בתנועה? | D10: כן | F10: =IF(D10=H10,0,IF(D10=I10,10,"ERROR")) -> 10 | G10: 10 | H10: כן | I10: לא
A11: Q2.7 | C11: האם המידע במערכת יוצפן במנוחה? | D11: כן | F11: =IF(D11=H11,0,IF(D11=I11,10,"ERROR")) -> 10 | G11: 10 | H11: כן | I11: לא
A12: Q2.8 | C12: היכן ינוהלו מפתחות ההצפנה? | D12: בענן על ידי שירות ענן אוטומטי | F12: =IF(D12=H12,10,IF(D12=I12,5,IF(D12=J12,3,IF(D12=K12,0,"ERROR")))) -> 5 | G12: 10 | H12: בענן על ידי שירות ענן אוטומטי | I12: בענן על ידי גוף התמ"ק | J12: בשירות מנוהל חיצוני על ידי גוף התמ"ק | K12: באופן מקומי ברשת גוף התמ"ק על ידי גוף התמ"ק
D14: תשובה
A15: Q2.9 | B15: מאפייני מערכת | C15: האם המידע או המערכת מוגדרים כתמ"ק (מערכת שבגללה הגוף הוגדר תמ"ק) | D15: לא | F15: =IF(D15=H15,100,IF(D15=I15,0,"ERROR")) -> 100 | G15: 100 | H15: כן | I15: לא
A16: Q2.10 | C16: סביבות במערכת | D16: סביבת בדיקות וסביבת ייצור | F16: =IF(D16=H16,0,IF(D16=I16,1,IF(D16=J16,2,IF(D16=K16,3,"ERROR")))) -> 0 | G16: 3 | H16: סביבות פיתוח | I16: סביבת פיתוח או בדיקות | J16: סביבת בדיקות וסביבת ייצור | K16: סביבת ייצור בלבד
A17: Q2.11 | C17: זמינות המערכת (SLA) דרושה | D17: כסף 99.9% - עד 9 שעות השבתה בשנה | F17: =IF(D17=H17,0,IF(D17=I17,1,IF(D17=J17,2,IF(D17=K17,3,"ERROR")))) -> 1 | G17: 3 | H17: זמינות Best Effort | I17: כסף 99.9% - עד 9 שעות השבתה בשנה | J17: זהב 99.99% - עד 1 שעת השבתה בשנה | K17: פלטינה 99.999% - פחות מ 6 דקות השבתה בשנה
A18: Q2.12 | C18: מידת הפגיעה בשירותי זמן אמת (Real Time Services) כתוצאה מפגיעה במערכת | D18: השפעה נמוכה מאוד על שירות לא אסטרטגי | F18: =IF(D18=H18,0,IF(D18=I18,1,IF(D18=J18,2,IF(D18=K18,3,"ERROR")))) -> 0 | G18: 3 | H18: השפעה נמוכה מאוד על שירות לא אסטרטגי | I18: חריגה של 1-3 יממות באספקת שירות לא אסטרטגי | J18: חריגה של עד מספר שעות לאספקת שירות אסטרטגי | K18: פגיעה ניכרת לאספקת שירות אסטרטגי בביקוש גבוהה
A19: Q2.13 | C19: מה מידת ההשפעה של פגיעה במערכת על גישה\הפעילות השוטפת של מערכות אחרות בארגון | D19: ללא פגיעה או השפעה על פעילות של מערכות פנימיות | F19: =IF(D19=H19,0,IF(D19=I19,1,IF(D19=J19,2,IF(D19=K19,3,"ERROR")))) -> 0 | G19: 3 | H19: ללא פגיעה או השפעה על פעילות של מערכות פנימיות | I19: פגיעה מצומצמת בפעילות השוטפת של מערכות פנימיות | J19: פגיעה חלקית ביכולת הגישה\הפעילות השוטפת של מערכות פנימיות קריטיות | K19: פגיעה מהותית ביכולת הגישה\הפעילות שוטפת של מערכות פנימיות קריטיות
A20: Q2.14 | C20: מידת השפעת פגיעה במערכת על תהליכים פיזיים OT (ניהול בניין, ניהול תהליך משני, ניהול תהליך ראשי) | D20: ללא השפעה או פגיעה בתהליך פיזי בארגון | F20: =IF(D20=H20,0,IF(D20=I20,1,IF(D20=J20,5,IF(D20=K20,10,"ERROR")))) -> 1 | G20: 10 | H20: ללא השפעה או פגיעה בתהליך פיזי בארגון | I20: פגיעה עקיפה לתהליך קבלת החלטות בנוגע לתהליך פיזי בארגון | J20: פגיעה עקיפה לתהליך קריטי בארגון | K20: פגיעה ישירה בתהליך ראשי פיזי (קינטי) קריטי לארגון
A21: Q2.15 | C21: מה היא תצורת השרידות של המערכת | D21: שרידות מלאה אוטומטית (גיבוי חם) | F21: =IF(D21=H21,0,IF(D21=I21,1,IF(D21=J21,2,IF(D21=K21,3,"ERROR")))) -> 0 | G21: 3 | H21: שרידות מלאה אוטומטית (גיבוי חם) | I21: שרידות מלאה ידנית | J21: שרידות חלקית אוטומטית | K21: שרידות חלקית ידנית
A22: Q2.16 | C22: מה מידת ההשפעה של פגיעה במערכת על ניהול התשתיות הטכנולוגיות בחברה (ניטור, ממשק ניהול, API, רשת,גיבויים וכו) | D22: ללא השפעה על פעילות מערכות ניהול תשתיות | F22: =IF(D22=H22,0,IF(D22=I22,1,IF(D22=J22,2,IF(D22=K22,3,"ERROR")))) -> 0 | G22: 3 | H22: ללא השפעה על פעילות מערכות ניהול תשתיות | I22: פגיעה חלקית בפונקציונליות של מערכת בודדת לניהול תשתיות לא קריטיות | J22: פגיעה מצומצמת למערכת ניהול תשתיות קריטיות | K22: פגיעה רוחבית למערכת ניהול תשתיות קריטיות
A23: Q2.17 | C23: סוג הגישה למערכת | D23: Web או מובייל או אפליקציה מהאינטרנט | F23: =IF(D23=H23,0,IF(D23=I23,1,IF(D23=J23,2,IF(D23=K23,3,"ERROR")))) -> 0 | G23: 3 | H23: WEB מתוך הארגון בלבד | I23: אפליקציה ייעודית ברשת הארגון | J23: מובייל או אפליקציה מהאינטרנט או מהארגון | K23: Web או מובייל או אפליקציה מהאינטרנט
D25: תשובה
A26: Q2.18 | B26: משתמשים והזדהות | C26: פרטו לגבי פרופילים אופייניים של המשתמשים במערכת | D26: חיצוניים | F26: =IF(D26=H26,0,IF(D26=I26,1,IF(D26=J26,2,IF(D26=K26,3,"ERROR")))) -> 2 | G26: 3 | H26: מנהלים פנימיים בלבד | I26: פנימיים | J26: חיצוניים | K26: אורחים
A27: Q2.19 | C27: מהו היקף המשתמשים הצפוי / קיים? | D27: מעל 100 משתמשים | F27: =IF(D27=H27,0,IF(D27=I27,1,IF(D27=J27,2,IF(D27=K27,3,"ERROR")))) -> 1 | G27: 3 | H27: בודדים עד 5 משתמשים | I27: בין 5-50 משתמשים | J27: בין 50-100 משתמשים | K27: מעל 100 משתמשים
A28: Q2.20 | C28: מהם תהליכי ההזדהות למערכת (עבור משתמשים) | D28: שם משתמש וסיסמא | F28: =IF(D28=H28,0,IF(D28=I28,1,IF(D28=J28,2,IF(D28=K28,3,"ERROR")))) -> 1 | G28: 3 | H28: לא קיימת הזדהות | I28: הזדהות רב שלבית ארגונית | J28: התחברות SSO ציבורית\צד ג' | K28: שם משתמש וסיסמא
A29: Q2.21 | C29: אופן הגישה למערכת (עבור משתמשים) | D29: המערכת נגישה במרשת האינטרנט עולמית ללא VPN | F29: =IF(D29=H29,0,IF(D29=I29,1,IF(D29=J29,2,IF(D29=K29,3,"ERROR")))) -> 0 | G29: 3 | H29: המערכת נגישה מסגמנט ייעודי ברשת הפנים ארגונית | I29: המערכת נגישה פנים ארגונית בלבד | J29: המערכת נגישה פנים ארגונית או באמצעות VPN | K29: המערכת נגישה במרשת האינטרנט עולמית ללא VPN
A30: Q2.22 | C30: תצורת הגישה | D30: גישה אינטרנטית WEB | F30: =IF(D30=H30,0,IF(D30=I30,1,IF(D30=J30,2,IF(D30=K30,3,"ERROR")))) -> 0 | G30: 3 | H30: גישה מבודלת על ידי מערכת אבטחה | I30: גישה API | J30: גישה בפורמט בסיס נתונים | K30: גישה אינטרנטית WEB
A31: Q2.23 | C31: כמות משתמשים פנימיים | D31: עשרות | F31: =IF(D31=H31,0,IF(D31=I31,1,IF(D31=J31,2,IF(D31=K31,3,"ERROR")))) -> 1 | G31: 3 | H31: לא קיימים משתמשים מסוג זה | I31: עשרות | J31: מאות | K31: אלפים ומעלה
A32: Q2.24 | C32: כמות משתמשים ספק חיצוני | D32: עשרות | F32: =IF(D32=H32,0,IF(D32=I32,1,IF(D32=J32,2,IF(D32=K32,3,"ERROR")))) -> 1 | G32: 3 | H32: לא קיימים משתמשים מסוג זה | I32: עשרות | J32: מאות | K32: אלפים ומעלה
A33: Q2.25 | C33: כמות משתמשים ציבוריים | D33: מאות | F33: =IF(D33=H33,0,IF(D33=I33,1,IF(D33=J33,2,IF(D33=K33,3,"ERROR")))) -> 0 | G33: 3 | H33: לא קיימים משתמשים מסוג זה | I33: עשרות | J33: מאות | K33: אלפים ומעלה
A34: Q2.26 | C34: אופן הגישה למערכת (עבור ניהול המערכת) | D34: שם משתמש וסיסמא - נותן שירות חיצוני ע"ג רשת האינטרנט | F34: =IF(D34=H34,0,IF(D34=I34,1,IF(D34=J34,2,IF(D34=K34,3,"ERROR")))) -> 0 | G34: 3 | H34: מערכת ייעודית לניהול מתוך הארגון בלבד או הזדהות רב שלבית ארגונית - ניהול פנימי לארגון | I34: התחברות SSO ארגונית - ניהול פנימי לארגון | J34: הזדהות רב שלבית חיצוני - נותן שירות חיצוני ע"ג רשת האינטרנט | K34: שם משתמש וסיסמא - נותן שירות חיצוני ע"ג רשת האינטרנט
D36: תשובה
A37: Q2.28 | B37: ממשקים | C37: כמות ממשקים לפנים הארגון | D37: לא רלוונטי / ללא ממשקים פנימיים | F37: =IF(D37=H37,0,IF(D37=I37,1,IF(D37=J37,2,IF(D37=K37,3,"ERROR")))) -> 0 | G37: 3 | H37: לא רלוונטי / ללא ממשקים פנימיים | I37: 1-2 ממשקים פנימים | J37: 2-10 ממשקים | K37: מעל 10 ממשקים
A38: Q2.29 | C38: כמות ממשקים חיצוניים (ביון הארגון לארגונים אחרים והחוצה) | D38: 2-10 ממשקים | F38: =IF(D38=H38,0,IF(D38=I38,1,IF(D38=J38,2,IF(D38=K38,3,"ERROR")))) -> 0 | G38: 3 | H38: לא רלוונטי / ללא ממשקים פנימיים | I38: 1-2 ממשקים פנימים | J38: 2-10 ממשקים | K38: מעל 10 ממשקים
A39: Q2.30 | C39: האם מבוצע תהליך זיכוי - הלבנה השחרה בממשקים | D39: לא מבוצע תהליך הלבנה\השחרה | F39: =IF(D39=H39,0,IF(D39=I39,1,IF(D39=J39,5,IF(D39=K39,10,"ERROR")))) -> 0 | G39: 10 | H39: לא רלוונטי / לא נדרש | I39: כן באופן מלא | J39: חלקי | K39: לא מבוצע תהליך הלבנה\השחרה
A40: Q2.31 | C40: תדירות הקישור לממשקים | D40: רב פעמית (עד 20 פעם ביום) | F40: =IF(D40=H40,0,IF(D40=I40,1,IF(D40=J40,2,IF(D40=K40,3,"ERROR")))) -> 0 | G40: 3 | H40: לא רלוונטי / לא נדרש | I40: רב פעמית (עד 20 פעם ביום) | J40: מרובה (20-50 פעם ביום) | K40: קבוע (מעל 50 פעם ביום)
A41: Q2.32 | C41: פרוטוקולים בשימוש הממשק | D41: פרוטוקול פומבי מוצפן | F41: =IF(D41=H41,0,IF(D41=I41,1,IF(D41=J41,2,IF(D41=K41,3,"ERROR")))) -> 0 | G41: 3 | H41: לא רלוונטי / פרוטוקול ייעודי מוצפן | I41: פרוטוקול פומבי מוצפן | J41: פרוטוקול ייעודי לא מוצפן | K41: פרוטוקול גלוי לא מוצפן
A42: Q2.33 | C42: האם מתקיימים ממשקי API מול מערכות מחוץ לשדרת המידע | D42: כן | F42: =IF(D42=H42,0,IF(D42=I42,1,"ERROR")) -> 0 | G42: 1 | H42: לא רלוונטי / לא קיים | I42: כן
A43: Q2.34 | C43: הסתמכות המערכת על ממשקי התקשרות חיצונית (תיבת מייל, CHAT BOT, וואצאפ\SMS נכנס, טעינה ועיבוד קבצים) | D43: חלק משני מפונקציונליות לא קריטית של המערכת מבוסס על העברת תוכן ממשקי התקשרות חיצוניים | F43: =IF(D43=H43,0,IF(D43=I43,1,IF(D43=J43,2,IF(D43=K43,3,"ERROR")))) -> 0 | G43: 3 | H43: לא רלוונטי / המערכת לא מתבססת על העברת תוכן ממשקי התקשרות חיצוניים | I43: חלק משני מפונקציונליות לא קריטית של המערכת מבוסס על העברת תוכן ממשקי התקשרות חיצוניים | J43: חלק ניכר מפעילות המערכת מתבסס על העברת תוכן מממשקי התקשרות חיצוניים | K43: כלל פעילות המערכת מבוססת על העברת תוכן מממשקי התקשרות חיצוניים
D45: תשובה
A46: Q2.35 | B46: אופן היישום בענן | C46: אופן המגרציה לענן | D46: refactor | F46: =IF(D46=H46,0,IF(D46=I46,1,IF(D46=J46,2,IF(D46=K46,3,"ERROR")))) -> 0 | G46: 3 | H46: retire או tetain | I46: rehost | J46: replatform | K46: refactor
A47: Q2.36 | C47: סוג ספק הענן | D47: ספק ענן אחר | F47: =IF(D47=H47,1,IF(D47=I47,2,IF(D47=J47,3,"ERROR"))) -> 2 | G47: 3 | H47: ספק ענן במסגרת פרויקט נימבוס | I47: ספק ענן גדול (Azure, GCP, AWS) | J47: ספק ענן אחר
A48: Q2.37 | C48: סוג איזור הנחיתה | D48: עצמאי | F48: =IF(D48=H48,0,IF(D48=I48,1,IF(D48=J48,2,"ERROR"))) -> 1 | G48: 2 | H48: LZ ממשלתי | I48: עצמאי | J48: אחר
A49: Q2.38 | C49: ספק הענן | D49: אחר | F49: 0 | G49: 0 | H49: AWS | I49: GCP | J49: Azure | K49: Oracle | L49: IBM | M49: Alibaba | N49: אחר
A50: Q2.39 | C50: סוג תשתית הענן | D50: PaaS | F50: 0 | G50: 0 | H50: הכל | I50: Iaas | J50: SaaS | K50: PaaS
A51: Q2.40 | C51: האם המערכת תשתמש ביותר מסביבה עננית אחת? | D51: כן | F51: =IF(D51=H51,0,IF(D51=I51,1,"ERROR")) -> 0 | G51: 1 | H51: לא | I51: כן
A52: Q2.41 | C52: האם המערכת משלבת שירותים מרובדי נימבוס | D52: לא בנימבוס | F52: =IF(D52=H52,1,IF(D52=I52,1,IF(D52=J52,1,IF(D52=K52,3,"ERROR")))) -> 1 | G52: 3 | H52: רובד 1 | I52: רובד 5 | J52: רובד 1 + 5 | K52: לא בנימבוס

Sheet חישובים
A1: INF TYPE | B1: CP | C1: Chosen INF | D1: Language | E1: Count Controls | G1: Identify | H1: Detect | I1: Protect | J1: Respond | K1: Recover | N1: Cloud Provider | O1: Language | Q1: Yes | S1: כמות בקרות להם יש בקרת ספק | T1: כמות בקרות ספק שמוטמעות ב LZ | U1: כמות בקרות חד פעמיות
A2: הכל | B2: ='פרופיל בקרות דרוש (8)'!E3 -> GCP | C2: ='פרופיל בקרות דרוש (8)'!E2 -> IaaS | D2: ='פרופיל בקרות דרוש (8)'!E4 -> עברית - מקוצר | E2: =IF( AND($D$2=$O$2, $B$2=$N$2), COUNTIF('בקרות להפחתת סיכון AWS (EN)'!A:A,"Yes"), IF( AND($D$2=$O$3, $B$2=$N$2), COUNTIF('בקרות להפחתת סיכון AWS (HEB)'!A:A,"Yes"), IF( AND($D$2=$O$2, $B$2=$N$3), COUNTIF('בקרות להפחתת סיכון GCP (EN)'!A:A,"Yes"), IF( AND($D$2=$O$3, $B$2=$N$3), COUNTIF('בקרות להפחתת סיכון GCP (HEB)'!A:A,"Yes") ) ) ) ) -> 218 | F2: = | G2: =IF( AND($D$2=$O$2, $B$2=$N$2), COUNTIFS('בקרות להפחתת סיכון AWS (EN)'!$A:$A,"YES",'בקרות להפחתת סיכון AWS (EN)'!$E:$E,G1) & "/" & COUNTIF('בקרות להפחתת סיכון AWS (EN)'!$E:$E,G1), IF( AND($D$2=$O$3, $B$2=$N$2), COUNTIFS('בקרות להפחתת סיכון AWS (HEB)'!$A:$A,"YES",'בקרות להפחתת סיכון AWS (HEB)'!$E:$E,G1) & "/" & COUNTIF('בקרות להפחתת סיכון AWS (HEB)'!$E:$E,G1), IF( AND($D$2=$O$2, $B$2=$N$3), COUNTIFS('בקרות להפחתת סיכון GCP (EN)'!$A:$A,"YES",'בקרות להפחתת סיכון GCP (EN)'!$E:$E,G1) & "/" & COUNTIF('בקרות להפחתת סיכון GCP (EN)'!$E:$E,G1), IF( AND($D$2=$O$3, $B$2=$N$3), COUNTIFS('בקרות להפחתת סיכון GCP (HEB)'!$A:$A,"YES",'בקרות להפחתת סיכון GCP (HEB)'!$E:$E,G1) & "/" & COUNTIF('בקרות להפחתת סיכון GCP (HEB)'!$E:$E,G1) ) ) ) ) -> 20/21 | H2: =IF( AND($D$2=$O$2, $B$2=$N$2), COUNTIFS('בקרות להפחתת סיכון AWS (EN)'!$A:$A,"YES",'בקרות להפחתת סיכון AWS (EN)'!$E:$E,H1) & "/" & COUNTIF('בקרות להפחתת סיכון AWS (EN)'!$E:$E,H1), IF( AND($D$2=$O$3, $B$2=$N$2), COUNTIFS('בקרות להפחתת סיכון AWS (HEB)'!$A:$A,"YES",'בקרות להפחתת סיכון AWS (HEB)'!$E:$E,H1) & "/" & COUNTIF('בקרות להפחתת סיכון AWS (HEB)'!$E:$E,H1), IF( AND($D$2=$O$2, $B$2=$N$3), COUNTIFS('בקרות להפחתת סיכון GCP (EN)'!$A:$A,"YES",'בקרות להפחתת סיכון GCP (EN)'!$E:$E,H1) & "/" & COUNTIF('בקרות להפחתת סיכון GCP (EN)'!$E:$E,H1), IF( AND($D$2=$O$3, $B$2=$N$3), COUNTIFS('בקרות להפחתת סיכון GCP (HEB)'!$A:$A,"YES",'בקרות להפחתת סיכון GCP (HEB)'!$E:$E,H1) & "/" & COUNTIF('בקרות להפחתת סיכון GCP (HEB)'!$E:$E,H1) ) ) ) ) -> 47/49 | I2: =IF( AND($D$2=$O$2, $B$2=$N$2), COUNTIFS('בקרות להפחתת סיכון AWS (EN)'!$A:$A,"YES",'בקרות להפחתת סיכון AWS (EN)'!$E:$E,I1) & "/" & COUNTIF('בקרות להפחתת סיכון AWS (EN)'!$E:$E,I1), IF( AND($D$2=$O$3, $B$2=$N$2), COUNTIFS('בקרות להפחתת סיכון AWS (HEB)'!$A:$A,"YES",'בקרות להפחתת סיכון AWS (HEB)'!$E:$E,I1) & "/" & COUNTIF('בקרות להפחתת סיכון AWS (HEB)'!$E:$E,I1), IF( AND($D$2=$O$2, $B$2=$N$3), COUNTIFS('בקרות להפחתת סיכון GCP (EN)'!$A:$A,"YES",'בקרות להפחתת סיכון GCP (EN)'!$E:$E,I1) & "/" & COUNTIF('בקרות להפחתת סיכון GCP (EN)'!$E:$E,I1), IF( AND($D$2=$O$3, $B$2=$N$3), COUNTIFS('בקרות להפחתת סיכון GCP (HEB)'!$A:$A,"YES",'בקרות להפחתת סיכון GCP (HEB)'!$E:$E,I1) & "/" & COUNTIF('בקרות להפחתת סיכון GCP (HEB)'!$E:$E,I1) ) ) ) ) -> 132/139 | J2: =IF( AND($D$2=$O$2, $B$2=$N$2), COUNTIFS('בקרות להפחתת סיכון AWS (EN)'!$A:$A,"YES",'בקרות להפחתת סיכון AWS (EN)'!$E:$E,J1) & "/" & COUNTIF('בקרות להפחתת סיכון AWS (EN)'!$E:$E,J1), IF( AND($D$2=$O$3, $B$2=$N$2), COUNTIFS('בקרות להפחתת סיכון AWS (HEB)'!$A:$A,"YES",'בקרות להפחתת סיכון AWS (HEB)'!$E:$E,J1) & "/" & COUNTIF('בקרות להפחתת סיכון AWS (HEB)'!$E:$E,J1), IF( AND($D$2=$O$2, $B$2=$N$3), COUNTIFS('בקרות להפחתת סיכון GCP (EN)'!$A:$A,"YES",'בקרות להפחתת סיכון GCP (EN)'!$E:$E,J1) & "/" & COUNTIF('בקרות להפחתת סיכון GCP (EN)'!$E:$E,J1), IF( AND($D$2=$O$3, $B$2=$N$3), COUNTIFS('בקרות להפחתת סיכון GCP (HEB)'!$A:$A,"YES",'בקרות להפחתת סיכון GCP (HEB)'!$E:$E,J1) & "/" & COUNTIF('בקרות להפחתת סיכון GCP (HEB)'!$E:$E,J1) ) ) ) ) -> 12/12 | K2: =IF( AND($D$2=$O$2, $B$2=$N$2), COUNTIFS('בקרות להפחתת סיכון AWS (EN)'!$A:$A,"YES",'בקרות להפחתת סיכון AWS (EN)'!$E:$E,K1) & "/" & COUNTIF('בקרות להפחתת סיכון AWS (EN)'!$E:$E,K1), IF( AND($D$2=$O$3, $B$2=$N$2), COUNTIFS('בקרות להפחתת סיכון AWS (HEB)'!$A:$A,"YES",'בקרות להפחתת סיכון AWS (HEB)'!$E:$E,K1) & "/" & COUNTIF('בקרות להפחתת סיכון AWS (HEB)'!$E:$E,K1), IF( AND($D$2=$O$2, $B$2=$N$3), COUNTIFS('בקרות להפחתת סיכון GCP (EN)'!$A:$A,"YES",'בקרות להפחתת סיכון GCP (EN)'!$E:$E,K1) & "/" & COUNTIF('בקרות להפחתת סיכון GCP (EN)'!$E:$E,K1), IF( AND($D$2=$O$3, $B$2=$N$3), COUNTIFS('בקרות להפחתת סיכון GCP (HEB)'!$A:$A,"YES",'בקרות להפחתת סיכון GCP (HEB)'!$E:$E,K1) & "/" & COUNTIF('בקרות להפחתת סיכון GCP (HEB)'!$E:$E,K1) ) ) ) ) -> 7/7 | N2: AWS | O2: English - Brief | Q2: ** | S2: =IF( AND($D$2=$O$2, $B$2=$N$2), COUNTIFS('בקרות להפחתת סיכון AWS (EN)'!AA:AA,"v",'בקרות להפחתת סיכון AWS (EN)'!A:A,"Yes"), IF( AND($D$2=$O$3, $B$2=$N$2), COUNTIFS('בקרות להפחתת סיכון AWS (HEB)'!AA:AA,"v",'בקרות להפחתת סיכון AWS (HEB)'!A:A,"Yes"), IF( AND($D$2=$O$2, $B$2=$N$3), COUNTIFS('בקרות להפחתת סיכון GCP (EN)'!AA:AA,"v",'בקרות להפחתת סיכון GCP (EN)'!A:A,"Yes"), IF( AND($D$2=$O$3, $B$2=$N$3), COUNTIFS('בקרות להפחתת סיכון GCP (HEB)'!AA:AA,"v",'בקרות להפחתת סיכון GCP (HEB)'!A:A,"Yes") ) ) ) ) -> 105 | T2: =IF( AND($D$2=$O$2, $B$2=$N$2), COUNTIFS('בקרות להפחתת סיכון AWS (EN)'!AA:AA,"v",'בקרות להפחתת סיכון AWS (EN)'!U:U,"v",'בקרות להפחתת סיכון AWS (EN)'!A:A,"Yes"), IF( AND($D$2=$O$3, $B$2=$N$2), COUNTIFS('בקרות להפחתת סיכון AWS (HEB)'!AA:AA,"v",'בקרות להפחתת סיכון AWS (HEB)'!U:U,"v",'בקרות להפחתת סיכון AWS (HEB)'!A:A,"Yes"), IF( AND($D$2=$O$2, $B$2=$N$3), COUNTIFS('בקרות להפחתת סיכון GCP (EN)'!AA:AA,"v",'בקרות להפחתת סיכון GCP (EN)'!U:U,"v",'בקרות להפחתת סיכון GCP (EN)'!A:A,"Yes"), IF( AND($D$2=$O$3, $B$2=$N$3), COUNTIFS('בקרות להפחתת סיכון GCP (HEB)'!AA:AA,"v",'בקרות להפחתת סיכון GCP (HEB)'!U:U,"v",'בקרות להפחתת סיכון GCP (HEB)'!A:A,"Yes") ) ) ) ) -> 25 | U2: =IF( AND($D$2=$O$2, $B$2=$N$2), COUNTIFS('בקרות להפחתת סיכון AWS (EN)'!W:W,"ארגוני",'בקרות להפחתת סיכון AWS (EN)'!A:A,"Yes"), IF( AND($D$2=$O$3, $B$2=$N$2), COUNTIFS('בקרות להפחתת סיכון AWS (HEB)'!W:W,"ארגוני",'בקרות להפחתת סיכון AWS (HEB)'!A:A,"Yes"), IF( AND($D$2=$O$2, $B$2=$N$3), COUNTIFS('בקרות להפחתת סיכון GCP (EN)'!W:W,"ארגוני",'בקרות להפחתת סיכון GCP (EN)'!A:A,"Yes"), IF( AND($D$2=$O$3, $B$2=$N$3), COUNTIFS('בקרות להפחתת סיכון GCP (HEB)'!W:W,"ארגוני",'בקרות להפחתת סיכון GCP (HEB)'!A:A,"Yes") ) ) ) ) -> 124 | V2: ארגוני
A3: IaaS | G3: =IF( AND($D$2=$O$2, $B$2=$N$2), COUNTIFS('בקרות להפחתת סיכון AWS (EN)'!$A:$A, "Yes", 'בקרות להפחתת סיכון AWS (EN)'!$E:$E, G1), IF( AND($D$2=$O$3, $B$2=$N$2), COUNTIFS('בקרות להפחתת סיכון AWS (HEB)'!$A:$A, "Yes", 'בקרות להפחתת סיכון AWS (HEB)'!$E:$E, G1), IF( AND($D$2=$O$2, $B$2=$N$3), COUNTIFS('בקרות להפחתת סיכון GCP (EN)'!$A:$A, "Yes", 'בקרות להפחתת סיכון GCP (EN)'!$E:$E, G1), IF( AND($D$2=$O$3, $B$2=$N$3), COUNTIFS('בקרות להפחתת סיכון GCP (HEB)'!$A:$A, "Yes", 'בקרות להפחתת סיכון GCP (HEB)'!$E:$E, G1) ) ) ) ) -> 20 | H3: =IF( AND($D$2=$O$2, $B$2=$N$2), COUNTIFS('בקרות להפחתת סיכון AWS (EN)'!$A:$A, "Yes", 'בקרות להפחתת סיכון AWS (EN)'!$E:$E, H1), IF( AND($D$2=$O$3, $B$2=$N$2), COUNTIFS('בקרות להפחתת סיכון AWS (HEB)'!$A:$A, "Yes", 'בקרות להפחתת סיכון AWS (HEB)'!$E:$E, H1), IF( AND($D$2=$O$2, $B$2=$N$3), COUNTIFS('בקרות להפחתת סיכון GCP (EN)'!$A:$A, "Yes", 'בקרות להפחתת סיכון GCP (EN)'!$E:$E, H1), IF( AND($D$2=$O$3, $B$2=$N$3), COUNTIFS('בקרות להפחתת סיכון GCP (HEB)'!$A:$A, "Yes", 'בקרות להפחתת סיכון GCP (HEB)'!$E:$E, H1) ) ) ) ) -> 47 | I3: =IF( AND($D$2=$O$2, $B$2=$N$2), COUNTIFS('בקרות להפחתת סיכון AWS (EN)'!$A:$A, "Yes", 'בקרות להפחתת סיכון AWS (EN)'!$E:$E, I1), IF( AND($D$2=$O$3, $B$2=$N$2), COUNTIFS('בקרות להפחתת סיכון AWS (HEB)'!$A:$A, "Yes", 'בקרות להפחתת סיכון AWS (HEB)'!$E:$E, I1), IF( AND($D$2=$O$2, $B$2=$N$3), COUNTIFS('בקרות להפחתת סיכון GCP (EN)'!$A:$A, "Yes", 'בקרות להפחתת סיכון GCP (EN)'!$E:$E, I1), IF( AND($D$2=$O$3, $B$2=$N$3), COUNTIFS('בקרות להפחתת סיכון GCP (HEB)'!$A:$A, "Yes", 'בקרות להפחתת סיכון GCP (HEB)'!$E:$E, I1) ) ) ) ) -> 132 | J3: =IF( AND($D$2=$O$2, $B$2=$N$2), COUNTIFS('בקרות להפחתת סיכון AWS (EN)'!$A:$A, "Yes", 'בקרות להפחתת סיכון AWS (EN)'!$E:$E, J1), IF( AND($D$2=$O$3, $B$2=$N$2), COUNTIFS('בקרות להפחתת סיכון AWS (HEB)'!$A:$A, "Yes", 'בקרות להפחתת סיכון AWS (HEB)'!$E:$E, J1), IF( AND($D$2=$O$2, $B$2=$N$3), COUNTIFS('בקרות להפחתת סיכון GCP (EN)'!$A:$A, "Yes", 'בקרות להפחתת סיכון GCP (EN)'!$E:$E, J1), IF( AND($D$2=$O$3, $B$2=$N$3), COUNTIFS('בקרות להפחתת סיכון GCP (HEB)'!$A:$A, "Yes", 'בקרות להפחתת סיכון GCP (HEB)'!$E:$E, J1) ) ) ) ) -> 12 | K3: =IF( AND($D$2=$O$2, $B$2=$N$2), COUNTIFS('בקרות להפחתת סיכון AWS (EN)'!$A:$A, "Yes", 'בקרות להפחתת סיכון AWS (EN)'!$E:$E, K1), IF( AND($D$2=$O$3, $B$2=$N$2), COUNTIFS('בקרות להפחתת סיכון AWS (HEB)'!$A:$A, "Yes", 'בקרות להפחתת סיכון AWS (HEB)'!$E:$E, K1), IF( AND($D$2=$O$2, $B$2=$N$3), COUNTIFS('בקרות להפחתת סיכון GCP (EN)'!$A:$A, "Yes", 'בקרות להפחתת סיכון GCP (EN)'!$E:$E, K1), IF( AND($D$2=$O$3, $B$2=$N$3), COUNTIFS('בקרות להפחתת סיכון GCP (HEB)'!$A:$A, "Yes", 'בקרות להפחתת סיכון GCP (HEB)'!$E:$E, K1) ) ) ) ) -> 7 | L3: Total | N3: GCP | O3: עברית - מקוצר | S3: =E2 -> 218 | T3: =E2 -> 218 | U3: =IF( AND($D$2=$O$2, $B$2=$N$2), COUNTIFS(#REF!,"מערכת",#REF!,"Yes"), IF( AND($D$2=$O$3, $B$2=$N$2), COUNTIFS(#REF!,"מערכת",#REF!,"Yes"), IF( AND($D$2=$O$2, $B$2=$N$3), COUNTIFS(#REF!,"מערכת",#REF!,"Yes"), IF( AND($D$2=$O$3, $B$2=$N$3), COUNTIFS(#REF!,"מערכת",#REF!,"Yes") ) ) ) ) -> #REF! | V3: מערכת
A4: PaaS | G4: =IF( AND($D$2=$O$2, $B$2=$N$2), COUNTIF('בקרות להפחתת סיכון AWS (EN)'!$E:$E,G1), IF( AND($D$2=$O$3, $B$2=$N$2), COUNTIF('בקרות להפחתת סיכון AWS (HEB)'!$E:$E, G1), IF( AND($D$2=$O$2, $B$2=$N$3), COUNTIF('בקרות להפחתת סיכון GCP (EN)'!$E:$E, G1), IF( AND($D$2=$O$3, $B$2=$N$3), COUNTIF('בקרות להפחתת סיכון GCP (HEB)'!$E:$E, G1) ) ) ) ) -> 21 | H4: =IF( AND($D$2=$O$2, $B$2=$N$2), COUNTIF('בקרות להפחתת סיכון AWS (EN)'!$E:$E,H1), IF( AND($D$2=$O$3, $B$2=$N$2), COUNTIF('בקרות להפחתת סיכון AWS (HEB)'!$E:$E, H1), IF( AND($D$2=$O$2, $B$2=$N$3), COUNTIF('בקרות להפחתת סיכון GCP (EN)'!$E:$E, H1), IF( AND($D$2=$O$3, $B$2=$N$3), COUNTIF('בקרות להפחתת סיכון GCP (HEB)'!$E:$E, H1) ) ) ) ) -> 49 | I4: =IF( AND($D$2=$O$2, $B$2=$N$2), COUNTIF('בקרות להפחתת סיכון AWS (EN)'!$E:$E,I1), IF( AND($D$2=$O$3, $B$2=$N$2), COUNTIF('בקרות להפחתת סיכון AWS (HEB)'!$E:$E, I1), IF( AND($D$2=$O$2, $B$2=$N$3), COUNTIF('בקרות להפחתת סיכון GCP (EN)'!$E:$E, I1), IF( AND($D$2=$O$3, $B$2=$N$3), COUNTIF('בקרות להפחתת סיכון GCP (HEB)'!$E:$E, I1) ) ) ) ) -> 139 | J4: =IF( AND($D$2=$O$2, $B$2=$N$2), COUNTIF('בקרות להפחתת סיכון AWS (EN)'!$E:$E,J1), IF( AND($D$2=$O$3, $B$2=$N$2), COUNTIF('בקרות להפחתת סיכון AWS (HEB)'!$E:$E, J1), IF( AND($D$2=$O$2, $B$2=$N$3), COUNTIF('בקרות להפחתת סיכון GCP (EN)'!$E:$E, J1), IF( AND($D$2=$O$3, $B$2=$N$3), COUNTIF('בקרות להפחתת סיכון GCP (HEB)'!$E:$E, J1) ) ) ) ) -> 12 | K4: =IF( AND($D$2=$O$2, $B$2=$N$2), COUNTIF('בקרות להפחתת סיכון AWS (EN)'!$E:$E,K1), IF( AND($D$2=$O$3, $B$2=$N$2), COUNTIF('בקרות להפחתת סיכון AWS (HEB)'!$E:$E, K1), IF( AND($D$2=$O$2, $B$2=$N$3), COUNTIF('בקרות להפחתת סיכון GCP (EN)'!$E:$E, K1), IF( AND($D$2=$O$3, $B$2=$N$3), COUNTIF('בקרות להפחתת סיכון GCP (HEB)'!$E:$E, K1) ) ) ) ) -> 7 | L4: Part | N4: אחר | O4: English - Full | S4: =S3-S2 -> 113 | T4: =T3-T2 -> 193 | U4: =E2 -> 218
A5: SaaS | G5: =G4-G3 -> 1 | H5: =H4-H3 -> 2 | I5: =I4-I3 -> 7 | J5: =J4-J3 -> 0 | K5: =K4-K3 -> 0 | L5: Didn’t | O5: עברית - מלא | S5: =S2/S3 -> 0.48165138 | T5: =T2/T3 -> 0.1146789 | U5: =U2/U4 -> 0.56880734
G6: =G3/G4 -> 0.95238095 | H6: =H3/H4 -> 0.95918367 | I6: =I3/I4 -> 0.94964029 | J6: =J3/J4 -> 1 | K6: =K3/K4 -> 1 | S6: =S4/S3 -> 0.51834862 | T6: =T4/T3 -> 0.8853211 | U6: =U3/U4 -> #REF!
G7: =G5/G4 -> 0.047619048 | H7: =H5/H4 -> 0.040816327 | I7: =I5/I4 -> 0.050359712 | J7: =J5/J4 -> 0 | K7: =K5/K4 -> 0 | S7: =S2 & "/" &S3 -> 105/218 | T7: =T2 & "/" &T3 -> 25/218 | U7: =U2 & "/" &U4 -> 124/218
S16: כמות בקרות C | T16: כמות בקרות I | U16: כמות בקרות A
R17: מופעל | S17: =IF( AND($D$2=$O$2, $B$2=$N$2), COUNTIFS('בקרות להפחתת סיכון AWS (EN)'!$A:$A, "Yes", 'בקרות להפחתת סיכון AWS (EN)'!$X:$X, "x"), IF( AND($D$2=$O$3, $B$2=$N$2), COUNTIFS('בקרות להפחתת סיכון AWS (HEB)'!$A:$A, "Yes", 'בקרות להפחתת סיכון AWS (HEB)'!$X:$X, "x"), IF( AND($D$2=$O$2, $B$2=$N$3), COUNTIFS('בקרות להפחתת סיכון GCP (EN)'!$A:$A, "Yes", 'בקרות להפחתת סיכון GCP (EN)'!$X:$X, "x"), IF( AND($D$2=$O$3, $B$2=$N$3), COUNTIFS('בקרות להפחתת סיכון GCP (HEB)'!$A:$A, "Yes", 'בקרות להפחתת סיכון GCP (HEB)'!$X:$X, "x") ) ) ) ) -> 213 | T17: =IF( AND($D$2=$O$2, $B$2=$N$2), COUNTIFS('בקרות להפחתת סיכון AWS (EN)'!$A:$A, "Yes", 'בקרות להפחתת סיכון AWS (EN)'!$Y:$Y, "x"), IF( AND($D$2=$O$3, $B$2=$N$2), COUNTIFS('בקרות להפחתת סיכון AWS (HEB)'!$A:$A, "Yes", 'בקרות להפחתת סיכון AWS (HEB)'!$Y:$Y, "x"), IF( AND($D$2=$O$2, $B$2=$N$3), COUNTIFS('בקרות להפחתת סיכון GCP (EN)'!$A:$A, "Yes", 'בקרות להפחתת סיכון GCP (EN)'!$Y:$Y, "x"), IF( AND($D$2=$O$3, $B$2=$N$3), COUNTIFS('בקרות להפחתת סיכון GCP (HEB)'!$A:$A, "Yes", 'בקרות להפחתת סיכון GCP (HEB)'!$Y:$Y, "x") ) ) ) ) -> 147 | U17: =IF( AND($D$2=$O$2, $B$2=$N$2), COUNTIFS('בקרות להפחתת סיכון AWS (EN)'!$A:$A, "Yes", 'בקרות להפחתת סיכון AWS (EN)'!$Z:$Z, "x"), IF( AND($D$2=$O$3, $B$2=$N$2), COUNTIFS('בקרות להפחתת סיכון AWS (HEB)'!$A:$A, "Yes", 'בקרות להפחתת סיכון AWS (HEB)'!$Z:$Z, "x"), IF( AND($D$2=$O$2, $B$2=$N$3), COUNTIFS('בקרות להפחתת סיכון GCP (EN)'!$A:$A, "Yes", 'בקרות להפחתת סיכון GCP (EN)'!$Z:$Z, "x"), IF( AND($D$2=$O$3, $B$2=$N$3), COUNTIFS('בקרות להפחתת סיכון GCP (HEB)'!$A:$A, "Yes", 'בקרות להפחתת סיכון GCP (HEB)'!$Z:$Z, "x") ) ) ) ) -> 128
R18: סה"כ | S18: =IF( $C$2 = $A$2, IF( AND($D$2 = $O$2, $B$2 = $N$2), COUNTIFS('בקרות להפחתת סיכון AWS (EN)'!X:X, "x"), IF( AND($D$2 = $O$3, $B$2 = $N$2), COUNTIFS('בקרות להפחתת סיכון AWS (HEB)'!X:X, "x"), IF( AND($D$2 = $O$2, $B$2 = $N$3), COUNTIFS('בקרות להפחתת סיכון GCP (EN)'!X:X, "x"), IF( AND($D$2 = $O$3, $B$2 = $N$3), COUNTIFS('בקרות להפחתת סיכון GCP (HEB)'!X:X, "x"), "nnn" ) ) ) ), IF( $C$2 = $A$3, IF( AND($D$2 = $O$2, $B$2 = $N$2), COUNTIFS('בקרות להפחתת סיכון AWS (EN)'!X:X, "x", 'בקרות להפחתת סיכון AWS (EN)'!$K:$K, "x"), IF( AND($D$2 = $O$3, $B$2 = $N$2), COUNTIFS('בקרות להפחתת סיכון AWS (HEB)'!X:X, "x", 'בקרות להפחתת סיכון AWS (HEB)'!$K:$K, "x"), IF( AND($D$2 = $O$2, $B$2 = $N$3), COUNTIFS('בקרות להפחתת סיכון GCP (EN)'!X:X, "x", 'בקרות להפחתת סיכון GCP (EN)'!$K:$K, "x"), IF( AND($D$2 = $O$3, $B$2 = $N$3), COUNTIFS('בקרות להפחתת סיכון GCP (HEB)'!X:X, "x", 'בקרות להפחתת סיכון GCP (HEB)'!$K:$K, "x"), "nnn" ) ) ) ), IF( $C$2 = $A$4, IF( AND($D$2 = $O$2, $B$2 = $N$2), COUNTIFS('בקרות להפחתת סיכון AWS (EN)'!X:X, "x", 'בקרות להפחתת סיכון AWS (EN)'!$L:$L, "x"), IF( AND($D$2 = $O$3, $B$2 = $N$2), COUNTIFS('בקרות להפחתת סיכון AWS (HEB)'!X:X, "x", 'בקרות להפחתת סיכון AWS (HEB)'!$L:$L, "x"), IF( AND($D$2 = $O$2, $B$2 = $N$3), COUNTIFS('בקרות להפחתת סיכון GCP (EN)'!X:X, "x", 'בקרות להפחתת סיכון GCP (EN)'!$L:$L, "x"), IF( AND($D$2 = $O$3, $B$2 = $N$3), COUNTIFS('בקרות להפחתת סיכון GCP (HEB)'!X:X, "x", 'בקרות להפחתת סיכון GCP (HEB)'!$L:$L, "x"), "nnn" ) ) ) ), IF( $C$2 = $A$5, IF( AND($D$2 = $O$2, $B$2 = $N$2), COUNTIFS('בקרות להפחתת סיכון AWS (EN)'!X:X, "x", 'בקרות להפחתת סיכון AWS (EN)'!$M:$M, "x"), IF( AND($D$2 = $O$3, $B$2 = $N$2), COUNTIFS('בקרות להפחתת סיכון AWS (HEB)'!X:X, "x", 'בקרות להפחתת סיכון AWS (HEB)'!$M:$M, "x"), IF( AND($D$2 = $O$2, $B$2 = $N$3), COUNTIFS('בקרות להפחתת סיכון GCP (EN)'!X:X, "x", 'בקרות להפחתת סיכון GCP (EN)'!$M:$M, "x"), IF( AND($D$2 = $O$3, $B$2 = $N$3), COUNTIFS('בקרות להפחתת סיכון GCP (HEB)'!X:X, "x", 'בקרות להפחתת סיכון GCP (HEB)'!$M:$M, "x"), "nnn" ) ) ) ), "nnn" ) ) ) ) -> 221 | T18: =IF( $C$2 = $A$2, IF( AND($D$2 = $O$2, $B$2 = $N$2), COUNTIFS('בקרות להפחתת סיכון AWS (EN)'!Y:Y, "x"), IF( AND($D$2 = $O$3, $B$2 = $N$2), COUNTIFS('בקרות להפחתת סיכון AWS (HEB)'!Y:Y, "x"), IF( AND($D$2 = $O$2, $B$2 = $N$3), COUNTIFS('בקרות להפחתת סיכון GCP (EN)'!Y:Y, "x"), IF( AND($D$2 = $O$3, $B$2 = $N$3), COUNTIFS('בקרות להפחתת סיכון GCP (HEB)'!Y:Y, "x"), "nnn" ) ) ) ), IF( $C$2 = $A$3, IF( AND($D$2 = $O$2, $B$2 = $N$2), COUNTIFS('בקרות להפחתת סיכון AWS (EN)'!Y:Y, "x", 'בקרות להפחתת סיכון AWS (EN)'!$K:$K, "x"), IF( AND($D$2 = $O$3, $B$2 = $N$2), COUNTIFS('בקרות להפחתת סיכון AWS (HEB)'!Y:Y, "x", 'בקרות להפחתת סיכון AWS (HEB)'!$K:$K, "x"), IF( AND($D$2 = $O$2, $B$2 = $N$3), COUNTIFS('בקרות להפחתת סיכון GCP (EN)'!Y:Y, "x", 'בקרות להפחתת סיכון GCP (EN)'!$K:$K, "x"), IF( AND($D$2 = $O$3, $B$2 = $N$3), COUNTIFS('בקרות להפחתת סיכון GCP (HEB)'!Y:Y, "x", 'בקרות להפחתת סיכון GCP (HEB)'!$K:$K, "x"), "nnn" ) ) ) ), IF( $C$2 = $A$4, IF( AND($D$2 = $O$2, $B$2 = $N$2), COUNTIFS('בקרות להפחתת סיכון AWS (EN)'!Y:Y, "x", 'בקרות להפחתת סיכון AWS (EN)'!$L:$L, "x"), IF( AND($D$2 = $O$3, $B$2 = $N$2), COUNTIFS('בקרות להפחתת סיכון AWS (HEB)'!Y:Y, "x", 'בקרות להפחתת סיכון AWS (HEB)'!$L:$L, "x"), IF( AND($D$2 = $O$2, $B$2 = $N$3), COUNTIFS('בקרות להפחתת סיכון GCP (EN)'!Y:Y, "x", 'בקרות להפחתת סיכון GCP (EN)'!$L:$L, "x"), IF( AND($D$2 = $O$3, $B$2 = $N$3), COUNTIFS('בקרות להפחתת סיכון GCP (HEB)'!Y:Y, "x", 'בקרות להפחתת סיכון GCP (HEB)'!$L:$L, "x"), "nnn" ) ) ) ), IF( $C$2 = $A$5, IF( AND($D$2 = $O$2, $B$2 = $N$2), COUNTIFS('בקרות להפחתת סיכון AWS (EN)'!Y:Y, "x", 'בקרות להפחתת סיכון AWS (EN)'!$M:$M, "x"), IF( AND($D$2 = $O$3, $B$2 = $N$2), COUNTIFS('בקרות להפחתת סיכון AWS (HEB)'!Y:Y, "x", 'בקרות להפחתת סיכון AWS (HEB)'!$M:$M, "x"), IF( AND($D$2 = $O$2, $B$2 = $N$3), COUNTIFS('בקרות להפחתת סיכון GCP (EN)'!Y:Y, "x", 'בקרות להפחתת סיכון GCP (EN)'!$M:$M, "x"), IF( AND($D$2 = $O$3, $B$2 = $N$3), COUNTIFS('בקרות להפחתת סיכון GCP (HEB)'!Y:Y, "x", 'בקרות להפחתת סיכון GCP (HEB)'!$M:$M, "x"), "nnn" ) ) ) ), "nnn" ) ) ) ) -> 155 | U18: =IF( $C$2 = $A$2, IF( AND($D$2 = $O$2, $B$2 = $N$2), COUNTIFS('בקרות להפחתת סיכון AWS (EN)'!Z:Z, "x"), IF( AND($D$2 = $O$3, $B$2 = $N$2), COUNTIFS('בקרות להפחתת סיכון AWS (HEB)'!Z:Z, "x"), IF( AND($D$2 = $O$2, $B$2 = $N$3), COUNTIFS('בקרות להפחתת סיכון GCP (EN)'!Z:Z, "x"), IF( AND($D$2 = $O$3, $B$2 = $N$3), COUNTIFS('בקרות להפחתת סיכון GCP (HEB)'!Z:Z, "x"), "nnn" ) ) ) ), IF( $C$2 = $A$3, IF( AND($D$2 = $O$2, $B$2 = $N$2), COUNTIFS('בקרות להפחתת סיכון AWS (EN)'!Z:Z, "x", 'בקרות להפחתת סיכון AWS (EN)'!$K:$K, "x"), IF( AND($D$2 = $O$3, $B$2 = $N$2), COUNTIFS('בקרות להפחתת סיכון AWS (HEB)'!Z:Z, "x", 'בקרות להפחתת סיכון AWS (HEB)'!$K:$K, "x"), IF( AND($D$2 = $O$2, $B$2 = $N$3), COUNTIFS('בקרות להפחתת סיכון GCP (EN)'!Z:Z, "x", 'בקרות להפחתת סיכון GCP (EN)'!$K:$K, "x"), IF( AND($D$2 = $O$3, $B$2 = $N$3), COUNTIFS('בקרות להפחתת סיכון GCP (HEB)'!Z:Z, "x", 'בקרות להפחתת סיכון GCP (HEB)'!$K:$K, "x"), "nnn" ) ) ) ), IF( $C$2 = $A$4, IF( AND($D$2 = $O$2, $B$2 = $N$2), COUNTIFS('בקרות להפחתת סיכון AWS (EN)'!Z:Z, "x", 'בקרות להפחתת סיכון AWS (EN)'!$L:$L, "x"), IF( AND($D$2 = $O$3, $B$2 = $N$2), COUNTIFS('בקרות להפחתת סיכון AWS (HEB)'!Z:Z, "x", 'בקרות להפחתת סיכון AWS (HEB)'!$L:$L, "x"), IF( AND($D$2 = $O$2, $B$2 = $N$3), COUNTIFS('בקרות להפחתת סיכון GCP (EN)'!Z:Z, "x", 'בקרות להפחתת סיכון GCP (EN)'!$L:$L, "x"), IF( AND($D$2 = $O$3, $B$2 = $N$3), COUNTIFS('בקרות להפחתת סיכון GCP (HEB)'!Z:Z, "x", 'בקרות להפחתת סיכון GCP (HEB)'!$L:$L, "x"), "nnn" ) ) ) ), IF( $C$2 = $A$5, IF( AND($D$2 = $O$2, $B$2 = $N$2), COUNTIFS('בקרות להפחתת סיכון AWS (EN)'!Z:Z, "x", 'בקרות להפחתת סיכון AWS (EN)'!$M:$M, "x"), IF( AND($D$2 = $O$3, $B$2 = $N$2), COUNTIFS('בקרות להפחתת סיכון AWS (HEB)'!Z:Z, "x", 'בקרות להפחתת סיכון AWS (HEB)'!$M:$M, "x"), IF( AND($D$2 = $O$2, $B$2 = $N$3), COUNTIFS('בקרות להפחתת סיכון GCP (EN)'!Z:Z, "x", 'בקרות להפחתת סיכון GCP (EN)'!$M:$M, "x"), IF( AND($D$2 = $O$3, $B$2 = $N$3), COUNTIFS('בקרות להפחתת סיכון GCP (HEB)'!Z:Z, "x", 'בקרות להפחתת סיכון GCP (HEB)'!$M:$M, "x"), "nnn" ) ) ) ), "nnn" ) ) ) ) -> 128
R19: לא מופעל | S19: =S18-S17 -> 8 | T19: =T18-T17 -> 8 | U19: =U18-U17 -> 0
S20: =S17/S18 -> 0.9638009 | T20: =T17/T18 -> 0.9483871 | U20: =U17/U18 -> 1
A22: אזהרה!!! | S22: 54 | T22: 46 | U22: 51 | V22: הכי נמוך
A23: שינוי מילים או מיקומי שדות ועדכון נוסחאות ישפיעו על תוצאות המחשבון
A24: נבנה על ידי אבא אקילוב

Sheet חישוב תמק
A1: דומיין | B1: ציון | C1: ציון מקסימלי | D1: אחוז אי העמידה בתקן | E1: משקל | H1: M4 | I1: M3 | J1: M2 | K1: M1 | L1: upper | M1: lower | N1: blank | O1: סיכון | P1: דומיין
A2: כשירות ארגונית | B2: =SUM('כשירות ארגונית (1)'!F5:F21) -> 8 | C2: =SUM('כשירות ארגונית (1)'!G5:G21) -> 23 | D2: =E13 -> 0.48205128 | E2: 1 | H2: 0.02 | I2: 0.05 | J2: 0.02 | K2: 0.05 | L2: 0.15 | M2: 0.2 | N2: =1-O2 -> 0.25 | O2: =_xlfn.NUMBERVALUE(E5) -> 0.75 | P2: סף רגישות כולל
A3: פרופיל מערכת | B3: =SUM('פרופיל מערכת (2)'!F5:F52) -> 140 | C3: =SUM('פרופיל מערכת (2)'!G5:G52) -> 241 | D3: =E21 -> 0.69792904 | E3: 10 | H3: 0.02 | I3: 0.05 | J3: 0.02 | K3: 0.05 | L3: 0.15 | M3: 0.2 | N3: =1-O3 -> 0.51794872 | O3: =D2 -> 0.48205128 | P3: כשירות ארגונית
A4: שרשרת אספקה | B4: =SUM('שרשרת אספקה (3)'!F5:F37) -> 37 | C4: =SUM('שרשרת אספקה (3)'!G5:G37) -> 103 | D4: =E27 -> 0.36519194 | E4: 1 | H4: 0.02 | I4: 0.05 | J4: 0.02 | K4: 0.05 | L4: 0.15 | M4: 0.2 | N4: =1-O4 -> 0.30207096 | O4: =D3 -> 0.69792904 | P4: פרופיל מערכת
E5: =IF(ISBLANK('כללי (0)'!C13),"75%",IF(OR('סיווג אופי מידע במערכת (4)'!D6="שמור אדום",'סיווג אופי מידע במערכת (4)'!D6="סודי"),"100%",SUMPRODUCT(D2:D4,E2:E4)/SUM(E2:E4))) -> 75% | F5: סה"כ | H5: 0.02 | I5: 0.05 | J5: 0.02 | K5: 0.05 | L5: 0.15 | M5: 0.2 | N5: =1-O5 -> 0.63480806 | O5: =D4 -> 0.36519194 | P5: שרשרת אספקה
E6: 1
A7: כשירות ארגונית | B7: ציון | C7: ציון מקסימלי | D7: אחוז אי העמידה בתקן | E7: משקל | K7: =IF(OR(O2>=70%,O3>=70%,O4>=70%,O5>=70%),"על סמך ניתוח המערכת הנך נדרש לפנות למנחה לבחינת ההיתכנות להעלאת המערכת לענן","על סמך ניתוח המערכת הנך נדרש לעדכן את המחנה בתוצאות הבחינה ולהמשיך בתהליך במודל רגולציה עצמית") -> על סמך ניתוח המערכת הנך נדרש לפנות למנחה לבחינת ההיתכנות להעלאת המערכת לענן
A8: אסטרטגיה | B8: =SUM('כשירות ארגונית (1)'!F5:F6) -> 1 | C8: =SUM('כשירות ארגונית (1)'!G5:G6) -> 3 | D8: =B8/C8 -> 0.33333333 | E8: 1
A9: ניהול סיכונים | B9: =SUM('כשירות ארגונית (1)'!F9:F10) -> 1 | C9: =SUM('כשירות ארגונית (1)'!G9:G10) -> 13 | D9: =B9/C9 -> 0.076923077 | E9: 1
A10: משאבי כ"א בתחום הענן | B10: =SUM('כשירות ארגונית (1)'!F13:F13) -> 1 | C10: =SUM('כשירות ארגונית (1)'!G13:G13) -> 1 | D10: =B10/C10 -> 1 | E10: 1
A11: ניהול פיננסי | B11: =SUM('כשירות ארגונית (1)'!F16:F17) -> 5 | C11: =SUM('כשירות ארגונית (1)'!G16:G17) -> 5 | D11: =B11/C11 -> 1 | E11: 1
A12: מדיניות, שיטות, נהלים ותהליכים | B12: =SUM('כשירות ארגונית (1)'!F20:F20) -> 0 | C12: =SUM('כשירות ארגונית (1)'!G20:G20) -> 1 | D12: =B12/C12 -> 0 | E12: 1
E13: =SUMPRODUCT(D8:D12,E8:E12)/SUM(E8:E12) -> 0.48205128 | F13: סה"כ
A15: פרופיל מערכת | B15: ציון | C15: ציון מקסימלי | D15: אחוז אי העמידה בתקן | E15: משקל
A16: מאפייני מידע | B16: =SUM('פרופיל מערכת (2)'!F5:F12) -> 28 | C16: =SUM('פרופיל מערכת (2)'!G5:G12) -> 45 | D16: =B16/C16 -> 0.62222222 | E16: 1
A17: מאפייני מערכת | B17: =SUM('פרופיל מערכת (2)'!F15:F23) -> 102 | C17: =SUM('פרופיל מערכת (2)'!G15:G23) -> 131 | D17: =B17/C17 -> 0.77862595 | E17: 20
A18: משתמשים והזדהות | B18: =SUM('פרופיל מערכת (2)'!F26:F34) -> 6 | C18: =SUM('פרופיל מערכת (2)'!G26:G34) -> 27 | D18: =B18/C18 -> 0.22222222 | E18: 1
A19: ממשקים | B19: =SUM('פרופיל מערכת (2)'!F37:F43) -> 0 | C19: =SUM('פרופיל מערכת (2)'!G37:G43) -> 26 | D19: =B19/C19 -> 0 | E19: 1
A20: אופן היישום בענן | B20: =SUM('פרופיל מערכת (2)'!F46:F52) -> 4 | C20: =SUM('פרופיל מערכת (2)'!G46:G52) -> 12 | D20: =B20/C20 -> 0.33333333 | E20: 1
E21: =SUMPRODUCT(D16:D20,E16:E20)/SUM(E16:E20) -> 0.69792904 | F21: סה"כ
A23: שרשרת אספקה | B23: ציון | C23: ציון מקסימלי | D23: אחוז אי העמידה בתקן | E23: משקל
A24: מאפייני הספקים | B24: =SUM('שרשרת אספקה (3)'!F5:F11) -> 2 | C24: =SUM('שרשרת אספקה (3)'!G5:G11) -> 9 | D24: =B24/C24 -> 0.22222222 | E24: 1
A25: ספק א' | B25: =SUM('שרשרת אספקה (3)'!F15:F24) -> 20 | C25: =SUM('שרשרת אספקה (3)'!G15:G24) -> 47 | D25: =B25/C25 -> 0.42553191 | E25: 10
A26: ספק ב' | B26: =SUM('שרשרת אספקה (3)'!F28:F37) -> 15 | C26: =SUM('שרשרת אספקה (3)'!G28:G37) -> 47 | D26: =B26/C26 -> 0.31914894 | E26: 10
E27: =SUMPRODUCT(D24:D26,E24:E26)/SUM(E24:E26) -> 0.36519194 | F27: סה"כ

Sheet שרשרת אספקה (3)
C3: מאפייני הספקים
D4: תשובה | F4: ציון | G4: ציון מקסימלי | H4: תשובה 1 | I4: תשובה 2 | J4: תשובה 3 | K4: תשובה 4
B5: מאפייני הספקים | C5: האם הארגון משתמש באינטגרטור מוסמך על ידי הספק להקמת המערכת? | D5: כן | F5: =IF(D5=H5,0,IF(D5=I5,1,"ERROR")) -> 0 | G5: 1 | H5: כן | I5: לא
C6: האם הספקים רשומים במאגר הספקים וחברות שרשרת האספקה "מערכת יובל" | D6: כן | F6: =IF(D6=H6,0,IF(D6=I6,1,"ERROR")) -> 0 | G6: 1 | H6: כן | I6: לא
C7: האם קיים אינטגרטור אשר מנהל בפועל את השימוש הענן? | D7: לא | F7: =IF(D7=H7,0,IF(D7=I7,1,"ERROR")) -> 0 | G7: 1 | H7: לא | I7: כן
C8: האם יש לספקים ביטוח סייבר אשר כולל בין היתר שיפוי לנזקים עבור צד ג' | D8: לא | F8: =IF(D8=H8,0,IF(D8=I8,1,"ERROR")) -> 1 | G8: 1 | H8: כן | I8: לא
C9: האם הספקים עברו תהליכי בדיקות מהימנות לספק ולעובדים בפרויקט? | D9: כן | F9: =IF(D9=H9,0,IF(D9=I9,1,"ERROR")) -> 0 | G9: 1 | H9: כן | I9: לא
C10: האם הספקים עומדים בהסמכות ISO 27K | D10: לא | F10: =IF(D10=H10,0,IF(D10=I10,1,"ERROR")) -> 1 | G10: 1 | H10: כן | I10: לא
C11: מספר הספקים בפרויקט | D11: ספק אחד | F11: =IF(D11=H11,0,IF(D11=I11,1,IF(D11=J11,2,IF(D11=K11,3,"ERROR")))) -> 0 | G11: 3 | H11: ספק אחד | I11: שני ספקים | J11: שלושה ספקים | K11: 4 ומעלה
B13: ספק א' | D13: תשובה
B14: ספק א' | C14: שם הספק
C15: האם מוגדר כספק מהותי | D15: לא | F15: =IF(D15=H15,0,IF(D15=I15,1,"ERROR")) -> 1 | G15: 1 | H15: כן | I15: לא
C16: האם הספק רשום במאגר הספקים וחברות שרשרת האספקה "מערכת יובל" | D16: כן | F16: =IF(D16=H16,0,IF(D16=I16,1,"ERROR")) -> 0 | G16: 1 | H16: כן | I16: לא
C17: תפקיד הספק | D17: אינטגרציה | F17: =IF(D17=H17,0,IF(D17=I17,1,IF(D17=J17,2,IF(D17=K17,3,"ERROR")))) -> 3 | G17: 3 | H17: ייעוץ | I17: פיתוח | J17: הקמה | K17: אינטגרציה
C18: תלות בספק | D18: תלות נמוכה | F18: =IF(D18=H18,0,IF(D18=I18,1,IF(D18=J18,2,IF(D18=K18,3,"ERROR")))) -> 1 | G18: 3 | H18: ללא תלות | I18: תלות נמוכה | J18: תלות בינונית | K18: תלות גבוהה
C19: רמת הנזק הצפוי לאגון מהספק | D19: בינוני | F19: =IF(D19=H19,0,IF(D19=I19,1,IF(D19=J19,5,IF(D19=K19,10,"ERROR")))) -> 5 | G19: 10 | H19: ללא נזק | I19: נמוך | J19: בינוני | K19: גבוהה
C20: נזק כלכלי לארגון כתוצאה מפגיעה בספק | D20: עשרות אלפי שקלים | F20: =IF(D20=H20,0,IF(D20=I20,1,IF(D20=J20,2,IF(D20=K20,3,"ERROR")))) -> 1 | G20: 3 | H20: ללא נזק | I20: עשרות אלפי שקלים | J20: מאות אלפי שקלים | K20: מעל מליון
C21: מידת הפגיעה ברציפות העסקית מפגיעה בספק | D21: התאוששות מאירוע אצל הספק תיקח מספר ימים | F21: =IF(D21=H21,0,IF(D21=I21,1,IF(D21=J21,5,IF(D21=K21,10,"ERROR")))) -> 5 | G21: 10 | H21: ללא נזק | I21: התאוששות מאירוע אצל הספק תיקח מספר שעות | J21: התאוששות מאירוע אצל הספק תיקח מספר ימים | K21: התאוששות מאירוע אצל הספק תיקח מספר שבועות
C22: רמת רגישות המידע הנגיש לספק | D22: מידע בעל רגישות נמוכה | F22: =IF(D22=H22,0,IF(D22=I22,1,IF(D22=J22,2,IF(D22=K22,3,"ERROR")))) -> 1 | G22: 3 | H22: ללא מידע | I22: מידע בעל רגישות נמוכה | J22: מידע בעל רגישות בינונית | K22: מידע בעל רגישות עסקית כגון פטנטים וסודות מסחריים
C23: סבירות להתממשות אירוע כתוצאה מההתקשרות | D23: תלות נמוכה בסייבר | F23: =IF(D23=H23,0,IF(D23=I23,1,IF(D23=J23,5,IF(D23=K23,10,"ERROR")))) -> 1 | G23: 10 | H23: ללא תלות | I23: תלות נמוכה בסייבר | J23: תלות בינונית בסייבר בהתקשרות עם הספק | K23: ספק בעל תלות גבוהה בסייבר
C24: האם הוגדר SLA עם הספק לטיפול בפערי אבטחת מידע | D24: הוגדר טיפול של עד 30 יום | F24: =IF(D24=H24,0,IF(D24=I24,1,IF(D24=J24,2,IF(D24=K24,3,"ERROR")))) -> 2 | G24: 3 | H24: טיפול מיידי | I24: הוגדר טיפול תוך תוך שעות עד ימים בודדים | J24: הוגדר טיפול של עד 30 יום | K24: הוגדר Best Effort
B26: ספק ב' | D26: תשובה
B27: ספק ב' | C27: שם הספק
C28: האם מוגדר כספק מהותי | D28: לא | F28: =IF(D28=H28,0,IF(D28=I28,1,"ERROR")) -> 1 | G28: 1 | H28: כן | I28: לא
C29: האם הספק רשום במאגר הספקים וחברות שרשרת האספקה "מערכת יובל" | D29: לא | F29: =IF(D29=H29,0,IF(D29=I29,1,"ERROR")) -> 1 | G29: 1 | H29: כן | I29: לא
C30: תפקיד הספק | D30: פיתוח | F30: =IF(D30=H30,0,IF(D30=I30,1,IF(D30=J30,2,IF(D30=K30,3,"ERROR")))) -> 1 | G30: 3 | H30: ייעוץ | I30: פיתוח | J30: הקמה | K30: אינטגרציה
C31: תלות בספק | D31: תלות נמוכה | F31: =IF(D31=H31,0,IF(D31=I31,1,IF(D31=J31,2,IF(D31=K31,3,"ERROR")))) -> 1 | G31: 3 | H31: ללא תלות | I31: תלות נמוכה | J31: תלות בינונית | K31: תלות גבוהה
C32: רמת הנזק הצפוי לאגון מהספק | D32: נמוך | F32: =IF(D32=H32,0,IF(D32=I32,1,IF(D32=J32,5,IF(D32=K32,10,"ERROR")))) -> 1 | G32: 10 | H32: ללא נזק | I32: נמוך | J32: בינוני | K32: גבוהה
C33: נזק כלכלי לארגון כתוצאה מפגיעה בספק | D33: מאות אלפי שקלים | F33: =IF(D33=H33,0,IF(D33=I33,1,IF(D33=J33,2,IF(D33=K33,3,"ERROR")))) -> 2 | G33: 3 | H33: ללא נזק | I33: עשרות אלפי שקלים | J33: מאות אלפי שקלים | K33: מעל מליון
C34: מידת הפגיעה ברציפות העסקית מפגיעה בספק | D34: ללא נזק | F34: =IF(D34=H34,0,IF(D34=I34,1,IF(D34=J34,5,IF(D34=K34,10,"ERROR")))) -> 0 | G34: 10 | H34: ללא נזק | I34: התאוששות מאירוע אצל הספק תיקח מספר שעות | J34: התאוששות מאירוע אצל הספק תיקח מספר ימים | K34: התאוששות מאירוע אצל הספק תיקח מספר שבועות
C35: רמת רגישות המידע הנגיש לספק | D35: מידע בעל רגישות נמוכה | F35: =IF(D35=H35,0,IF(D35=I35,1,IF(D35=J35,2,IF(D35=K35,3,"ERROR")))) -> 1 | G35: 3 | H35: ללא מידע | I35: מידע בעל רגישות נמוכה | J35: מידע בעל רגישות בינונית | K35: מידע בעל רגישות עסקית כגון פטנטים וסודות מסחריים
C36: סבירות להתממשות אירוע כתוצאה מההתקשרות | D36: תלות בינונית בסייבר בהתקשרות עם הספק | F36: =IF(D36=H36,0,IF(D36=I36,1,IF(D36=J36,5,IF(D36=K36,10,"ERROR")))) -> 5 | G36: 10 | H36: ללא תלות | I36: תלות נמוכה בסייבר | J36: תלות בינונית בסייבר בהתקשרות עם הספק | K36: ספק בעל תלות גבוהה בסייבר
C37: האם הוגדר SLA עם הספק לטיפול בפערי אבטחת מידע | D37: הוגדר טיפול של עד 30 יום | F37: =IF(D37=H37,0,IF(D37=I37,1,IF(D37=J37,2,IF(D37=K37,3,"ERROR")))) -> 2 | G37: 3 | H37: טיפול מיידי | I37: הוגדר טיפול תוך תוך שעות עד ימים בודדים | J37: הוגדר טיפול של עד 30 יום | K37: הוגדר Best Effort

Sheet סיווג אופי מידע במערכת (4)
C5: הערכת סיווג ואופי המידע | D5: תשובה
A6: Q4.1 | B6: פומביות המידע | C6: סיווג המידע במערכת | D6: בלמס
A7: Q4.2 | C7: האם קיימת מניעה משפטית (חוק, תקנה או דרישה רגולטורית) להנגשת המידע לציבור? | D7: כן
A9: Q4.3 | B9: פרטיות המידע | C9: האם הנתונים מכילים מידע פרטי (כולל מזהים ישירים/עקיפים) כהגדרתו במסמך זה? | D9: כן
A10: Q4.4 | C10: האם הנתונים מכילים מידע פרטי בעל רגישות מיוחדת כהגדרתו במסמך זה? | D10: לא
A11: Q4.5 | C11: האם המידע נוגע לעניינים פנימיים של הגוף המונחה? | D11: לא
A13: Q4.6 | B13: השפעת חשיפה או פגיעה במידע/במערכת על התנהלות הגוף המונחה או הציבור | C13: חשיפת מידע אסטרטגי לישויות מדיניות זרות (מדינות, רשויות או ארגונים בינ"ל) | D13: לא
A14: Q4.7 | C14: השפעה על הציבור או המשק או פגיעה בהם, הטיה או מתן יתרון תחרותי בלתי הוגן. | D14: לא
A15: Q4.8 | C15: פוטנציאל לפגיעה בגוף או בנפש או פגיעה כלכלית בהתאם לתבחיני תמ"ק ? | D15: לא
A16: Q4.9 | C16: פוטנציאל פגיעה באופן רוחבי\ נרחב במספר גופים | D16: לא
C17: ↘ ↙
B18: תוצאת סיווג ואופי המידע
B19: ='חישובים ונתונים'!B12 -> בלמס - מידע פנימי
B21: הגדרות הסיווג הביטחוני
B22: סיווג המידע | C22: סיווג המידע | D22: רמה
B23: מידע בלמ"ס | C23: מידע, אשר אם יגיעו לידי גורם שאיננו מוסמך לכך, לא ייגרם נזק ביטחוני | D23: 1
B24: שמור צהוב | C24: מידע, אשר אם יגיעו לידי גורם שאיננו מוסמך לכך, עלול לסייע בפגוע בביטחון מדינת ישראל | D24: 2
B25: שמור אדום | C25: בהתאם להגדרות התו"ל | D25: 3
B26: סודי | C26: בהתאם להגדרות התו"ל | D26: 4
B28: הגדרות סיווג אופי המידע במערכת (בסיווג בלמ"ס)
B29: אופי המידע | C29: אופי המידע | D29: רמה
B30: מידע פומבי | C30: מידע שפורסם באופן חוקי לציבור או מידע המותר לפרסום לכלל הציבור על פי דין | D30: 1
B31: מידע פנימי | C31: מידע הנוגע לענייניה הפנימיים של הגוף המונחה, המיועד לשימוש פנימי בארגון או בין מספר משרדים, שאין לפרסמו לכלל הציבור ואינו מכיל מידע פרטי. | D31: 2
B32: מידע פנימי מוגבל | C32: מידע המיועד לשימוש פנימי בארגון אשר חלות עליו הגבלות על פי חוק (לדוגמה, סודיות מסחרית), תקנות (לדוגמה, תקנות חובת המכרזים) רגולציה ייעודית או הסכם או מידע פרטי שאינו מידע בעל רגישות מיוחדת. | D32: 3
B33: מידע פנימי חסוי | C33: מידע פרטי בעל רגישות מיוחדת או מידע שהחוק או התקנות או רגולציה או הארגון קבעו שהסיווג עבורו גבוה במיוחד. | D33: 4

Sheet הערכת נזק פוטנציאלי למערכת (5)
B4: הגדרות חומרת הנזק הפוטנציאלי למערכת ולמידע
B5: חומרת הנזק | C5: אופי הנזק הפוטנציאלי | J5: רמת הנזק
B6: נזק מינמלי | C6: מערכת ומידע שחשיפתם או פגיעה בהם תגרום נזק מינימלי | J6: 1
B7: נזק מוגבל | C7: מערכת ומידע שלחשיפתם או לפגיעה בהם עשויה להיות השפעה שלילית מוגבלת על תפקוד הארגון או תדמיתו | J7: 2
B8: נזק בינוני | C8: מערכת ומידע שחשיפתם או הפגיעה בהם תגרום להשפעה שלילית גבוהה לארגון או לממשלה | J8: 3
B9: נזק חמור | C9: מערכת ומידע שחשיפתם או הפגיעה בהם תגרום לנזק חמור במיוחד לציבור או לאינטרס הלאומי | J9: 4
B12: הערכת הנזק הפוטנציאלי בהיבטי חסיון, אמינות וזמינות המידע והמערכת
B13: ההערכה תתבצע ע"פ מקרא הגדרות הנזק הפוטנציאלי מטה
C14: פגיעה בתקציב הארגון | D14: נזק לתדמית הארגון בעיני הציבור | E14: פגיעה בייעדי רציפות התפקודית | F14: פגיעה בייעדי מתן שירות לציבור \ ללקוחות | G14: חשיפה משפטית/ רגולטורית / משילות | H14: נכס מידע תשתיתי רוחבי | I14: פגיעה בביטחון/ בטיחות/ שלום הציבור או עובדי הארגון | J14: סיכום מידת הנזק המקסימאלית
A15: Q3.1 | B15: חסיון (חשיפת המידע או המערכת) Confidentiality | C15: מינימלית | D15: מינימלי | E15: מוגבלת | F15: מוגבלת | G15: מינימלית | H15: מוגבלות | I15: מינימלית | J15: ='חישובים ונתונים'!S42 -> מוגבלת
A16: Q3.2 | B16: אמינות (שלמות המידע או מערכת) Integrity | C16: מינימלית | D16: מינימלי | E16: מוגבלת | F16: מינימלית | G16: מינימלית | H16: מוגבלות | I16: מינימלית | J16: ='חישובים ונתונים'!S43 -> מוגבלת
A17: Q3.3 | B17: זמינות (מידע או מערכת) Availability | C17: מינימלית | D17: מינימלי | E17: מינימלית | F17: מינימלית | G17: מינימלית | H17: מינימליות | I17: בינונית | J17: ='חישובים ונתונים'!S44 -> בינונית
B18: הערות (במידה ויש)
F19: ↘ ↙
B21: תוצאת הנזק הפוטנציאלי מפגיעה במערכת ובמידע
B22: ='חישובים ונתונים'!D39 -> מידת הנזק הפוטנציאלי הצפוי למשרד הוא - נזק בינוני
B25: מקרא הגדרות הנזק הפוטנציאלי
B26: קריטריון | C26: פגיעה כלכלית בארגון | D26: נזק לתדמית הארגון בעיני הציבור | E26: פגיעה בייעדי רציפות התפקודית | F26: פגיעה בייעדי מתן שירות לציבור \ ללקוחות | G26: חשיפה משפטית/ רגולטורית / משילות | H26: נכס מידע תשתיתי רוחבי | I26: פגיעה בביטחון/ בטיחות/ שלום הציבור או עובדי הארגון
B27: נזק מינימלי | C27: ללא פגיעה כלכלית בארגון | D27: ללא נזק תדמיתי או חשיפה תקשורתית נמוכה | E27: ללא פגיעה ברציפות התפקודית | F27: ללא פגיעה במתן שירות לציבור או הללקוחות / לא רלוונטי | G27: ללא חשיפה משפטית | H27: ללא השפעה | I27: ללא פגיעה
B28: נזק מוגבל | C28: פגיעה של עד 0.5% מהתקציב התפעולי השנתי של הארגון או המשרד הממשלתי | D28: כיסוי תקשורתי שלילי של כלי התקשורת איזוטריים | E28: פגיעה מצומצמת ברציפות התפקודית תוך עמידה ביעדים | F28: פגיעה נקודתית במתן שירות לציבור / ללקחות תוך עמידה ביעדים | G28: חשיפה נמוכה מאוד לתביעות משפטיות | H28: השפעה על נכס מידע תשתיתי לא אסטרטגי בודד | I28: פגיעה נקודתית
B29: נזק בינוני | C29: פגיעה מצומצמת עד 2% מהתקציב התפעולי השנתי של הארגון או המשרד הממשלתי | D29: כיסוי תקשורתי שלילי נרחב ברמה הלאומית בעל השלכות המצריכות תקשור לציבור | E29: פגיעה נמוכה ביעדי הרציפות התפקודית | F29: פגיעה נרחבת במתן שירותים לציבור / ללקוחות תוך עמידה ביעדים | G29: חשיפה נמוכה לתביעות משפטיות | H29: השפעה על מספר נכסים לא אסטרטגיים או על נכס אסטרטגי בודד | I29: פגיעה נרחבת בודדת או מספר פגיעות נקודתיות
B30: נזק חמור | C30: פגיעה משמעותית של מעל 2% מהתקציב התפעולי השנתי של הארגון או המשרד הממשלתי | D30: כיסוי תקשורתי שלילי משמעותי ברמה בינלאומית עד כדי עצירת פעילות הארגון (יתכן והאירוע מצריך מתן הסברים ובירורים על ידי גורמי רגולציה חיצוניים) | E30: פגיעה חמורה וממושכת ביעדי הרציפות התפקודית | F30: פגיעה נרחבת במתן שירותים לציבור / ללקוחות לתקופת זמן ממושכת וחריגה מייעדי השירות | G30: חשיפה משפטית לקובלנה פלילית, אפשרות לעצירת פעילות הארגון או המשרד הממשלתי | H30: השפעה על מספר נכסים אסטרטגיים עד כדי הפסקת פעילות הארגון או המשרד הממשלתי | I30: מספר פגיעות נרחבות

Sheet מערכות הגנה (6)
C4: מערכות הגנה | D4: תשובה | E4: שם המערכת
B5: הגנת רשת | C5: האם תוטמע מערכת חומת אש Firewall (כולל IDS\IPS) | D5: לא | E5: אין FW/IDS/IPS ייעודי — הגנת רשת ברובד ה-Edge של ספק הענן
C6: האם תוטמע מערכת חומת אש אפליקטיבית Web Application Firwall (WAF) | D6: כן | E6: Vercel Firewall / Attack Challenge Mode (אומת בפועל: x-vercel-mitigated: challenge)
C7: האם תוטמע מערכת אבטחת ממשקים (API Gateway) | D7: לא | E7: ממשקי API ממומשים כ-Route Handlers של Next.js עם אימות והרשאות בצד השרת
C8: האם תוטמע מערכת האצת תוכן (CDN) | D8: כן | E8: Vercel Edge Network (CDN)
C9: האם תוטמע מערכת אבטחת אינטרנט של דברים (IOT) | D9: לא | E9: אין רכיבי IoT במערכת
B11: אבטחת מידע | C11: האם תוטמע מערכת לזיהוי מידע רגיש (Discovery And Classification) | D11: לא | E11: -
C12: האם תוטמע מערכת למניעת איבוד מידע (DLP) | D12: לא | E12: -
C13: האם תוטמע מערכת אבטחת בסיסי נתונים | D13: כן | E13: Neon PostgreSQL — TLS בתעבורה, הצפנה במנוחה, בידוד רשת והרשאות
C14: האם תוטמע מערכת לשמירה על פרטיות מידע (Data Privecy) | D14: לא | E14: -
B17: פוגענים ונוזקות | C17: האם תוטמע מערכת לזיהוי ושיקום מתקדמת XDR | D17: לא | E17: -
C18: האם תוטמע מערכת הלבנת קבצים (CDR + Sandbox) | D18: לא | E18: פער מזוהה — נדרש CDR/Sandbox להעלאת קבצים (GIS / מפות מדידה) לפני ייצור
B20: הגנת סביבת ענן | C20: האם תוטמע מערכת אבטחת צופן ייעודית (HSM) | D20: לא | E20: -
C21: האם תוטמע מערכת ניהול בקרת תצורת אבטחת ענן (CSPM) | D21: לא | E21: -
C22: מערכת ניהול מפתחות וסודות (KMS) | D22: כן | E22: ניהול סודות במשתני סביבה של Vercel ומפתחות מנוהלים בענן (Neon)
C23: האם תוטמע מערכת הגנה על סביבת עבודה בענן (CWPP) | D23: לא | E23: -
B25: ניטור ותגובה | C25: האם תוטמע מערכת ניהול התראות אבטחה מרכזית (SIEM) | D25: לא | E25: פער מזוהה — נדרש חיבור לניטור SIEM/SOC ארגוני לפני ייצור
C26: האם תוטמע מערכת גילוי משטחת תקיפה חיצוני (EASM) | D26: לא | E26: -
C27: האם תוטמע מערכת ציד מודיעין עסקי (Threat Intelligence) | D27: לא | E27: -
C28: האם תוטמע מערכת תגובה לאירועים באופן אוטומטי (SOAR) | D28: לא | E28: -
B30: ניהול זהויות | C30: האם תוטמע מערכת ניהול זהויות מרכזית (IDP) | D30: לא | E30: כיום הזדהות מקומית ל-CMS (סיסמה בגיבוב SHA-256, עוגייה חתומה). מתוכנן: SSO ארגוני
C31: מערכת ניטור הרשאות ענן (CIEM) | D31: לא | E31: -
C32: האם תוטמע מערכת סוכן אבטחה של גישה לענן (CASB) | D32: לא | E32: -
B34: הגנת סביבות פיתוח | C34: האם תוטמע מערכת זיכוי קוד פיתוח בשלב הפיתוח ההטמעה CICD (בסגנון Snyk, jfrog) | D34: כן | E34: בדיקת אבטחה אוטומטית בצנרת: npm audit ו-npm run security:check (סריקת סודות וכותרות אבטחה)
C35: האם תוטמע מערכת ניהול חשיפות תוכנה (Automated patch management) | D35: כן | E35: עדכוני תלויות ו-npm audit, כולל overrides לחסימת גרסאות פגיעות
C36: האם תוטמע מערכת ניהול אבטחת קונטיינרים | D36: לא | E36: אין קונטיינרים — ארכיטקטורת Serverless

Sheet ארכיטקטורה מלאה (7)
B4: ארכיטקטורה
C5: תרשים זרימה תהליכי
C6: נא לצרף טופולוגית ענן + ON PREM (כולל ממשקים)
B22: תרשים זרימה תהליכי
C24: נא לצרף תרשים זרימה תהליכי

Sheet פרופיל בקרות דרוש (8)
D2: תצורת ענן מבוקשת | E2: ='פרופיל מערכת (2)'!D50 -> IaaS
D3: ספק הענן | E3: =IF('פרופיל מערכת (2)'!D49="AWS","AWS",IF('פרופיל מערכת (2)'!D49="GCP","GCP","AWS")) -> GCP
D4: תצוגה | E4: עברית - מקוצר
B9: {=IF( AND(E4=חישובים!O2, E3=חישובים!N2), IF( INDEX(AWS[], SMALL(IF((AWS[Column1]=חישובים!$Q$1)+(AWS[Column1]=חישובים!$Q$2), ROW(AWS[Column1])-MIN(ROW(AWS[Column1]))+1, ""), ROW(INDIRECT("1:"&COUNTIF(AWS[Column1],חישובים!$Q$1)+COUNTIF(AWS[Column1],חישובים!$Q$2)))), {3,4,5,6,27,2,23,21}) = 0, "", INDEX(AWS[], SMALL(IF((AWS[Column1]=חישובים!$Q$1)+(AWS[Column1]=חישובים!$Q$2), ROW(AWS[Column1])-MIN(ROW(AWS[Column1]))+1, ""), ROW(INDIRECT("1:"&COUNTIF(AWS[Column1],חישובים!$Q$1)+COUNTIF(AWS[Column1],חישובים!$Q$2)))), {3,4,5,6,27,2,23,21}) ), IF( AND(E4=חישובים!O3, E3=חישובים!N2), IF( INDEX(AWS_2[], SMALL(IF((AWS_2[Column1]=חישובים!$Q$1)+(AWS_2[Column1]=חישובים!$Q$2), ROW(AWS_2[Column1])-MIN(ROW(AWS_2[Column1]))+1, ""), ROW(INDIRECT("1:"&COUNTIF(AWS_2[Column1],חישובים!$Q$1)+COUNTIF(AWS_2[Column1],חישובים!$Q$2)))), {3,4,5,6,27,2,23,21}) = 0, "", INDEX(AWS_2[], SMALL(IF((AWS_2[Column1]=חישובים!$Q$1)+(AWS_2[Column1]=חישובים!$Q$2), ROW(AWS_2[Column1])-MIN(ROW(AWS_2[Column1]))+1, ""), ROW(INDIRECT("1:"&COUNTIF(AWS_2[Column1],חישובים!$Q$1)+COUNTIF(AWS_2[Column1],חישובים!$Q$2)))), {3,4,5,6,27,2,23,21}) ), IF( AND(E4=חישובים!O2, E3=חישובים!N3), IF( INDEX(GCP[], SMALL(IF((GCP[Column1]=חישובים!$Q$1)+(GCP[Column1]=חישובים!$Q$2), ROW(GCP[Column1])-MIN(ROW(GCP[Column1]))+1, ""), ROW(INDIRECT("1:"&COUNTIF(GCP[Column1],חישובים!$Q$1)+COUNTIF(GCP[Column1],חישובים!$Q$2)))), {3,4,5,6,27,2,23,21}) = 0, "", INDEX(GCP[], SMALL(IF((GCP[Column1]=חישובים!$Q$1)+(GCP[Column1]=חישובים!$Q$2), ROW(GCP[Column1])-MIN(ROW(GCP[Column1]))+1, ""), ROW(INDIRECT("1:"&COUNTIF(GCP[Column1],חישובים!$Q$1)+COUNTIF(GCP[Column1],חישובים!$Q$2)))), {3,4,5,6,27,2,23,21}) ), IF( AND(E4=חישובים!O3, E3=חישובים!N3), IF( INDEX(GCP_2[], SMALL(IF((GCP_2[Column1]=חישובים!$Q$1)+(GCP_2[Column1]=חישובים!$Q$2), ROW(GCP_2[Column1])-MIN(ROW(GCP_2[Column1]))+1, ""), ROW(INDIRECT("1:"&COUNTIF(GCP_2[Column1],חישובים!$Q$1)+COUNTIF(GCP_2[Column1],חישובים!$Q$2)))), {3,4,5,6,27,2,23,21}) = 0, "", INDEX(GCP_2[], SMALL(IF((GCP_2[Column1]=חישובים!$Q$1)+(GCP_2[Column1]=חישובים!$Q$2), ROW(GCP_2[Column1])-MIN(ROW(GCP_2[Column1]))+1, ""), ROW(INDIRECT("1:"&COUNTIF(GCP_2[Column1],חישובים!$Q$1)+COUNTIF(GCP_2[Column1],חישובים!$Q$2)))), {3,4,5,6,27,2,23,21}) ), "Error" ) ) ) )} -> מספר בקרה ב CIS | C9: סוג הנכס | D9: סוג בקרת אבטחה | E9: תיאור | F9: בקרת ספק מומלצת | G9: מספר בקרה ספק ענן CIS | H9: סוג הבקרה | I9: מתקבל כברירת מחדל באזור הנחיתה הממשלתי
B10: - | C10: - | D10: - | E10: מיפוי ובקרה על נכסים ארגוניים | F10: - | G10: - | H10: - | I10: .
B11: 1.1 | C11: Devices | D11: Identify | E11: הקמה ותחזוקה של מיפוי נכסים ארגוניים מפורטים | F11: v | G11: 2.13 | H11: מערכת | I11: -
B12: 1.2 | C12: Devices | D12: Respond | E12: התייחס לנכסים לא מורשים | G12: - | H12: ארגוני | I12: -
B13: 1.3 | C13: Devices | D13: Detect | E13: השתמשו בכלי גילוי אקטיביים | G13: - | H13: ארגוני | I13: -
B14: 1.4 | C14: Devices | D14: Identify | E14: השתמש ברישום-Dynamic Host Configuration Protocol (DHCP) כדי לעדכן את מיפוי הנכסים הארגוניים | G14: - | H14: ארגוני | I14: -
B15: 1.5 | C15: Devices | D15: Detect | E15: השתמש בכלי גילוי נכסים פסיבי | G15: - | H15: ארגוני | I15: -
B16: - | C16: - | D16: - | E16: מיפוי ובקרת נכסי תוכנה | F16: - | G16: - | H16: - | I16: -
B17: 2.1 | C17: Applications | D17: Identify | E17: הקמה ותחזוקה של מיפוי תוכנה | G17: - | H17: ארגוני | I17: -
B18: 2.2 | C18: Applications | D18: Identify | E18: ודא כי התוכנה המורשית בארגון נתמכת על ידי היצרן | F18: v | G18: 4.12 | H18: מערכת | I18: -
B19: 2.3 | C19: Applications | D19: Respond | E19: קיים תוכנית לטיפול ברכיבי תוכנה לא מאושרים | G19: - | H19: ארגוני | I19: -
B20: 2.4 | C20: Applications | D20: Detect | E20: השתמש בכלי מיפוי תוכנה אוטומטיים | G20: - | H20: ארגוני | I20: -
B21: 2.5 | C21: Applications | D21: Protect | E21: ניהול רשימת תוכנות מאושרות | G21: - | H21: ארגוני | I21: -
B22: 2.6 | C22: Applications | D22: Protect | E22: ניהול רשימת ספריות קוד מאושרות | G22: - | H22: מערכת | I22: -
B23: 2.7 | C23: Applications | D23: Protect | E23: ניהול רשימת קטעי קוד וסקריפטים מאושרים | F23: v | G23: 6.3.1 | H23: מערכת | I23: -
A24: {=IFERROR(INDEX(#REF!, MATCH("Yes",#REF!, 0),0),"")} | B24: - | C24: - | D24: - | E24: הגנת מידע | F24: - | G24: - | H24: - | I24: -
A25: {=IFERROR(INDEX(#REF!, MATCH("Yes",#REF!, 0),0),"")} | B25: 3.1 | C25: Data | D25: Identify | E25: נדרש להקין ולתחזוק תהליך ניהול אבטחת מידע | G25: - | H25: מערכת | I25: -
B26: 3.2 | C26: Data | D26: Identify | E26: הקמה ותחזוקה של מיפוי נתונים | G26: - | H26: ארגוני | I26: -
B27: 3.3 | C27: Data | D27: Protect | E27: הגדר בקרת גישה לנתונים | F27: v | G27: 1.6 | H27: ארגוני | I27: v
B28: 3.3 | C28: Data | D28: Protect | E28: הגדר בקרת גישה לנתונים | F28: v | G28: 1.8 | H28: מערכת | I28: -
B29: 3.3 | C29: Data | D29: Protect | E29: הגדר בקרת גישה לנתונים | F29: v | G29: 1.9 | H29: מערכת | I29: -
B30: 3.3 | C30: Data | D30: Protect | E30: הגדר בקרת גישה לנתונים | F30: v | G30: 1.11 | H30: מערכת | I30: -
B31: 3.3 | C31: Data | D31: Protect | E31: הגדר בקרת גישה לנתונים | F31: v | G31: 2.3 | H31: מערכת | I31: -
B32: 3.3 | C32: Data | D32: Protect | E32: הגדר בקרת גישה לנתונים | F32: v | G32: 2.15 | H32: מערכת | I32: -
B33: 3.3 | C33: Data | D33: Protect | E33: הגדר בקרת גישה לנתונים | F33: v | G33: 4.9 | H33: ארגוני | I33: v
B34: 3.3 | C34: Data | D34: Protect | E34: הגדר בקרת גישה לנתונים | F34: v | G34: 5.1 | H34: ארגוני | I34: v
B35: 3.3 | C35: Data | D35: Protect | E35: הגדר בקרת גישה לנתונים | F35: v | G35: 5.2 | H35: ארגוני | I35: v
B36: 3.3 | C36: Data | D36: Protect | E36: הגדר בקרת גישה לנתונים | F36: v | G36: 6.1.2 | H36: מערכת | I36: -
B37: 3.3 | C37: Data | D37: Protect | E37: הגדר בקרת גישה לנתונים | F37: v | G37: 6.3.2 | H37: מערכת | I37: -
B38: 3.3 | C38: Data | D38: Protect | E38: הגדר בקרת גישה לנתונים | F38: v | G38: 6.3.7 | H38: מערכת | I38: -
... B41: 3.3 | C41: Data | D41: Protect | E41: הגדר בקרת גישה לנתונים | F41: v | G41: 7.1 | H41: מערכת | I41: v
B42: 3.4 | C42: Data | D42: Protect | E42: יש להגדיר אכיפת Data Ritention | G42: - | H42: ארגוני | I42: -
B43: 3.5 | C43: Data | D43: Protect | E43: יש לוודא השמדת מידע מאובטחת בסיום תקופת ה Ritention | G43: - | H43: ארגוני | I43: -
B44: 3.7 | C44: Data | D44: Identify | E44: הקמה ותחזוקה של תוכנית סיווג נתונים | G44: - | H44: ארגוני | I44: -
B45: 3.8 | C45: Data | D45: Identify | E45: הגדרת אופן זרימת נתונים | G45: - | H45: ארגוני | I45: -
B46: 3.1 | C46: Data | D46: Protect | E46: הצפנת נתונים רגישים בתנועה | F46: v | G46: 3.9 | H46: ארגוני | I46: v
B47: 3.1 | C47: Data | D47: Protect | E47: הצפנת נתונים רגישים בתנועה | F47: v | G47: 4.3 | H47: מערכת | I47: -
B48: 3.1 | C48: Data | D48: Protect | E48: הצפנת נתונים רגישים בתנועה | F48: v | G48: 4.10 | H48: מערכת | I48: -
B49: 3.1 | C49: Data | D49: Protect | E49: הצפנת נתונים רגישים בתנועה | F49: v | G49: 6.4 | H49: מערכת | I49: -
B50: 3.11 | C50: Data | D50: Protect | E50: הצפנת נתונים רגישים במנוחה | F50: v | G50: 1.10 | H50: מערכת | I50: -
B51: 3.11 | C51: Data | D51: Protect | E51: הצפנת נתונים רגישים במנוחה | F51: v | G51: 1.17 | H51: מערכת | I51: -
B52: 3.11 | C52: Data | D52: Protect | E52: הצפנת נתונים רגישים במנוחה | F52: v | G52: 1.18 | H52: מערכת | I52: -
B53: 3.11 | C53: Data | D53: Protect | E53: הצפנת נתונים רגישים במנוחה | F53: v | G53: 4.7 | H53: מערכת | I53: -
B54: 3.11 | C54: Data | D54: Protect | E54: הצפנת נתונים רגישים במנוחה | F54: v | G54: 4.11 | H54: מערכת | I54: -
B55: 3.11 | C55: Data | D55: Protect | E55: הצפנת נתונים רגישים במנוחה | F55: v | G55: 7.2 | H55: מערכת | I55: -
B56: 3.11 | C56: Data | D56: Protect | E56: הצפנת נתונים רגישים במנוחה | F56: v | G56: 7.3 | H56: מערכת | I56: -
B57: 3.11 | C57: Data | D57: Protect | E57: הצפנת נתונים רגישים במנוחה | F57: v | G57: 1.7 | H57: מערכת | I57: -
B58: 3.12 | C58: Network | D58: Protect | E58: פלח עיבוד נתונים ואחסון בהתבסס על רגישות המידע | G58: - | H58: ארגוני | I58: -
B59: - | C59: - | D59: - | E59: תצורה מאובטחת של נכסים ותוכנה ארגוניים | F59: - | G59: - | H59: - | I59: -
B60: 4.1 | C60: Applications | D60: Protect | E60: הקמה ותחזוקה של תהליך תצורה מאובטח | F60: v | G60: 6.3.3 | H60: מערכת | I60: -
B61: 4.1 | C61: Applications | D61: Protect | E61: הקמה ותחזוקה של תהליך תצורה מאובטח | F61: v | G61: 6.3.4 | H61: מערכת | I61: -
B62: 4.1 | C62: Applications | D62: Protect | E62: הקמה ותחזוקה של תהליך תצורה מאובטח | F62: v | G62: 6.3.6 | H62: מערכת | I62: -
B63: 4.2 | C63: Network | D63: Protect | E63: הקמה ותחזוקה של תהליך תצורה מאובטח עבור תשתית רשת | F63: v | G63: 3.1 | H63: ארגוני | I63: v
B64: 4.2 | C64: Network | D64: Protect | E64: הקמה ותחזוקה של תהליך תצורה מאובטח עבור תשתית רשת | F64: v | G64: 3.2 | H64: מערכת | I64: -
B65: 4.2 | C65: Network | D65: Protect | E65: הקמה ותחזוקה של תהליך תצורה מאובטח עבור תשתית רשת | F65: v | G65: 3.3 | H65: מערכת | I65: -
B66: 4.2 | C66: Network | D66: Protect | E66: הקמה ותחזוקה של תהליך תצורה מאובטח עבור תשתית רשת | F66: v | G66: 3.5 | H66: מערכת | I66: -
B67: 4.2 | C67: Network | D67: Protect | E67: הקמה ותחזוקה של תהליך תצורה מאובטח עבור תשתית רשת | F67: v | G67: 3.4 | H67: מערכת | I67: -
B68: 4.3 | C68: Users | D68: Protect | E68: הגדר נעילת אוטומטית בהתחברות לנכסים ארגוניים | G68: - | H68: מערכת | I68: -
B69: 4.4 | C69: Devices | D69: Protect | E69: יש להתמיע מערכת חומת אש ולנהל אותה | F69: v | G69: 3.6 | H69: מערכת | I69: v
B70: 4.4 | C70: Devices | D70: Protect | E70: יש להתמיע מערכת חומת אש ולנהל אותה | F70: v | G70: 3.7 | H70: ארגוני | I70: v
B71: 4.4 | C71: Devices | D71: Protect | E71: יש להתמיע מערכת חומת אש ולנהל אותה | F71: v | G71: 4.6 | H71: מערכת | I71: -
B72: 4.5 | C72: Devices | D72: Protect | E72: יישום וניהול חומת אש עבור שרתים ומשתמש קצה | F72: v | G72: 3.6 | H72: ארגוני | I72: -
B73: 4.5 | C73: Devices | D73: Protect | E73: יישום וניהול חומת אש עבור שרתים ומשתמש קצה | F73: v | G73: 3.7 | H73: ארגוני | I73: -
B74: 4.5 | C74: Devices | D74: Protect | E74: יישום וניהול חומת אש עבור שרתים ומשתמש קצה | F74: v | G74: 4.6 | H74: מערכת | I74: -
B75: 4.6 | C75: Network | D75: Protect | E75: ניהול מאובטח של נכסים ותוכנה ארגוניים | F75: v | G75: 6.2.9 | H75: מערכת | I75: v
B76: 4.7 | C76: Users | D76: Protect | E76: נהל חשבונות ברירת מחדל בנכסים ותוכנה ארגוניים | F76: v | G76: 4.1 | H76: מערכת | I76: v
B77: 4.7 | C77: Users | D77: Protect | E77: נהל חשבונות ברירת מחדל בנכסים ותוכנה ארגוניים | F77: v | G77: 4.2 | H77: מערכת | I77: v
B78: 4.7 | C78: Users | D78: Protect | E78: נהל חשבונות ברירת מחדל בנכסים ותוכנה ארגוניים | F78: v | G78: 6.1.1 | H78: מערכת | I78: -
B79: 4.8 | C79: Devices | D79: Protect | E79: הסר או השבת שירותים מיותרים בנכסים ותוכנות ארגוניות | F79: v | G79: 4.5 | H79: מערכת | I79: v
B80: 4.8 | C80: Devices | D80: Protect | E80: הסר או השבת שירותים מיותרים בנכסים ותוכנות ארגוניות | F80: v | G80: 6.3.5 | H80: מערכת | I80: -
B81: 4.9 | C81: Devices | D81: Protect | E81: הגדר שרתי DNS מהימנים בנכסי ארגונים | G81: - | H81: מערכת | I81: -
B82: 4.1 | C82: Devices | D82: Respond | E82: יש להגדיר אכיפה של נעילת מכשיר אוטומטית על מכשירי משתמש קצה ניידים | G82: - | H82: מערכת | I82: -
B83: 4.11 | C83: Devices | D83: Protect | E83: אכיפת יכולת מחיקה מרחוק במכשירי משתמש קצה ניידים | G83: - | H83: מערכת | I83: -
B84: 4.12 | C84: Devices | D84: Protect | E84: הפרד סביבות עבודה ארגוניות במכשירי משתמש קצה ניידים | G84: - | H84: מערכת | I84: -
B85: - | C85: - | D85: - | E85: ניהול חשבון | F85: - | G85: - | H85: - | I85: -
B86: 5.1 | C86: Users | D86: Identify | E86: הקמה ותחזוקה של מיפוי חשבונות וזהויות | G86: - | H86: ארגוני | I86: -
B87: 5.2 | C87: Users | D87: Protect | E87: השתמש בסיסמאות ייחודיות | F87: v | G87: 4.3 | H87: ארגוני | I87: -
B88: 5.3 | C88: Users | D88: Respond | E88: השבת חשבונות רדומים | G88: - | H88: ארגוני | I88: -
B89: 5.4 | C89: Users | D89: Protect | E89: הגבל את הרשאות מנהל לחשבונות מנהל ייעודיים | F89: v | G89: 1.5 | H89: ארגוני | I89: -
B90: 5.5 | C90: Users | D90: Identify | E90: הקמה ותחזוקה של מיפוי של חשבונות שירות | G90: - | H90: ארגוני | I90: -
B91: 5.6 | C91: Users | D91: Protect | E91: הגדר ניהול מרכזי לחשבונות וזהויות עבור הארגון | F91: v | G91: 1.1 | H91: ארגוני | I91: -
B92: 5.6 | C92: Users | D92: Protect | E92: הגדר ניהול מרכזי לחשבונות וזהויות עבור הארגון | F92: v | G92: 3.10 | H92: ארגוני | I92: -
B93: 5.6 | C93: Users | D93: Protect | E93: הגדר ניהול מרכזי לחשבונות וזהויות עבור הארגון | F93: v | G93: 4.4 | H93: ארגוני | I93: v
B94: 5.6 | C94: Users | D94: Protect | E94: הגדר ניהול מרכזי לחשבונות וזהויות עבור הארגון | F94: v | G94: 1.4 | H94: ארגוני | I94: v
B95: - | C95: - | D95: - | E95: ניהול בקרת גישה | F95: - | G95: - | H95: - | I95: -
B96: 6.1 | C96: Users | D96: Protect | E96: הקמת תהליך הענקת גישה | G96: - | H96: ארגוני | I96: -
B97: 6.2 | C97: Users | D97: Protect | E97: קבע תהליך ביטול גישה | G97: - | H97: ארגוני | I97: -
B98: 6.3 | C98: Users | D98: Protect | E98: דרוש MFA עבור יישומים חשופים חיצונית | F98: v | G98: 1.2 | H98: ארגוני | I98: v
B99: 6.3 | C99: Users | D99: Protect | E99: דרוש MFA עבור יישומים חשופים חיצונית | F99: v | G99: 1.3 | H99: מערכת | I99: -
B100: 6.4 | C100: Users | D100: Protect | E100: דרוש MFA עבור גישה מרחוק לרשת | G100: - | H100: ארגוני | I100: -
B101: 6.5 | C101: Users | D101: Protect | E101: דרוש MFA עבור גישה מנהלתית | G101: - | H101: ארגוני | I101: -
B102: 6.6 | C102: Users | D102: Identify | E102: הקמה ותחזוקה של מיפוי של מערכות אימות והרשאה | F102: v | G102: 2.13 | H102: מערכת | I102: -
B103: 6.7 | C103: Users | D103: Protect | E103: הגדר בקרת גישה מרכזת בארגון | F103: v | G103: 4.4 | H103: ארגוני | I103: v
B104: 6.8 | C104: Data | D104: Protect | E104: הגדר ותחזק בקרת גישה מבוססת תפקידים RBAC | G104: - | H104: ארגוני | I104: -
B105: - | C105: - | D105: - | E105: ניהול פגיעות מתמשך | F105: - | G105: - | H105: - | I105: -
B106: 7.1 | C106: Applications | D106: Protect | E106: Establish and Maintain a Vulnerability Management Process | G106: - | H106: ארגוני | I106: -
B107: 7.2 | C107: Applications | D107: Respond | E107: Establish and Maintain a Remediation Process | G107: - | H107: ארגוני | I107: -
...

Sheet חישובים ונתונים
C1: אזהרה!!! שינוי מילים או מיקומי שדות ועדכון נוסחאות ישפיעו על תוצאות המחשבון נבנה על ידי אבא אקילוב | XFD1: נבנה על ידי אבא אקילוב
D9: {=IF($D$13="כן","מידע מסווג ביטחוני אינו חלק מסיווג זה", IF(OR($D$13=0,$D$14=0,$D$16=0,$D$17=0,$D$18=0,$D$20=0,$D$21=0,$D$22=0,$D$23=0),"נא להשלים הזנה של מאפייני מידע", IF(AND(OR($D$14="כן", $D$18="כן"),$D$13="לא",$D$16="לא",$D$17="לא",$D$20="לא",$D$21="לא",$D$22="לא",$D$23="לא"),"מידע פנימי", IF(AND(OR($D$20="כן",$D$21="כן",$D$22="כן",$D$23="כן",$D$17="כן"),$D$13="לא",$D$14="כן"),"מידע פנימי חסוי", IF(AND($D$13="לא",$D$14="לא",$D$16="לא",$D$17="לא",$D$18="לא",$D$20="לא",$D$21="לא",$D$22="לא",$D$23="לא"),"מידע פומבי", IF(AND($D$13="לא",$D$14="כן",$D$17="לא",$D$16="כן",$D$20="לא",$D$21="לא",$D$22="לא",$D$23="לא"),"מידע פנימי מוגבל", IF(OR(AND($D$13="לא",$D$14="כן",$D$18="כן",$D$16:$D$18="לא",$D$20:$D$23="לא"),AND($D$13="לא",$D$14="כן",$D$18="לא",$D$16:$D$18="לא",$D$20:$D$23="לא")),"מידע פנימי","קיימת סתירה בהגדרות אופי המידע")))))))} -> קיימת סתירה בהגדרות אופי המידע
E11: רמת המידע | F11: רמת נזק
B12: {=IF(OR($D$13="שמור אדום",$D$13="סודי"),"נדרש אישור מנחה", IF(AND($D$13="שמור צהוב",$D$14="לא"),"קיימת אי התאמה בין סיווג המידע לפומביות המידע", IF(OR($D$13=0,$D$14=0,$D$16=0,$D$17=0,$D$18=0,$D$20=0,$D$21=0,$D$22=0,$D$23=0),"נא להשלים הזנה של מאפייני מידע", IF(AND(OR($D$14="כן",$D$18="כן"),OR($D$13="בלמס",$D$13="שמור צהוב"),$D$16="לא",$D$17="לא",$D$20="לא",$D$21="לא",$D$22="לא",$D$23="לא"),D13&" - "&"מידע פנימי", IF(AND(OR($D$20="כן",$D$21="כן",$D$22="כן",$D$23="כן",$D$17="כן"),OR($D$13="בלמס",$D$13="שמור צהוב")),D13&" - "&"מידע פנימי חסוי", IF(AND(OR($D$13="בלמס",$D$13="שמור צהוב"),$D$14="לא",$D$16="לא",$D$17="לא",$D$18="לא",$D$20="לא",$D$21="לא",$D$22="לא",$D$23="לא"),D13&" - "&"מידע פומבי", IF(AND(OR($D$13="בלמס",$D$13="שמור צהוב"),$D$14="כן",$D$17="לא",$D$16="כן",$D$20="לא",$D$21="לא",$D$22="לא",$D$23="לא"),D13&" - "&"מידע פנימי מוגבל", IF(OR(AND(OR($D$13="בלמס",$D$13="שמור צהוב"),$D$14="כן",$D$18="כן",$D$16:$D$18="לא",$D$20:$D$23="לא"),AND($D$13="לא",$D$14="כן",$D$18="לא",$D$16:$D$18="לא",$D$20:$D$23="לא")),D13&" - "&"מידע פנימי", IF(AND(OR($D$16="כן",$D$17="כן"),$D$14="לא"),"על סמך המידע שהוזן קיימת מניעה משפטית בפרסום המידע בציבור אנא בדקו את שאלה 2", "קיימת סתירה בהגדרות אופי המידע")))))))))} -> בלמס - מידע פנימי | E12: =VLOOKUP(B12,G12:H18,2,FALSE) -> 2 | F12: =R45 -> 3 | G12: =D13&" - "&"מידע פומבי" -> בלמס - מידע פומבי | H12: 1 | K12: מינימלית | L12: 1 | M12: מינימלית
C13: האם המידע בסיווג בטחוני גבוה מבלמ"ס? | D13: ='סיווג אופי מידע במערכת (4)'!$D$6 -> בלמס | G13: =D13&" - "&"מידע פנימי" -> בלמס - מידע פנימי | H13: 2 | K13: מוגבלת | L13: 2 | M13: מוגבלת
C14: האם קיימת מניעה משפטית (חסיון על פי דין, חוק, תקנה או דרישה רגולטורית) להנגשת המידע לציבור? | D14: ='סיווג אופי מידע במערכת (4)'!$D$7 -> כן | G14: =D13&" - "&"מידע פנימי מוגבל" -> בלמס - מידע פנימי מוגבל | H14: 3 | K14: בינונית | L14: 3 | M14: בינונית
D15: ='סיווג אופי מידע במערכת (4)'!$D$8 -> 0 | G15: =D13&" - "&"מידע פנימי חסוי" -> בלמס - מידע פנימי חסוי | H15: 4 | K15: חמורה | L15: 4 | M15: חמורה
C16: האם הנתונים מכילים מידע פרטי (כולל מזהים ישירים\עקיפים) כהגדרתו במסמך זה? | D16: ='סיווג אופי מידע במערכת (4)'!$D$9 -> לא | G16: לא הוזנו מאפייני מידע | H16: 0
C17: האם הנתונים מכילים מידע פרטי בעל רגישות מיוחדת כהגדרתו במסמך זה? | D17: ='סיווג אופי מידע במערכת (4)'!$D$10 -> לא | G17: מידע מסווג ביטחוני אינו חלק מסיווג זה | H17: 0 | K17: מינימלי | L17: 1 | M17: מינימלי
C18: האם המידע נוגע לעניינים פנימיים של המשרד? | D18: ='סיווג אופי מידע במערכת (4)'!$D$11 -> לא | G18: קיימת סתירה בהגדרות אופי המידע | H18: 0 | K18: מוגבל | L18: 2 | M18: מוגבל
D19: ='סיווג אופי מידע במערכת (4)'!$D$12 -> 0 | K19: בינוני | L19: 3 | M19: בינוני
C20: חשיפת מידע אסטרטגי לישויות מדיניות זרות (מדינות, רשויות או ארגונים בינ"ל) | D20: ='סיווג אופי מידע במערכת (4)'!$D$13 -> לא | F20: חישוב רמת הנזק | K20: חמור | L20: 4 | M20: חמור
C21: ההשפעה או פגיעה על הציבור, המשק, הטיה או מתן יתרון תחרותי | D21: ='סיווג אופי מידע במערכת (4)'!$D$14 -> לא | G21: =IF('חישובים ונתונים'!E12=0,"אנא השלם את הפרטים בשלבים הקודמים",IF(AND('חישובים ונתונים'!E12=1,F12=1),1,IF(AND('חישובים ונתונים'!E12=1,F12=2),2,IF(AND('חישובים ונתונים'!E12=1,F12=3),3,IF(AND('חישובים ונתונים'!E12=1,F12=4),4,IF(AND('חישובים ונתונים'!E12=2,F12=1),2,IF(AND('חישובים ונתונים'!E12=2,F12=2),2,IF(AND('חישובים ונתונים'!E12=2,F12=3),3,IF(AND('חישובים ונתונים'!E12=2,F12=4),4,IF(AND('חישובים ונתונים'!E12=3,F12=1),3,IF(AND('חישובים ונתונים'!E12=3,F12=2),3,IF(AND('חישובים ונתונים'!E12=3,F12=3),3,IF(AND('חישובים ונתונים'!E12=3,F12=4),4,IF(AND('חישובים ונתונים'!E12=4,F12=1),4,IF(AND('חישובים ונתונים'!E12=4,F12=2),4,IF(AND('חישובים ונתונים'!E12=4,F12=3),4,IF(AND('חישובים ונתונים'!E12=4,F12=4),4))))))))))))))))) -> 3 | I21: =G21 -> 3
C22: פוטנציאל לפגיעה בגוף או בנפש | D22: ='סיווג אופי מידע במערכת (4)'!$D$15 -> לא | K22: מינימליות | L22: 1
C23: פוטנציאל לפגיעה ביחסי החוץ של המדינה | D23: ='סיווג אופי מידע במערכת (4)'!$D$16 -> לא | F23: חישוב הנזק השיורי | K23: מוגבלות | L23: 2
G24: =IF('חישובים ונתונים'!E12=0, "אנא השלם את הפרטים בשלבים הקודמים", IF(AND('חישובים ונתונים'!E12=1, F12=1), 1, IF(AND('חישובים ונתונים'!E12=1, F12=2), 1, IF(AND('חישובים ונתונים'!E12=1, F12=3), 2, IF(AND('חישובים ונתונים'!E12=1, F12=4), 3, IF(AND('חישובים ונתונים'!E12=2, F12=1), 1, IF(AND('חישובים ונתונים'!E12=2, F12=2), 1, IF(AND('חישובים ונתונים'!E12=2, F12=3), 2, IF(AND('חישובים ונתונים'!E12=2, F12=4), 2, IF(AND('חישובים ונתונים'!E12=3, F12=1), 2, IF(AND('חישובים ונתונים'!E12=3, F12=2), 2, IF(AND('חישובים ונתונים'!E12=3, F12=3), 2, IF(AND('חישובים ונתונים'!E12=3, F12=4), 3, IF(AND('חישובים ונתונים'!E12=4, F12=1), 2, IF(AND('חישובים ונתונים'!E12=4, F12=2), 2, IF(AND('חישובים ונתונים'!E12=4, F12=3), 3, IF(AND('חישובים ונתונים'!E12=4, F12=4), 3))))))))))))))))) -> 2 | K24: בינוניות | L24: 3
D25: ='סיווג אופי מידע במערכת (4)'!#REF! -> #REF! | G25: =IF(ISNUMBER(G24),"רמת הסיכון השיורי למערכת ולמידע לאחר יישום הבקרות הינו"& " - " &VLOOKUP(G24,'חישובים ונתונים'!$L$27:$M$30,2),"נא השלם פרק קודם") -> רמת הסיכון השיורי למערכת ולמידע לאחר יישום הבקרות הינו - סיכון בינוני | K25: חמורות | L25: 4
D26: ='סיווג אופי מידע במערכת (4)'!$D$17 -> 0
D27: ='סיווג אופי מידע במערכת (4)'!$D$18 -> 0 | L27: 1 | M27: סיכון נמוך
D28: ='סיווג אופי מידע במערכת (4)'!$D$19 -> 0 | L28: 2 | M28: סיכון בינוני
D29: ='סיווג אופי מידע במערכת (4)'!$D$35 -> 0 | L29: 3 | M29: סיכון גבוה
D30: ='סיווג אופי מידע במערכת (4)'!$D$36 -> 0 | L30: 4 | M30: סיכון גבוה מאוד
D31: ='סיווג אופי מידע במערכת (4)'!$D$37 -> 0
D32: ='סיווג אופי מידע במערכת (4)'!$D$38 -> 0
D33: ='סיווג אופי מידע במערכת (4)'!$D$39 -> 0
D34: ='סיווג אופי מידע במערכת (4)'!$D$40 -> 0
D35: ='סיווג אופי מידע במערכת (4)'!$D$41 -> 0
D36: ='סיווג אופי מידע במערכת (4)'!$D$42 -> 0
D38: =B12 -> בלמס - מידע פנימי | G38: =IF(R45="נא להשלים את כלל הפרטים בהערכת הנזק","נא להשלים את כלל הפרטים בהערכת הנזק","נזק"& " " &VLOOKUP('חישובים ונתונים'!R45,'חישובים ונתונים'!$L$17:$M$20,2,FALSE)) -> נזק בינוני
D39: =IF(ISNUMBER(R45)," מידת הנזק הפוטנציאלי הצפוי למשרד הוא"&" - נזק"&" "&VLOOKUP('חישובים ונתונים'!R45,'חישובים ונתונים'!$L$17:$M$20,2,FALSE),"נא להשלים את כלל הפרטים בהערכת הנזק") -> מידת הנזק הפוטנציאלי הצפוי למשרד הוא - נזק בינוני
D40: =IF(ISNUMBER(G21),"רמת הסיכון השורשי למערכת ולמידע לאחר חישוב הינו"& " - " &VLOOKUP('חישובים ונתונים'!$G$21,'חישובים ונתונים'!$L$27:$M$30,2),"נא השלם פרק קודם") -> רמת הסיכון השורשי למערכת ולמידע לאחר חישוב הינו - סיכון גבוה
K41: פגיעה כלכלית בארגון | L41: נזק לתדמית הארגון בעיני הציבור | M41: פגיעה בייעדי רציפות התפקודית | N41: פגיעה בייעדי מתן שירות לציבור \ ללקוחות | O41: חשיפה משפטית/ רגולטורית / משילות | P41: נכס מידע תשתיתי רוחבי | Q41: פגיעה בביטחון/ בטיחות/ שלום הציבור או עובדי הארגון | R41: סיכום מידת הנזק
J42: חסיון Confidentiality | K42: =VLOOKUP('הערכת נזק פוטנציאלי למערכת (5)'!C15,'חישובים ונתונים'!$K$12:$L$15,2,FALSE) -> 1 | L42: =VLOOKUP('הערכת נזק פוטנציאלי למערכת (5)'!D15,K17:L20,2,FALSE) -> 1 | M42: =VLOOKUP('הערכת נזק פוטנציאלי למערכת (5)'!E15,'חישובים ונתונים'!$K$12:$L$15,2,FALSE) -> 2 | N42: =VLOOKUP('הערכת נזק פוטנציאלי למערכת (5)'!F15,'חישובים ונתונים'!$K$12:$L$15,2,FALSE) -> 2 | O42: =VLOOKUP('הערכת נזק פוטנציאלי למערכת (5)'!G15,'חישובים ונתונים'!$K$12:$L$15,2,FALSE) -> 1 | P42: =VLOOKUP('הערכת נזק פוטנציאלי למערכת (5)'!H15,$K$22:$L$25,2,FALSE) -> 2 | Q42: =VLOOKUP('הערכת נזק פוטנציאלי למערכת (5)'!I15,'חישובים ונתונים'!$K$12:$L$15,2,FALSE) -> 1 | R42: =MAX(K42:Q42) -> 2 | S42: =IF(ISNUMBER(R42),VLOOKUP('חישובים ונתונים'!$R$42,'חישובים ונתונים'!$L$12:$M$15,2,FALSE),"חסרים פרטים") -> מוגבלת
J43: אמינות Integrity | K43: =VLOOKUP('הערכת נזק פוטנציאלי למערכת (5)'!C16,'חישובים ונתונים'!$K$12:$L$15,2,FALSE) -> 1 | L43: =VLOOKUP('הערכת נזק פוטנציאלי למערכת (5)'!D16,'חישובים ונתונים'!$K$17:$L$20,2,FALSE) -> 1 | M43: =VLOOKUP('הערכת נזק פוטנציאלי למערכת (5)'!E16,'חישובים ונתונים'!$K$12:$L$15,2,FALSE) -> 2 | N43: =VLOOKUP('הערכת נזק פוטנציאלי למערכת (5)'!F16,'חישובים ונתונים'!$K$12:$L$15,2,FALSE) -> 1 | O43: =VLOOKUP('הערכת נזק פוטנציאלי למערכת (5)'!G16,'חישובים ונתונים'!$K$12:$L$15,2,FALSE) -> 1 | P43: =VLOOKUP('הערכת נזק פוטנציאלי למערכת (5)'!H16,$K$22:$L$25,2,FALSE) -> 2 | Q43: =VLOOKUP('הערכת נזק פוטנציאלי למערכת (5)'!I16,'חישובים ונתונים'!$K$12:$L$15,2,FALSE) -> 1 | R43: =MAX(K43:Q43) -> 2 | S43: =IF(ISNUMBER(R43),VLOOKUP('חישובים ונתונים'!$R$43,'חישובים ונתונים'!$L$12:$M$15,2,FALSE),"חסרים פרטים") -> מוגבלת
J44: זמינות Availability | K44: =VLOOKUP('הערכת נזק פוטנציאלי למערכת (5)'!C17,'חישובים ונתונים'!$K$12:$L$15,2,FALSE) -> 1 | L44: =VLOOKUP('הערכת נזק פוטנציאלי למערכת (5)'!D17,'חישובים ונתונים'!$K$17:$L$20,2,FALSE) -> 1 | M44: =VLOOKUP('הערכת נזק פוטנציאלי למערכת (5)'!E17,'חישובים ונתונים'!$K$12:$L$15,2,FALSE) -> 1 | N44: =VLOOKUP('הערכת נזק פוטנציאלי למערכת (5)'!F17,'חישובים ונתונים'!$K$12:$L$15,2,FALSE) -> 1 | O44: =VLOOKUP('הערכת נזק פוטנציאלי למערכת (5)'!G17,'חישובים ונתונים'!$K$12:$L$15,2,FALSE) -> 1 | P44: =VLOOKUP('הערכת נזק פוטנציאלי למערכת (5)'!H17,$K$22:$L$25,2,FALSE) -> 1 | Q44: =VLOOKUP('הערכת נזק פוטנציאלי למערכת (5)'!I17,'חישובים ונתונים'!$K$12:$L$15,2,FALSE) -> 3 | R44: =MAX(K44:Q44) -> 3 | S44: =IF(ISNUMBER(R44),VLOOKUP('חישובים ונתונים'!$R$44,'חישובים ונתונים'!$L$12:$M$15,2,FALSE),"חסרים פרטים") -> בינונית
K45: =MAX(K42:K44) -> 1 | L45: =MAX(L42:L44) -> 1 | M45: =MAX(M42:M44) -> 2 | N45: =MAX(N42:N44) -> 2 | O45: =MAX(O42:O44) -> 1 | P45: =MAX(P42:P44) -> 2 | Q45: =MAX(Q42:Q44) -> 3 | R45: =IF(ISERROR(MAX(R42:R44)),"נא להשלים את כלל הפרטים בהערכת הנזק",MAX(R42:R44)) -> 3
K46: {=IF(ISNUMBER(K45),TEXT(VLOOKUP(K41,$W$49:$AA$55,K45+1,FALSE),CELL("color",Y49)),"חסרים פרטים")} -> ללא פגיעה כלכלית בארגון | L46: =IF(ISNUMBER(L45),VLOOKUP(L41,$W$49:$AA$55,L45+1,FALSE),"חסרים פרטים") -> ללא נזק תדמיתי או חשיפה תקשורתית נמוכה | M46: =IF(ISNUMBER(M45),VLOOKUP(M41,$W$49:$AA$55,M45+1,FALSE),"חסרים פרטים") -> פגיעה מצומצמת ברציפות התפקודית תוך עמידה ביעדים | N46: =IF(ISNUMBER(N45),VLOOKUP(N41,$W$49:$AA$55,N45+1,FALSE),"חסרים פרטים") -> פגיעה נקודתית במתן שירות לציבור / ללקחות תוך עמידה ביעדים | O46: =IF(ISNUMBER(O45),VLOOKUP(O41,$W$49:$AA$55,O45+1,FALSE),"חסרים פרטים") -> ללא חשיפה משפטית | P46: =IF(ISNUMBER(P45),VLOOKUP(P41,$W$49:$AA$55,P45+1,FALSE),"חסרים פרטים") -> השפעה על נכס מידע תשתיתי לא אסטרטגי בודד | Q46: =IF(ISNUMBER(Q45),VLOOKUP(Q41,$W$49:$AA$55,Q45+1,FALSE),"חסרים פרטים") -> פגיעה נרחבת בודדת או מספר פגיעות נקודתיות
W48: קריטריון | X48: נזק מינימלי | Y48: נזק מוגבל | Z48: נזק בינוני | AA48: נזק חמור
W49: פגיעה כלכלית בארגון | X49: ללא פגיעה כלכלית בארגון | Y49: פגיעה של עד 0.5% מהתקציב התפעולי השנתי של הארגון או המשרד הממשלתי | Z49: פגיעה מצומצמת עד 2% מהתקציב התפעולי השנתי של הארגון או המשרד הממשלתי | AA49: פגיעה משמעותית של מעל 2% מהתקציב התפעולי השנתי של הארגון או המשרד הממשלתי
W50: נזק לתדמית הארגון בעיני הציבור | X50: ללא נזק תדמיתי או חשיפה תקשורתית נמוכה | Y50: כיסוי תקשורתי שלילי של כלי התקשורת איזוטריים | Z50: כיסוי תקשורתי שלילי נרחב ברמה הלאומית בעל השלכות המצריכות תקשור לציבור | AA50: כיסוי תקשורתי שלילי משמעותי ברמה בינלאומית עד כדי עצירת פעילות הארגון (יתכן והאירוע מצריך מתן הסברים ובירורים על ידי גורמי רגולציה חיצוניים)
H51: ללא פגיעה כלכלית במשרד | I51: ללא נזק תדמיתי או חשיפה תקשורתית נמוכה | J51: ללא פגיעה ברציפות התפקודית | K51: ללא פגיעה במתן שירות לציבור \ לא רלוונטי | L51: ללא חשיפה משפטית | M51: ללא השפעה | N51: ללא פגיעה | W51: פגיעה בייעדי רציפות התפקודית | X51: ללא פגיעה ברציפות התפקודית | Y51: פגיעה מצומצמת ברציפות התפקודית תוך עמידה ביעדים | Z51: פגיעה נמוכה ביעדי הרציפות התפקודית | AA51: פגיעה חמורה וממושכת ביעדי הרציפות התפקודית
H52: פגיעה של עד 0.5% מהתקציב התפעולי השנתי של המשרד הממשלתי | I52: כיסוי תקשורתי שלילי של כלי התקשורת איזוטריים | J52: פגיעה מצומצמת ברציפות התפקודית תוך עמידה ביעדים | K52: פגיעה נקודתית במתן שירות לציבור תוך עמידה ביעדים | L52: חשיפה נמוכה מאוד לתביעות משפטיות | M52: השפעה על הליך לא אסטרטגי בודד | N52: פגיעה נקודתית | W52: פגיעה בייעדי מתן שירות לציבור \ ללקוחות | X52: ללא פגיעה במתן שירות לציבור או הללקוחות / לא רלוונטי | Y52: פגיעה נקודתית במתן שירות לציבור / ללקחות תוך עמידה ביעדים | Z52: פגיעה נרחבת במתן שירותים לציבור / ללקוחות תוך עמידה ביעדים | AA52: פגיעה נרחבת במתן שירותים לציבור / ללקוחות לתקופת זמן ממושכת וחריגה מייעדי השירות
H53: פגיעה מצומצמת עד 2% מהתקציב התפעולי השנתי של המשרד הממשלתי | I53: כיסוי תקשורתי שלילי נרחב ברמה הלאומית בעל השלכות המצריכות תקשור לציבור | J53: פגיעה נמוכה ביעדי הרציפות התפקודית | K53: פגיעה נרחבת במתן שירותים לציבור תוך עמידה ביעדים | L53: חשיפה משפטית לתביעות נמוכה | M53: השפעה על מספר הליכים לא אסטרטגיים או על הליך אסטרטגי בודד | N53: פגיעה נרחבת בודדת או מספר פגיעות נקודתיות | W53: חשיפה משפטית/ רגולטורית / משילות | X53: ללא חשיפה משפטית | Y53: חשיפה נמוכה מאוד לתביעות משפטיות | Z53: חשיפה נמוכה לתביעות משפטיות | AA53: חשיפה משפטית לקובלנה פלילית, אפשרות לעצירת פעילות הארגון או המשרד הממשלתי
H54: פגיעה משמעותית של מעל 2% מהתקציב התפעולי השנתי של המשרד הממשלתי | I54: כיסוי תקשורתי שלילי משמעותי ברמה בינלאומית עד כדי עצירת פעילות המשרד (יתכן והאירוע מצריך מתן הסברים ובירורים על ידי גורמי רגולציה חיצוניים) | J54: פגיעה חמורה וממושכת ביעדי הרציפות התפקודית | K54: פגיעה נרחבת במתן שירותים לציבור לתקופת זמן ממושכת וחריגה מייעדי השירות | L54: חשיפה משפטית לקובלנה פלילית בינונית ואפשרות לחשיפה פלילית, אפשרות לעצירת פעילות המשרד הממשלתי | M54: השפעה על מספר הליכים אסטרטגיים עד כדי הפסקת פעילות המשרד הממשלתי | N54: מספר פגיעות נרחבות | W54: נכס מידע תשתיתי רוחבי | X54: ללא השפעה | Y54: השפעה על נכס מידע תשתיתי לא אסטרטגי בודד | Z54: השפעה על מספר נכסים לא אסטרטגיים או על נכס אסטרטגי בודד | AA54: השפעה על מספר נכסים אסטרטגיים עד כדי הפסקת פעילות הארגון או המשרד הממשלתי
W55: פגיעה בביטחון/ בטיחות/ שלום הציבור או עובדי הארגון | X55: ללא פגיעה | Y55: פגיעה נקודתית | Z55: פגיעה נרחבת בודדת או מספר פגיעות נקודתיות | AA55: מספר פגיעות נרחבות
A1048576: נבנה על ידי אבא אקילוב | XFD1048576: נבנה על ידי אבא אקילוב

Sheet תמצ המערכת
F3: ="תמונת מצב המערכת " -> תמונת מצב המערכת
K12: מסלול אדום מעל 70%
D23: תוצאת סטאטוס מערכת (מסלול אדום \ ירוק)
D24: ='חישוב תמק'!K7 -> על סמך ניתוח המערכת הנך נדרש לפנות למנחה לבחינת ההיתכנות להעלאת המערכת לענן
D26: תוצאת סיווג אופי המידע | H26: תוצאת הנזק הפוטנציאלי
D27: ='חישובים ונתונים'!D38 -> בלמס - מידע פנימי | G27: + | H27: ='חישובים ונתונים'!G38 -> נזק בינוני
G28: ↘ ↙
D30: תוצאת רמת הסיכון השורשית
D31: ='חישובים ונתונים'!D40 -> רמת הסיכון השורשי למערכת ולמידע לאחר חישוב הינו - סיכון גבוה
G32: â
G33: =חישובים!E2 -> 218
G34: â
D35: תוצאת רמת הסיכון השיורי
D36: ='חישובים ונתונים'!G25 -> רמת הסיכון השיורי למערכת ולמידע לאחר יישום הבקרות הינו - סיכון בינוני
D38: מפת חום לרמות הסיכון
F39: אופי המידע
F40: מידע פומבי | G40: מידע פנימי | H40: מידע פנימי מוגבל | I40: מידע פנימי חסוי
D41: חומרת נזק פוטנציאלי | E41: נזק מינימלי | F41: נמוך | G41: בינוני | H41: גבוה | I41: גבוה מאוד
E42: נזק מוגבל | F42: בינוני | G42: בינוני | H42: גבוה | I42: גבוה מאוד
E43: נזק בינוני | F43: גבוה | G43: גבוה | H43: גבוה | I43: גבוה מאוד
E44: נזק חמור | F44: גבוה מאוד | G44: גבוה מאוד | H44: גבוה מאוד | I44: גבוה מאוד
D47: סיכום הנזקים הפוטנציאליים
D48: פגיעה כלכלית בארגון | F48: ='חישובים ונתונים'!K46 -> ללא פגיעה כלכלית בארגון
D49: נזק לתדמית הארגון בעיני הציבור | F49: ='חישובים ונתונים'!L46 -> ללא נזק תדמיתי או חשיפה תקשורתית נמוכה
D50: פגיעה בייעדי רציפות התפקודית | F50: ='חישובים ונתונים'!M46 -> פגיעה מצומצמת ברציפות התפקודית תוך עמידה ביעדים
D51: פגיעה בייעדי מתן שירות לציבור \ ללקוחות | F51: ='חישובים ונתונים'!N46 -> פגיעה נקודתית במתן שירות לציבור / ללקחות תוך עמידה ביעדים
D52: חשיפה משפטית/ רגולטורית / משילות | F52: ='חישובים ונתונים'!O46 -> ללא חשיפה משפטית
D53: נכס מידע תשתיתי רוחבי | F53: ='חישובים ונתונים'!P46 -> השפעה על נכס מידע תשתיתי לא אסטרטגי בודד
D54: פגיעה בביטחון/ בטיחות/ שלום הציבור או עובדי הארגון | F54: ='חישובים ונתונים'!Q46 -> פגיעה נרחבת בודדת או מספר פגיעות נקודתיות
G56: סיכום רמת רגישות מידע/מערכת שורשי
F57: חסיון | G57: אמינות | H57: זמינות
F58: =IF(ISNUMBER('חישובים ונתונים'!R42), 'חישובים ונתונים'!R42, "לא זמין") -> 2 | G58: =IF(ISNUMBER('חישובים ונתונים'!R43), 'חישובים ונתונים'!R43, "לא זמין") -> 2 | H58: =IF(ISNUMBER('חישובים ונתונים'!R44), 'חישובים ונתונים'!R44, "לא זמין") -> 3

Sheet פרופיל בקרות טכני
B3: {=IF( AND('פרופיל בקרות דרוש (8)'!E4=חישובים!O2, 'פרופיל בקרות דרוש (8)'!E3=חישובים!N2), INDEX(AWS[], SMALL(IF((AWS[Column1]=חישובים!$Q$1)+(AWS[Column1]=חישובים!$Q$2), ROW(AWS[Column1])-MIN(ROW(AWS[Column1]))+1, ""), ROW(INDIRECT("1:"&COUNTIF(AWS[Column1],חישובים!$Q$1)+COUNTIF(AWS[Column1],חישובים!$Q$2)))), {3,4,5,6,7,14,16,2,17,19,20,27,23,21}), IF( AND('פרופיל בקרות דרוש (8)'!E4=חישובים!O3, 'פרופיל בקרות דרוש (8)'!E3=חישובים!N2), INDEX(AWS_2[], SMALL(IF((AWS_2[Column1]=חישובים!$Q$1)+(AWS_2[Column1]=חישובים!$Q$2), ROW(AWS_2[Column1])-MIN(ROW(AWS_2[Column1]))+1, ""), ROW(INDIRECT("1:"&COUNTIF(AWS_2[Column1],חישובים!$Q$1)+COUNTIF(AWS_2[Column1],חישובים!$Q$2)))), {3,4,5,6,7,14,16,2,17,19,20,27,23,21}), IF( AND('פרופיל בקרות דרוש (8)'!E4=חישובים!O2, 'פרופיל בקרות דרוש (8)'!E3=חישובים!N3), INDEX(GCP[], SMALL(IF((GCP[Column1]=חישובים!$Q$1)+(GCP[Column1]=חישובים!$Q$2), ROW(GCP[Column1])-MIN(ROW(GCP[Column1]))+1, ""), ROW(INDIRECT("1:"&COUNTIF(GCP[Column1],חישובים!$Q$1)+COUNTIF(GCP[Column1],חישובים!$Q$2)))), {3,4,5,6,7,14,16,2,17,19,20,27,23,21}), IF( AND('פרופיל בקרות דרוש (8)'!E4=חישובים!O3, 'פרופיל בקרות דרוש (8)'!E3=חישובים!N3), INDEX(GCP_2[], SMALL(IF((GCP_2[Column1]=חישובים!$Q$1)+(GCP_2[Column1]=חישובים!$Q$2), ROW(GCP_2[Column1])-MIN(ROW(GCP_2[Column1]))+1, ""), ROW(INDIRECT("1:"&COUNTIF(GCP_2[Column1],חישובים!$Q$1)+COUNTIF(GCP_2[Column1],חישובים!$Q$2)))), {3,4,5,6,7,14,16,2,17,19,20,27,23,21}), "Error" ) ) ) )} -> מספר בקרה ב CIS | C3: סוג הנכס | D3: סוג בקרת אבטחה | E3: תיאור | F3: תיאור מפורט | G3: תיאור בקרת ספק | H3: תיאור | I3: מספר בקרה ספק ענן CIS | J3: הסבר | K3: אופן מימוש הבקרה | L3: קישורים יישימים | M3: בקרת ספק מומלצת | N3: סוג הבקרה | O3: מתקבל כברירת מחדל באזור הנחיתה הממשלתי
B4: - | C4: - | D4: - | E4: מיפוי ובקרה על נכסים ארגוניים | F4: Actively manage (inventory, track, and correct) all enterprise assets (end-user devices, including portable and mobile; network devices; non-computing/Internet of Things (IoT) devices; and servers) connected to the infrastructure physically, virtually, remotely, and those within cloud environments, to accurately know the totality of assets that need to be monitored and protected within the enterprise. This will also support identifying unauthorized and unmanaged assets to remove or remediate. | G4: - | H4: - | I4: - | J4: - | K4: - | L4: - | M4: - | N4: - | O4: .
B5: 1.1 | C5: Devices | D5: Identify | E5: הקמה ותחזוקה של מיפוי נכסים ארגוניים מפורטים | F5: Establish and maintain an accurate, detailed, and up-to-date inventory of all enterprise assets with the potential to store or process data, to include: end-user devices (including portable and mobile), network devices, non-computing/IoT devices, and servers. Ensure the inventory records the network address (if static), hardware address, machine name, enterprise asset owner, department for each asset, and whether the asset has been approved to connect to the network. For mobile end-user devices, MDM type tools can support this process, where appropriate. This inventory includes assets connected to the infrastructure physically, virtually, remotely, and those within cloud environments. Additionally, it includes assets that are regularly connected to the enterprise’s network infrastructure, even if they are not under control of the enterprise. Review and update the inventory of all enterprise assets bi-annually, or more frequently. | G5: 2.13 Ensure Cloud Asset Inventory Is Enabled (Automated) | H5: GCP Cloud Asset Inventory is services that provides a historical view of GCP resources and IAM policies through a time-series database. The information recorded includes metadata on Google Cloud resources, metadata on policies set on Google Cloud projects or resources, and runtime information gathered within a Google Cloud resource. | I5: 2.13 | J5: The GCP resources and IAM policies captured by GCP Cloud Asset Inventory enables security analysis, resource change tracking, and compliance auditing. It is recommended GCP Cloud Asset Inventory be enabled for all GCP projects. | K5: From Google Cloud Console Enable the Cloud Asset API: 1. Go to API & Services/Library by visiting https://console.cloud.google.com/apis/library 2. Search for Cloud Asset API and select the result for Cloud Asset API 3. Click the ENABLE button. Page 115 From Google Cloud CLI Enable the Cloud Asset API: 1. Enable the Cloud Asset API through the services interface: gcloud services enable cloudasset.googleapis.com Default Value: The Cloud Asset Inventory API is disabled by default in each project. | L5: 1. https://cloud.google.com/asset-inventory/docs | M5: v | N5: מערכת | O5: -
B6: 1.2 | C6: Devices | D6: Respond | E6: התייחס לנכסים לא מורשים | F6: Ensure that a process exists to address unauthorized assets on a weekly basis. The enterprise may choose to remove the asset from the network, deny the asset from connecting remotely to the network, or quarantine the asset. | G6: - | H6: - | I6: - | J6: - | K6: - | L6: - | N6: ארגוני | O6: -
B7: 1.3 | C7: Devices | D7: Detect | E7: השתמשו בכלי גילוי אקטיביים | F7: Utilize an active discovery tool to identify assets connected to the enterprise’s network. Configure the active discovery tool to execute daily, or more frequently. | G7: - | H7: - | I7: - | J7: - | K7: - | L7: - | N7: ארגוני | O7: -
B8: 1.4 | C8: Devices | D8: Identify | E8: השתמש ברישום-Dynamic Host Configuration Protocol (DHCP) כדי לעדכן את מיפוי הנכסים הארגוניים | F8: Use DHCP logging on all DHCP servers or Internet Protocol (IP) address management tools to update the enterprise’s asset inventory. Review and use logs to update the enterprise’s asset inventory weekly, or more frequently. | G8: - | H8: - | I8: - | J8: - | K8: - | L8: - | N8: ארגוני | O8: -
B9: 1.5 | C9: Devices | D9: Detect | E9: השתמש בכלי גילוי נכסים פסיבי | F9: Use a passive discovery tool to identify assets connected to the enterprise’s network. Review and use scans to update the enterprise’s asset inventory at least weekly, or more frequently. | G9: - | H9: - | I9: - | J9: - | K9: - | L9: - | N9: ארגוני | O9: -
B10: - | C10: - | D10: - | E10: מיפוי ובקרת נכסי תוכנה | F10: Actively manage (inventory, track, and correct) all software (operating systems and applications) on the network so that only authorized software is installed and can execute, and that unauthorized and unmanaged software is found and prevented from installation or execution. | G10: - | H10: - | I10: - | J10: - | K10: - | L10: - | M10: - | N10: - | O10: -
B11: 2.1 | C11: Applications | D11: Identify | E11: הקמה ותחזוקה של מיפוי תוכנה | F11: Establish and maintain a detailed inventory of all licensed software installed on enterprise assets. The software inventory must document the title, publisher, initial install/use date, and business purpose for each entry; where appropriate, include the Uniform Resource Locator (URL), app store(s), version(s), deployment mechanism, and decommission date. Review and update the software inventory bi-annually, or more frequently. | G11: - | H11: - | I11: - | J11: - | K11: - | L11: - | N11: ארגוני | O11: -
B12: 2.2 | C12: Applications | D12: Identify | E12: ודא כי התוכנה המורשית בארגון נתמכת על ידי היצרן | F12: Ensure that only currently supported software is designated as authorized in the software inventory for enterprise assets. If software is unsupported, yet necessary for the fulfillment of the enterprise’s mission, document an exception detailing mitigating controls and residual risk acceptance. For any unsupported software without an exception documentation, designate as unauthorized. Review the software list to verify software support at least monthly, or more frequently. | G12: 4.12 Ensure the Latest Operating System Updates Are Installed On Your Virtual Machines in All Projects (Manual) | H12: Google Cloud Virtual Machines have the ability via an OS Config agent API to periodically (about every 10 minutes) report OS inventory data. A patch compliance API periodically reads this data, and cross references metadata to determine if the latest updates are installed. This is not the only Patch Management solution available to your organization and you should weigh your needs before committing to using this method. | I12: 4.12 | J12: Keeping virtual machine operating systems up to date is a security best practice. Using this service will simplify this process. Impact: Most Operating Systems require a restart or changing critical resources to apply the updates. Using the Google Cloud VM manager for its OS Patch management will incur additional costs for each VM managed by it. Please view the VM manager pricing reference for further information. | K12: From Google Cloud Console Enabling OS Patch Management on a Project by Project Basis Install OS Config API for the Project 1. Navigate into a project. In the expanded portal menu located at the top left of the screen hover over "APIs & Services". Then in the menu right of that select "API Libraries" 2. Search for "VM Manager (OS Config API) or scroll down in the left hand column and select the filter labeled "Compute" where it is the last listed. Open this API. 3. Click the blue 'Enable' button. Add MetaData Tags for OSConfig Parsing 1. From the main Google Cloud console, open the portal menu in the top left. Mouse over Computer Engine to expand the menu next to it. 2. Under the "Settings" heading, select "Metadata". 3. In this view there will be a list of the project wide metadata tags for VMs. Click edit and 'add item' in the key column type 'enable-osconfig' and in the value column set it to 'true'. From Command Line 1. For project wide tagging, run the following command gcloud compute project-info add-metadata \ --project <PROJECT_ID>\ --metadata=enable-osconfig=TRUE Please see the reference /compute/docs/troubleshooting/vm-manager/verify-setup#metadata-enabled at the bottom for more options like instance specific tagging. Note: Adding a new tag via commandline may overwrite existing tags. You will need to do this at a time of low usage for the least impact. Install and Start the Local OSConfig for Data Parsing There is no way to centrally manage or start the Local OSConfig agent. Please view the reference of manage-os#agent-install to view specific operating system commands. Setup a project wide Service Account Please view Recommendation 4.1 to view how to setup a service account. Rerun the audit procedure to test if it has taken effect. Enable NAT or Configure Private Google Access to allow Access to Public Update Hosting For the sake of brevity, please see the attached resources to enable NAT or Private Google Access. Rerun the audit procedure to test if it has taken effect. From Command Line: Install OS Config API for the Project 1. In each project you wish to audit run gcloud services enable osconfig.googleapis.com Install and Start the Local OSConfig for Data Parsing Please view the reference of manage-os#agent-install to view specific operating system commands. Setup a project wide Service Account Please view Recommendation 4.1 to view how to setup a service account. Rerun the audit procedure to test if it has taken effect. Enable NAT or Configure Private Google Access to allow Access to Public Update Hosting For the sake of brevity, please see the attached resources to enable NAT or Private Google Access. Rerun the audit procedure to test if it has taken effect. Determine if Instances can connect to public update hosting Linux Debian Based Operating Systems sudo apt update The output should have a numbered list of lines with Hit: URL of updates. Redhat Based Operating Systems yum check-update The output should show a list of packages that have updates available. Windows ping http://windowsupdate.microsoft.com/ The ping should successfully be delivered and received. Default Value: By default most operating systems and programs do not update themselves. The Google Cloud VM Manager which is a dependency of the OS Patch management feature is installed on Google Built OS images with a build date of v20200114 or later. The VM manager is not enabled in a project by default and will need to be setup. | L12: 1. https://cloud.google.com/compute/docs/manage-os 2. https://cloud.google.com/compute/docs/os-patch-management 3. https://cloud.google.com/compute/docs/vm-manager 4. https://cloud.google.com/compute/docs/images/os-details#vm-manager 5. https://cloud.google.com/compute/docs/vm-manager#pricing 6. https://cloud.google.com/compute/docs/troubleshooting/vm-manager/verify-setup 7. https://cloud.google.com/compute/docs/instances/view-os-details#view-data-tools 8. https://cloud.google.com/compute/docs/os-patch-management/create-patch-job 9. https://cloud.google.com/nat/docs/set-up-network-address-translation 10. https://cloud.google.com/vpc/docs/configure-private-google-access 11. https://workbench.cisecurity.org/sections/811638/recommendations/1334335 12. https://cloud.google.com/compute/docs/manage-os#agent-install 13. https://cloud.google.com/compute/docs/troubleshooting/vm-manager/verify-setup#service-account-enabled 14. https://cloud.google.com/compute/docs/os-patch-management#use-dashboard 15. https://cloud.google.com/compute/docs/troubleshooting/vm-manager/verify-setup#metadata-enabled | M12: v | N12: מערכת | O12: -
B13: 2.3 | C13: Applications | D13: Respond | E13: קיים תוכנית לטיפול ברכיבי תוכנה לא מאושרים | F13: Ensure that unauthorized software is either removed from use on enterprise assets or receives a documented exception. Review monthly, or more frequently. | G13: - | H13: - | I13: - | J13: - | K13: - | L13: - | N13: ארגוני | O13: -
B14: 2.4 | C14: Applications | D14: Detect | E14: השתמש בכלי מיפוי תוכנה אוטומטיים | F14: Utilize software inventory tools, when possible, throughout the enterprise to automate the discovery and documentation of installed software. | G14: - | H14: - | I14: - | J14: - | K14: - | L14: - | N14: ארגוני | O14: -
B15: 2.5 | C15: Applications | D15: Protect | E15: ניהול רשימת תוכנות מאושרות | F15: Use technical controls, such as application allowlisting, to ensure that only authorized software can execute or be accessed. Reassess bi-annually, or more frequently. | G15: - | H15: - | I15: - | J15: - | K15: - | L15: - | N15: ארגוני | O15: -
B16: 2.6 | C16: Applications | D16: Protect | E16: ניהול רשימת ספריות קוד מאושרות | F16: Use technical controls to ensure that only authorized software libraries, such as specific .dll, .ocx, .so, etc., files, are allowed to load into a system process. Block unauthorized libraries from loading into a system process. Reassess bi-annually, or more frequently. | G16: - | H16: - | I16: - | J16: - | K16: - | L16: - | N16: מערכת | O16: -
B17: 2.7 | C17: Applications | D17: Protect | E17: ניהול רשימת קטעי קוד וסקריפטים מאושרים | F17: Use technical controls, such as digital signatures and version control, to ensure that only authorized scripts, such as specific .ps1, .py, etc., files, are allowed to execute. Block unauthorized scripts from executing. Reassess bi-annually, or more frequently. | G17: 6.3.1 Ensure 'external scripts enabled' database flag for Cloud SQL SQL Server instance is set to 'off' (Automated) | H17: It is recommended to set external scripts enabled database flag for Cloud SQL SQL Server instance to off | I17: 6.3.1 | J17: external scripts enabled enable the execution of scripts with certain remote language extensions. This property is OFF by default. When Advanced Analytics Services is installed, setup can optionally set this property to true. As the External Scripts Enabled feature allows scripts external to SQL such as files located in an R library to be executed, which could adversely affect the security of the system, hence this should be disabled. This recommendation is applicable to SQL Server database instances. Impact: Setting custom flags via command line on certain instances will cause all omitted flags to be reset to defaults. This may cause you to lose custom flags and could result in unforeseen complications or instance restarts. Because of this, it is recommended you apply these flags changes during a period of low usage. | K17: From Google Cloud Console 1. Go to the Cloud SQL Instances page in the Google Cloud Console by visiting https://console.cloud.google.com/sql/instances. 2. Select the SQL Server instance for which you want to enable to database flag. 3. Click Edit. 4. Scroll down to the Flags section. 5. To set a flag that has not been set on the instance before, click Add item, choose the flag external scripts enabled from the drop-down menu, and set its value to off. 6. Click Save to save your changes. 7. Confirm your changes under Flags on the Overview page. From Google Cloud CLI 1. Configure the external scripts enabled database flag for every Cloud SQL SQL Server database instance using the below command. gcloud sql instances patch <INSTANCE_NAME> --database-flags "external scripts enabled=off" Note : This command will overwrite all database flags previously set. To keep those and add new ones, include the values for all flags you want set on the instance; any flag not specifically included is set to its default value. For flags that do not take a value, specify the flag name followed by an equals sign ("="). Default Value: By default external scripts enabled is off | L17: 1. https://docs.microsoft.com/en-us/sql/database-engine/configure-windows/external-scripts-enabled-server-configuration-option?view=sql-server-ver15 2. https://cloud.google.com/sql/docs/sqlserver/flags 3. https://docs.microsoft.com/en-us/sql/advanced-analytics/concepts/security?view=sql-server-ver15 4. https://www.stigviewer.com/stig/ms_sql_server_2016_instance/2018-03-09/finding/V-79347 | M17: v | N17: מערכת | O17: -
A18: {=IFERROR(INDEX(#REF!, MATCH("Yes",#REF!, 0),0),"")} | B18: - | C18: - | D18: - | E18: הגנת מידע | F18: Develop processes and technical controls to identify, classify, securely handle, retain, and dispose of data. | G18: - | H18: - | I18: - | J18: - | K18: - | L18: - | M18: - | N18: - | O18: -
A19: {=IFERROR(INDEX(#REF!, MATCH("Yes",#REF!, 0),0),"")} | B19: 3.1 | C19: Data | D19: Identify | E19: נדרש להקין ולתחזוק תהליך ניהול אבטחת מידע | F19: Establish and maintain a data management process. In the process, address data sensitivity, data owner, handling of data, data retention limits, and disposal requirements, based on sensitivity and retention standards for the enterprise. Review and update documentation annually, or when significant enterprise changes occur that could impact this Safeguard. | G19: - | H19: - | I19: - | J19: - | K19: - | L19: - | N19: מערכת | O19: -
B20: 3.2 | C20: Data | D20: Identify | E20: הקמה ותחזוקה של מיפוי נתונים | F20: Establish and maintain a data inventory, based on the enterprise’s data management process. Inventory sensitive data, at a minimum. Review and update inventory annually, at a minimum, with a priority on sensitive data. | G20: - | H20: - | I20: - | J20: - | K20: - | L20: - | N20: ארגוני | O20: -
B21: 3.3 | C21: Data | D21: Protect | E21: הגדר בקרת גישה לנתונים | F21: Configure data access control lists based on a user’s need to know. Apply data access control lists, also known as access permissions, to local and remote file systems, databases, and applications. | G21: 1.6 Ensure That IAM Users Are Not Assigned the Service Account User or Service Account Token Creator Roles at Project Level (Automated) | H21: It is recommended to assign the Service Account User (iam.serviceAccountUser) and Service Account Token Creator (iam.serviceAccountTokenCreator) roles to a user for a specific service account rather than assigning the role to a user at project level. After revoking Service Account User or Service Account Token Creator roles at the project level from all impacted user account(s), these roles should be assigned to a user(s) for specific service account(s) according to business needs. By default, users do not have the Service Account User or Service Account Token Creator role assigned at project level. | I21: 1.6 | J21: A service account is a special Google account that belongs to an application or a virtual machine (VM), instead of to an individual end-user. Application/VM-Instance uses the service account to call the service's Google API so that users aren't directly involved. In addition to being an identity, a service account is a resource that has IAM policies attached to it. These policies determine who can use the service account. Users with IAM roles to update the App Engine and Compute Engine instances (such as App Engine Deployer or Compute Instance Admin) can effectively run code as the service accounts used to run these instances, and indirectly gain access to all the resources for which the service accounts have access. Similarly, SSH access to a Compute Engine instance may also provide the ability to execute code as that instance/Service account. Based on business needs, there could be multiple user-managed service accounts configured for a project. Granting the iam.serviceAccountUser or iam.serviceAccountTokenCreator roles to a user for a project gives the user access to all service accounts in the project, including service accounts that may be created in the future. This can result in elevation of privileges by using service accounts and corresponding Compute Engine instances. In order to implement least privileges best practices, IAM users should not be assigned the Service Account User or Service Account Token Creator roles at the project level. Instead, these roles should be assigned to a user for a specific service account, giving that user access to the service account. The Service Account User allows a user to bind a service account to a long-running job service, whereas the Service Account Token Creator role allows a user to directly impersonate (or assert) the identity of a service account. | K21: From Google Cloud Console 1. Go to the IAM page in the GCP Console by visiting: https://console.cloud.google.com/iam-admin/iam. 2. Click on the filter table text bar. Type Role: Service Account User 3. Click the Delete Bin icon in front of the role Service Account User for every user listed as a result of a filter. 4. Click on the filter table text bar. Type Role: Service Account Token Creator 5. Click the Delete Bin icon in front of the role Service Account Token Creator for every user listed as a result of a filter. From Google Cloud CLI 1. Using a text editor, remove the bindings with the roles/iam.serviceAccountUser or roles/iam.serviceAccountTokenCreator. For example, you can use the iam.json file shown below as follows: { "bindings": [ { "members": [ "serviceAccount:our-project-123@appspot.gserviceaccount.com", ], "role": "roles/appengine.appViewer" }, { "members": [ "user:email1@gmail.com" ], "role": "roles/owner" }, { "members": [ "serviceAccount:our-project-123@appspot.gserviceaccount.com", "serviceAccount:123456789012-compute@developer.gserviceaccount.com" ], "role": "roles/editor" } ], "etag": "BwUjMhCsNvY=" } 2. Update the project's IAM policy: gcloud projects set-iam-policy PROJECT_ID iam.json | L21: 1. https://cloud.google.com/iam/docs/service-accounts 2. https://cloud.google.com/iam/docs/granting-roles-to-service-accounts 3. https://cloud.google.com/iam/docs/understanding-roles 4. https://cloud.google.com/iam/docs/granting-changing-revoking-access 5. https://console.cloud.google.com/iam-admin/iam | M21: v | N21: ארגוני | O21: v
B22: 3.3 | C22: Data | D22: Protect | E22: הגדר בקרת גישה לנתונים | F22: Configure data access control lists based on a user’s need to know. Apply data access control lists, also known as access permissions, to local and remote file systems, databases, and applications. | G22: 1.8 Ensure That Separation of Duties Is Enforced While Assigning Service Account Related Roles to Users (Automated) | H22: It is recommended that the principle of 'Separation of Duties' is enforced while assigning service-account related roles to users. Additional Information: Users granted with Owner (roles/owner) and Editor (roles/editor) have privileges equivalent to Service Account Admin and Service Account User. To avoid the misuse, Owner and Editor roles should be granted to very limited users and Use of these primitive privileges should be minimal. These requirements are addressed in separate recommendations. | I22: 1.8 | J22: The built-in/predefined IAM role Service Account admin allows the user/identity to create, delete, and manage service account(s). The built-in/predefined IAM role Service Account User allows the user/identity (with adequate privileges on Compute and App Engine) to assign service account(s) to Apps/Compute Instances. Separation of duties is the concept of ensuring that one individual does not have all necessary permissions to be able to complete a malicious action. In Cloud IAM - service accounts, this could be an action such as using a service account to access resources that user should not normally have access to. Separation of duties is a business control typically used in larger organizations, meant to help avoid security or privacy incidents and errors. It is considered best practice. No user should have Service Account Admin and Service Account User roles assigned at the same time. Impact: The removed role should be assigned to a different user based on business needs. | K22: From Google Cloud Console 1. Go to IAM & Admin/IAM using https://console.cloud.google.com/iam-admin/iam. 2. For any member having both Service Account Admin and Service account User roles granted/assigned, click the Delete Bin icon to remove either role from the member. Removal of a role should be done based on the business requirements. References: 1. https://cloud.google.com/iam/docs/service-accounts 2. https://cloud.google.com/iam/docs/understanding-roles 3. https://cloud.google.com/iam/docs/granting-roles-to-service-accounts | L22: References: 1. https://cloud.google.com/iam/docs/service-accounts 2. https://cloud.google.com/iam/docs/understanding-roles 3. https://cloud.google.com/iam/docs/granting-roles-to-service-accounts | M22: v | N22: מערכת | O22: -
B23: 3.3 | C23: Data | D23: Protect | E23: הגדר בקרת גישה לנתונים | F23: Configure data access control lists based on a user’s need to know. Apply data access control lists, also known as access permissions, to local and remote file systems, databases, and applications. | G23: 1.9 Ensure That Cloud KMS Cryptokeys Are Not Anonymously or Publicly Accessible (Automated) | H23: It is recommended that the IAM policy on Cloud KMS cryptokeys should restrict anonymous and/or public access. [key_ring_name] : Is the resource ID of the key ring, which is the fully-qualified Key ring name. This value is case-sensitive and in the form: projects/PROJECT_ID/locations/LOCATION/keyRings/KEY_RING You can retrieve the key ring resource ID using the Cloud Console: 1. Open the Cryptographic Keys page in the Cloud Console. 2. For the key ring whose resource ID you are retrieving, click the More icon (3 vertical dots). 3. Click Copy Resource ID. The resource ID for the key ring is copied to your clipboard. [key_name] : Is the resource ID of the key, which is the fully-qualified CryptoKey name. This value is case-sensitive and in the form: projects/PROJECT_ID/locations/LOCATION/keyRings/KEY_RING/cryptoKeys/KEY You can retrieve the key resource ID using the Cloud Console: 1. Open the Cryptographic Keys page in the Cloud Console. 2. Click the name of the key ring that contains the key. 3. For the key whose resource ID you are retrieving, click the More icon (3 vertical dots). 4. Click Copy Resource ID. The resource ID for the key is copied to your clipboard. [role] : The role to remove the member from. | I23: 1.9 | J23: Granting permissions to allUsers or allAuthenticatedUsers allows anyone to access the dataset. Such access might not be desirable if sensitive data is stored at the location. In this case, ensure that anonymous and/or public access to a Cloud KMS cryptokey is not allowed. Impact: Removing the binding for allUsers and allAuthenticatedUsers members denies accessing cryptokeys to anonymous or public users. | K23: Remediation: From Google Cloud CLI 1. List all Cloud KMS Cryptokeys. gcloud kms keys list --keyring=[key_ring_name] --location=global --format=json | jq '.[].name' 2. Remove IAM policy binding for a KMS key to remove access to allUsers and allAuthenticatedUsers using the below command. gcloud kms keys remove-iam-policy-binding [key_name] --keyring=[key_ring_name] --location=global --member='allAuthenticatedUsers' --role='[role]' gcloud kms keys remove-iam-policy-binding [key_name] --keyring=[key_ring_name] --location=global --member='allUsers' --role='[role]' Default Value: By default Cloud KMS does not allow access to allUsers or allAuthenticatedUsers. | L23: 1. https://cloud.google.com/sdk/gcloud/reference/kms/keys/remove-iam-policy-binding 2. https://cloud.google.com/sdk/gcloud/reference/kms/keys/set-iam-policy 3. https://cloud.google.com/sdk/gcloud/reference/kms/keys/get-iam-policy 4. https://cloud.google.com/kms/docs/object-hierarchy#key_resource_id | M23: v | N23: מערכת | O23: -
B24: 3.3 | C24: Data | D24: Protect | E24: הגדר בקרת גישה לנתונים | F24: Configure data access control lists based on a user’s need to know. Apply data access control lists, also known as access permissions, to local and remote file systems, databases, and applications. | G24: 1.11 Ensure That Separation of Duties Is Enforced While Assigning KMS Related Roles to Users (Automated) | H24: It is recommended that the principle of 'Separation of Duties' is enforced while assigning KMS related roles to users. Additional Information: Users granted with Owner (roles/owner) and Editor (roles/editor) have privileges equivalent to Cloud KMS Admin and Cloud KMS CryptoKey Encrypter/Decrypter. To avoid misuse, Owner and Editor roles should be granted to a very limited group of users. Use of these primitive privileges should be minimal. These requirements are addressed in separate recommendations. | I24: 1.11 | J24: The built-in/predefined IAM role Cloud KMS Admin allows the user/identity to create, delete, and manage service account(s). The built-in/predefined IAM role Cloud KMS CryptoKey Encrypter/Decrypter allows the user/identity (with adequate privileges on concerned resources) to encrypt and decrypt data at rest using an encryption key(s). The built-in/predefined IAM role Cloud KMS CryptoKey Encrypter allows the user/identity (with adequate privileges on concerned resources) to encrypt data at rest using an encryption key(s). The built-in/predefined IAM role Cloud KMS CryptoKey Decrypter allows the user/identity (with adequate privileges on concerned resources) to decrypt data at rest using an encryption key(s). Separation of duties is the concept of ensuring that one individual does not have all necessary permissions to be able to complete a malicious action. In Cloud KMS, this could be an action such as using a key to access and decrypt data a user should not normally have access to. Separation of duties is a business control typically used in larger organizations, meant to help avoid security or privacy incidents and errors. It is considered best practice. No user(s) should have Cloud KMS Admin and any of the Cloud KMS CryptoKey Encrypter/Decrypter, Cloud KMS CryptoKey Encrypter, Cloud KMS CryptoKey Decrypter roles assigned at the same time. Impact: Removed roles should be assigned to another user based on business needs. | K24: From Google Cloud Console 1. Go to IAM & Admin/IAM using https://console.cloud.google.com/iam-admin/iam 2. For any member having Cloud KMS Admin and any of the Cloud KMS CryptoKey Encrypter/Decrypter, Cloud KMS CryptoKey Encrypter, Cloud KMS CryptoKey Decrypter roles granted/assigned, click the Delete Bin icon to remove the role from the member. Note: Removing a role should be done based on the business requirement. | L24: 1. https://cloud.google.com/kms/docs/separation-of-duties | M24: v | N24: מערכת | O24: -
B25: 3.3 | C25: Data | D25: Protect | E25: הגדר בקרת גישה לנתונים | F25: Configure data access control lists based on a user’s need to know. Apply data access control lists, also known as access permissions, to local and remote file systems, databases, and applications. | G25: 2.3 Ensure That Retention Policies on Cloud Storage Buckets Used for Exporting Logs Are Configured Using Bucket Lock (Automated) | H25: Enabling retention policies on log buckets will protect logs stored in cloud storage buckets from being overwritten or accidentally deleted. It is recommended to set up retention policies and configure Bucket Lock on all storage buckets that are used as log sinks. Default Value: By default, storage buckets used as log sinks do not have retention policies and Bucket Lock configured. | I25: 2.3 | J25: Logs can be exported by creating one or more sinks that include a log filter and a destination. As Cloud Logging receives new log entries, they are compared against each sink. If a log entry matches a sink's filter, then a copy of the log entry is written to the destination. Sinks can be configured to export logs in storage buckets. It is recommended to configure a data retention policy for these cloud storage buckets and to lock the data retention policy; thus permanently preventing the policy from being reduced or removed. This way, if the system is ever compromised by an attacker or a malicious insider who wants to cover their tracks, the activity logs are definitely preserved for forensics and security investigations. Impact: Locking a bucket is an irreversible action. Once you lock a bucket, you cannot remove the retention policy from the bucket or decrease the retention period for the policy. You will then have to wait for the retention period for all items within the bucket before you can delete them, and then the bucket. | K25: From Google Cloud Console 1. If sinks are not configured, first follow the instructions in the recommendation: Ensure that sinks are configured for all Log entries. 2. For each storage bucket configured as a sink, go to the Cloud Storage browser at https://console.cloud.google.com/storage/browser/<BUCKET_NAME>. 3. Select the Bucket Lock tab near the top of the page. 4. In the Retention policy entry, click the Add Duration link. The Set a retention policy dialog box appears. 5. Enter the desired length of time for the retention period and click Save policy. 6. Set the Lock status for this retention policy to Locked. From Google Cloud CLI 1. To list all sinks destined to storage buckets: gcloud logging sinks list --folder=FOLDER_ID | --organization=ORGANIZATION_ID | --project=PROJECT_ID 2. For each storage bucket listed above, set a retention policy and lock it: gsutil retention set [TIME_DURATION] gs://[BUCKET_NAME] gsutil retention lock gs://[BUCKET_NAME] For more information, visit https://cloud.google.com/storage/docs/using-bucket-lock#set-policy. | L25: 1. https://cloud.google.com/storage/docs/bucket-lock 2. https://cloud.google.com/storage/docs/using-bucket-lock 3. https://cloud.google.com/storage/docs/bucket-lock | M25: v | N25: מערכת | O25: -
B26: 3.3 | C26: Data | D26: Protect | E26: הגדר בקרת גישה לנתונים | F26: Configure data access control lists based on a user’s need to know. Apply data access control lists, also known as access permissions, to local and remote file systems, databases, and applications. | G26: 2.15 Ensure 'Access Approval' is 'Enabled' (Automated) | H26: GCP Access Approval enables you to require your organizations' explicit approval whenever Google support try to access your projects. You can then select users within your organization who can approve these requests through giving them a security role in IAM. All access requests display which Google Employee requested them in an email or Pub/Sub message that you can choose to Approve. This adds an additional control and logging of who in your organization approved/denied these requests. | I26: 2.15 | J26: Controlling access to your information is one of the foundations of information security. Google Employees do have access to your organizations' projects for support reasons. With Access Approval, organizations can then be certain that their information is accessed by only approved Google Personnel. Impact: To use Access Approval your organization will need have enabled Access Transparency and have at one of the following support level: Enhanced or Premium. There will be subscription costs associated with these support levels, as well as increased storage costs for storing the logs. You will also not be able to turn the Access Transparency which Access Approval depends on, off yourself. To do so you will need to submit a service request to Google Cloud Support. There will also be additional overhead in managing user permissions. There may also be a potential delay in support times as Google Personnel will have to wait for their access to be approved. | K26: From Google Cloud Console 1. From the Google Cloud Home, within the project you wish to enable, click on the Navigation hamburger menu in the top left. Hover over the Security Menu. Select Access Approval in the middle of the column that opens. 2. The status will be displayed here. On this screen, there is an option to click Enroll. If it is greyed out and you see an error bar at the top of the screen that says Access Transparency is not enabled please view the corresponding reference within this section to enable it. 3. In the second screen click Enroll. Grant an IAM Group or User the role with permissions to Add Users to be Access Approval message Recipients 1. From the Google Cloud Home, within the project you wish to enable, click on the Navigation hamburger menu in the top left. Hover over the IAM and Admin. Select IAM in the middle of the column that opens. 2. Click the blue button the says + ADD at the top of the screen. 3. In the principals field, select a user or group by typing in their associated email address. 4. Click on the role field to expand it. In the filter field enter Access Approval Approver and select it. 5. Click save. Add a Group or User as an Approver for Access Approval Requests 1. As a user with the Access Approval Approver permission, within the project where you wish to add an email address to which request will be sent, click on the Navigation hamburger menu in the top left. Hover over the Security Menu. Select Access Approval in the middle of the column that opens. 2. Click Manage Settings 3. Under Set up approval notifications, enter the email address associated with a Google Cloud User or Group you wish to send Access Approval requests to. All future access approvals will be sent as emails to this address. From Google Cloud CLI 1. To update all services in an entire project, run the following command from an account that has permissions as an 'Approver for Access Approval Requests' gcloud access-approval settings update --project=<project name> --enrolled_services=all --notification_emails='<email recipient for access approval requests>@<domain name>' Default Value: By default Access Approval and its dependency of Access Transparency are not enabled. | L26: 1. https://cloud.google.com/cloud-provider-access-management/access-approval/docs 2. https://cloud.google.com/cloud-provider-access-management/access-approval/docs/overview 3. https://cloud.google.com/cloud-provider-access-management/access-approval/docs/quickstart-custom-key 4. https://cloud.google.com/cloud-provider-access-management/access-approval/docs/supported-services 5. https://cloud.google.com/cloud-provider-access-management/access-approval/docs/view-historical-requests | M26: v | N26: מערכת | O26: -
B27: 3.3 | C27: Data | D27: Protect | E27: הגדר בקרת גישה לנתונים | F27: Configure data access control lists based on a user’s need to know. Apply data access control lists, also known as access permissions, to local and remote file systems, databases, and applications. | G27: 4.9 Ensure That Compute Instances Do Not Have Public IP Addresses (Automated) | H27: Compute instances should not be configured to have external IP addresses. | I27: 4.9 | J27: To reduce your attack surface, Compute instances should not have public IP addresses. Instead, instances should be configured behind load balancers, to minimize the instance's exposure to the internet. Impact: Removing the external IP address from your Compute instance may cause some applications to stop working. | K27: Remediation: From Google Cloud Console 1. Go to the VM instances page by visiting: https://console.cloud.google.com/compute/instances. 2. Click on the instance name to go the the Instance detail page. 3. Click Edit. 4. For each Network interface, ensure that External IP is set to None. 5. Click Done and then click Save. From Google Cloud CLI 1. Describe the instance properties: gcloud compute instances describe <INSTANCE_NAME> --zone=<ZONE> 2. Identify the access config name that contains the external IP address. This access config appears in the following format: networkInterfaces: - accessConfigs: - kind: compute#accessConfig name: External NAT natIP: 130.211.181.55 type: ONE_TO_ONE_NAT 3. Delete the access config. gcloud compute instances delete-access-config <INSTANCE_NAME> --zone=<ZONE> --access-config-name <ACCESS_CONFIG_NAME> In the above example, the ACCESS_CONFIG_NAME is External NAT. The name of your access config might be different. Prevention: You can configure the Define allowed external IPs for VM instances Organization Policy to prevent VMs from being configured with public IP addresses. Learn more at: https://console.cloud.google.com/orgpolicies/compute-vmExternalIpAccess Default Value: By default, Compute instances have a public IP address. | L27: 1. https://cloud.google.com/load-balancing/docs/backend-service#backends_and_external_ip_addresses 2. https://cloud.google.com/compute/docs/instances/connecting-advanced#sshbetweeninstances 3. https://cloud.google.com/compute/docs/instances/connecting-to-instance 4. https://cloud.google.com/compute/docs/ip-addresses/reserve-static-external-ip-address#unassign_ip 5. https://cloud.google.com/resource-manager/docs/organization-policy/org-policy-constraints | M27: v | N27: ארגוני | O27: v
B28: 3.3 | C28: Data | D28: Protect | E28: הגדר בקרת גישה לנתונים | F28: Configure data access control lists based on a user’s need to know. Apply data access control lists, also known as access permissions, to local and remote file systems, databases, and applications. | G28: 5.1 Ensure That Cloud Storage Bucket Is Not Anonymously or Publicly Accessible (Automated) | H28: It is recommended that IAM policy on Cloud Storage bucket does not allows anonymous or public access. To implement Access restrictions on buckets, configuring Bucket IAM is preferred way than configuring Bucket ACL. On GCP console, "Edit Permissions" for bucket exposes IAM configurations only. Bucket ACLs are configured automatically as per need in order to implement/support User enforced Bucket IAM policy. In-case administrator changes bucket ACL using command-line(gsutils)/API bucket IAM also gets updated automatically. | I28: 5.1 | J28: Allowing anonymous or public access grants permissions to anyone to access bucket content. Such access might not be desired if you are storing any sensitive data. Hence, ensure that anonymous or public access to a bucket is not allowed. Impact: No storage buckets would be publicly accessible. You would have to explicitly administer bucket access. | K28: From Google Cloud Console 1. Go to Storage browser by visiting https://console.cloud.google.com/storage/browser. 2. Click on the bucket name to go to its Bucket details page. 3. Click on the Permissions tab. 4. Click Delete button in front of allUsers and allAuthenticatedUsers to remove that particular role assignment. From Google Cloud CLI Remove allUsers and allAuthenticatedUsers access. gsutil iam ch -d allUsers gs://BUCKET_NAME gsutil iam ch -d allAuthenticatedUsers gs://BUCKET_NAME Prevention: You can prevent Storage buckets from becoming publicly accessible by setting up the Domain restricted sharing organization policy at: https://console.cloud.google.com/iam-admin/orgpolicies/iam-allowedPolicyMemberDomains . Default Value: By Default, Storage buckets are not publicly shared. | L28: 1. https://cloud.google.com/storage/docs/access-control/iam-reference 2. https://cloud.google.com/storage/docs/access-control/making-data-public 3. https://cloud.google.com/storage/docs/gsutil/commands/iam | M28: v | N28: ארגוני | O28: v
B29: 3.3 | C29: Data | D29: Protect | E29: הגדר בקרת גישה לנתונים | F29: Configure data access control lists based on a user’s need to know. Apply data access control lists, also known as access permissions, to local and remote file systems, databases, and applications. | G29: 5.2 Ensure That Cloud Storage Buckets Have Uniform Bucket-Level Access Enabled (Automated) | H29: It is recommended that uniform bucket-level access is enabled on Cloud Storage buckets. | I29: 5.2 | J29: It is recommended to use uniform bucket-level access to unify and simplify how you grant access to your Cloud Storage resources. Cloud Storage offers two systems for granting users permission to access your buckets and objects: Cloud Identity and Access Management (Cloud IAM) and Access Control Lists (ACLs). These systems act in parallel - in order for a user to access a Cloud Storage resource, only one of the systems needs to grant the user permission. Cloud IAM is used throughout Google Cloud and allows you to grant a variety of permissions at the bucket and project levels. ACLs are used only by Cloud Storage and have limited permission options, but they allow you to grant permissions on a per-object basis. In order to support a uniform permissioning system, Cloud Storage has uniform bucket-level access. Using this feature disables ACLs for all Cloud Storage resources: access to Cloud Storage resources then is granted exclusively through Cloud IAM. Enabling uniform bucket-level access guarantees that if a Storage bucket is not publicly accessible, no object in the bucket is publicly accessible either. Impact: If you enable uniform bucket-level access, you revoke access from users who gain their access solely through object ACLs. Certain Google Cloud services, such as Stackdriver, Cloud Audit Logs, and Datastore, cannot export to Cloud Storage buckets that have uniform bucket-level access enabled. | K29: From Google Cloud Console 1. Open the Cloud Storage browser in the Google Cloud Console by visiting: https://console.cloud.google.com/storage/browser 2. In the list of buckets, click on the name of the desired bucket. 3. Select the Permissions tab near the top of the page. 4. In the text box that starts with This bucket uses fine-grained access control..., click Edit. 5. In the pop-up menu that appears, select Uniform. 6. Click Save. From Google Cloud CLI Use the on option in a uniformbucketlevelaccess set command: gsutil uniformbucketlevelaccess set on gs://BUCKET_NAME/ Prevention You can set up an Organization Policy to enforce that any new bucket has uniform bucket level access enabled. Learn more at: https://cloud.google.com/storage/docs/setting-org-policies#uniform-bucket Default Value: By default, Cloud Storage buckets do not have uniform bucket-level access enabled. | L29: 1. https://cloud.google.com/storage/docs/uniform-bucket-level-access 2. https://cloud.google.com/storage/docs/using-uniform-bucket-level-access 3. https://cloud.google.com/storage/docs/setting-org-policies#uniform-bucket | M29: v | N29: ארגוני | O29: v
B30: 3.3 | C30: Data | D30: Protect | E30: הגדר בקרת גישה לנתונים | F30: Configure data access control lists based on a user’s need to know. Apply data access control lists, also known as access permissions, to local and remote file systems, databases, and applications. | G30: 6.1.2 Ensure ‘Skip_show_database’ Database Flag for Cloud SQL MySQL Instance Is Set to ‘On’ (Automated) | H30: It is recommended to set skip_show_database database flag for Cloud SQL Mysql instance to on Additional Information: "WARNING: This patch modifies database flag values, which may require your instance to be restarted. Check the list of supported flags - https://cloud.google.com/sql/docs/mysql/flags - to see if your instance will be restarted when this patch is submitted. Note: some database flag settings can affect instance availability or stability, and remove the instance from the Cloud SQL SLA. For information about these flags, see Operational Guidelines." Note: Configuring the above flag restarts the Cloud SQL instance. | I30: 6.1.2 | J30: skip_show_database' database flag prevents people from using the SHOW DATABASES statement if they do not have the SHOW DATABASES privilege. This can improve security if you have concerns about users being able to see databases belonging to other users. Its effect depends on the SHOW DATABASES privilege: If the variable value is ON, the SHOW DATABASES statement is permitted only to users who have the SHOW DATABASES privilege, and the statement displays all database names. If the value is OFF, SHOW DATABASES is permitted to all users, but displays the names of only those databases for which the user has the SHOW DATABASES or other privilege. This recommendation is applicable to Mysql database instances. | K30: From Google Cloud Console 1. Go to the Cloud SQL Instances page in the Google Cloud Console by visiting https://console.cloud.google.com/sql/instances. 2. Select the Mysql instance for which you want to enable to database flag. 3. Click Edit. 4. Scroll down to the Flags section. 5. To set a flag that has not been set on the instance before, click Add item, choose the flag skip_show_database from the drop-down menu, and set its value to on. 6. Click Save to save your changes. 7. Confirm your changes under Flags on the Overview page. From Google Cloud CLI 1. List all Cloud SQL database Instances gcloud sql instances list 2. Configure the skip_show_database database flag for every Cloud SQL Mysql database instance using the below command. gcloud sql instances patch INSTANCE_NAME --database-flags skip_show_database=on Note : This command will overwrite all database flags previously set. To keep those and add new ones, include the values for all flags you want set on the instance; any flag not specifically included is set to its default value. For flags that do not take a value, specify the flag name followed by an equals sign ("="). | L30: 1. https://cloud.google.com/sql/docs/mysql/flags 2. https://dev.mysql.com/doc/refman/5.7/en/server-system-variables.html#sysvar_skip_show_database | M30: v | N30: מערכת | O30: -
B31: 3.3 | C31: Data | D31: Protect | E31: הגדר בקרת גישה לנתונים | F31: Configure data access control lists based on a user’s need to know. Apply data access control lists, also known as access permissions, to local and remote file systems, databases, and applications. | G31: 6.3.2 Ensure that the 'cross db ownership chaining' database flag for Cloud SQL SQL Server instance is set to 'off' (Automated) | H31: It is recommended to set cross db ownership chaining database flag for Cloud SQL SQL Server instance to off. | I31: 6.3.2 | J31: Use the cross db ownership for chaining option to configure cross-database ownership chaining for an instance of Microsoft SQL Server. This server option allows you to control cross-database ownership chaining at the database level or to allow cross-database ownership chaining for all databases. Enabling cross db ownership is not recommended unless all of the databases hosted by the instance of SQL Server must participate in cross-database ownership chaining and you are aware of the security implications of this setting. This recommendation is applicable to SQL Server database instances. Impact: Updating flags may cause the database to restart. This may cause it to unavailable for a short amount of time, so this is best done at a time of low usage. You should also determine if the tables in your databases reference another table without using credentials for that database, as turning off cross database ownership will break this relationship. | K31: From Google Cloud Console 1. Go to the Cloud SQL Instances page in the Google Cloud Console by visiting https://console.cloud.google.com/sql/instances. 2. Select the SQL Server instance for which you want to enable to database flag. 3. Click Edit. 4. Scroll down to the Flags section. 5. To set a flag that has not been set on the instance before, click Add item, choose the flag cross db ownership chaining from the drop-down menu, and set its value to off. 6. Click Save. 7. Confirm the changes under Flags on the Overview page. From Google Cloud CLI 1. Configure the cross db ownership chaining database flag for every Cloud SQL SQL Server database instance using the below command: gcloud sql instances patch <INSTANCE_NAME> --database-flags "cross db ownership chaining=off" Note: This command will overwrite all database flags previously set. To keep those and add new ones, include the values for all flags to be set on the instance; any flag not specifically included is set to its default value. For flags that do not take a value, specify the flag name followed by an equals sign ("="). Default Value: As you have to manually turn on this flag, the default value for this is 'On'. Though you would have had to design your database schema from the start to include this feature, it often is not enabled. | L31: 1. https://cloud.google.com/sql/docs/sqlserver/flags 2. https://docs.microsoft.com/en-us/sql/database-engine/configure-windows/cross-db-ownership-chaining-server-configuration-option?view=sql-server-ver15 | M31: v | N31: מערכת | O31: -
B32: 3.3 | C32: Data | D32: Protect | E32: הגדר בקרת גישה לנתונים | F32: Configure data access control lists based on a user’s need to know. Apply data access control lists, also known as access permissions, to local and remote file systems, databases, and applications. | G32: 6.3.7 Ensure that the 'contained database authentication' database flag for Cloud SQL on the SQL Server instance is set to 'off' (Automated) | H32: It is recommended to set contained database authentication database flag for Cloud SQL on the SQL Server instance to off. | I32: 6.3.7 | J32: A contained database includes all database settings and metadata required to define the database and has no configuration dependencies on the instance of the Database Engine where the database is installed. Users can connect to the database without authenticating a login at the Database Engine level. Isolating the database from the Database Engine makes it possible to easily move the database to another instance of SQL Server. Contained databases have some unique threats that should be understood and mitigated by SQL Server Database Engine administrators. Most of the threats are related to the USER WITH PASSWORD authentication process, which moves the authentication boundary from the Database Engine level to the database level, hence this is recommended to disable this flag. This recommendation is applicable to SQL Server database instances. Impact: When contained database authentication is off (0) for the instance, contained databases cannot be created, or attached to the Database Engine. Turning on logging will increase the required storage over time. Mismanaged logs may cause your storage costs to increase.Setting custom flags via command line on certain instances will cause all omitted flags to be reset to defaults. This may cause you to lose custom flags and could result in unforeseen complications or instance restarts. Because of this, it is recommended you apply these flags changes during a period of low usage. | K32: From Google Cloud Console 1. Go to the Cloud SQL Instances page in the Google Cloud Console by visiting https://console.cloud.google.com/sql/instances. 2. Select the SQL Server instance for which you want to enable to database flag. 3. Click Edit. 4. Scroll down to the Flags section. 5. To set a flag that has not been set on the instance before, click Add item, choose the flag contained database authentication from the drop-down menu, and set its value to off. 6. Click Save. 7. Confirm the changes under Flags on the Overview page. From Google Cloud CLI 1. Configure the contained database authentication database flag for every Cloud SQL SQL Server database instance using the below command: gcloud sql instances patch <INSTANCE_NAME> --database-flags "contained database authentication=off" Note: This command will overwrite all database flags previously set. To keep those and add new ones, include the values for all flags to be set on the instance; any flag not specifically included is set to its default value. For flags that do not take a value, specify the flag name followed by an equals sign ("="). | L32: 1. https://cloud.google.com/sql/docs/sqlserver/flags 2. https://docs.microsoft.com/en-us/sql/database-engine/configure-windows/contained-database-authentication-server-configuration-option?view=sql-server-ver15 3. https://docs.microsoft.com/en-us/sql/relational-databases/databases/security-best-practices-with-contained-databases?view=sql-server-ver15 | M32: v | N32: מערכת | O32: -
... B35: 3.3 | C35: Data | D35: Protect | E35: הגדר בקרת גישה לנתונים | F35: Configure data access control lists based on a user’s need to know. Apply data access control lists, also known as access permissions, to local and remote file systems, databases, and applications. | G35: 7.1 Ensure That BigQuery Datasets Are Not Anonymously or Publicly Accessible (Automated) | H35: It is recommended that the IAM policy on BigQuery datasets does not allow anonymous and/or public access. | I35: 7.1 | J35: Granting permissions to allUsers or allAuthenticatedUsers allows anyone to access the dataset. Such access might not be desirable if sensitive data is being stored in the dataset. Therefore, ensure that anonymous and/or public access to a dataset is not allowed. Impact: The dataset is not publicly accessible. Explicit modification of IAM privileges would be necessary to make them publicly accessible. | K35: Remediation: From Google Cloud Console 1. Go to BigQuery by visiting: https://console.cloud.google.com/bigquery. 2. Select the dataset from 'Resources'. 3. Click SHARING near the right side of the window and select Permissions. 4. Review each attached role. 5. Click the delete icon for each member allUsers or allAuthenticatedUsers. On the popup click Remove. From Google Cloud CLI List the name of all datasets. bq ls Retrieve the data set details: bq show --format=prettyjson PROJECT_ID:DATASET_NAME > PATH_TO_FILE In the access section of the JSON file, update the dataset information to remove all roles containing allUsers or allAuthenticatedUsers. Update the dataset: bq update --source PATH_TO_FILE PROJECT_ID:DATASET_NAME Prevention: You can prevent Bigquery dataset from becoming publicly accessible by setting up the Domain restricted sharing organization policy at: https://console.cloud.google.com/iam-admin/orgpolicies/iam-allowedPolicyMemberDomains . Default Value: By default, BigQuery datasets are not publicly accessible. | L35: 1. https://cloud.google.com/bigquery/docs/dataset-access-controls | M35: v | N35: מערכת | O35: v
B36: 3.4 | C36: Data | D36: Protect | E36: יש להגדיר אכיפת Data Ritention | F36: Retain data according to the enterprise’s data management process. Data retention must include both minimum and maximum timelines. | G36: - | H36: - | I36: - | J36: - | K36: - | L36: - | N36: ארגוני | O36: -
B37: 3.5 | C37: Data | D37: Protect | E37: יש לוודא השמדת מידע מאובטחת בסיום תקופת ה Ritention | F37: Securely dispose of data as outlined in the enterprise’s data management process. Ensure the disposal process and method are commensurate with the data sensitivity. | G37: - | H37: - | I37: - | J37: - | K37: - | L37: - | N37: ארגוני | O37: -
B38: 3.7 | C38: Data | D38: Identify | E38: הקמה ותחזוקה של תוכנית סיווג נתונים | F38: Establish and maintain an overall data classification scheme for the enterprise. Enterprises may use labels, such as “Sensitive,” “Confidential,” and “Public,” and classify their data according to those labels. Review and update the classification scheme annually, or when significant enterprise changes occur that could impact this Safeguard. | G38: - | H38: - | I38: - | J38: - | K38: - | L38: - | N38: ארגוני | O38: -
B39: 3.8 | C39: Data | D39: Identify | E39: הגדרת אופן זרימת נתונים | F39: Document data flows. Data flow documentation includes service provider data flows and should be based on the enterprise’s data management process. Review and update documentation annually, or when significant enterprise changes occur that could impact this Safeguard. | G39: - | H39: - | I39: - | J39: - | K39: - | L39: - | N39: ארגוני | O39: -
B40: 3.1 | C40: Data | D40: Protect | E40: הצפנת נתונים רגישים בתנועה | F40: Encrypt sensitive data in transit. Example implementations can include: Transport Layer Security (TLS) and Open Secure Shell (OpenSSH). | G40: 3.9 Ensure No HTTPS or SSL Proxy Load Balancers Permit SSL Policies With Weak Cipher Suites (Manual) | H40: Secure Sockets Layer (SSL) policies determine what port Transport Layer Security (TLS) features clients are permitted to use when connecting to load balancers. To prevent usage of insecure features, SSL policies should use (a) at least TLS 1.2 with the MODERN profile; or (b) the RESTRICTED profile, because it effectively requires clients to use TLS 1.2 regardless of the chosen minimum TLS version; or (3) a CUSTOM profile that does not support any of the following features: TLS_RSA_WITH_AES_128_GCM_SHA256 TLS_RSA_WITH_AES_256_GCM_SHA384 TLS_RSA_WITH_AES_128_CBC_SHA TLS_RSA_WITH_AES_256_CBC_SHA TLS_RSA_WITH_3DES_EDE_CBC_SHA | I40: 3.9 | J40: Load balancers are used to efficiently distribute traffic across multiple servers. Both SSL proxy and HTTPS load balancers are external load balancers, meaning they distribute traffic from the Internet to a GCP network. GCP customers can configure load balancer SSL policies with a minimum TLS version (1.0, 1.1, or 1.2) that clients can use to establish a connection, along with a profile (Compatible, Modern, Restricted, or Custom) that specifies permissible cipher suites. To comply with users using outdated protocols, GCP load balancers can be configured to permit insecure cipher suites. In fact, the GCP default SSL policy uses a minimum TLS version of 1.0 and a Compatible profile, which allows the widest range of insecure cipher suites. As a result, it is easy for customers to configure a load balancer without even knowing that they are permitting outdated cipher suites. Impact: Creating more secure SSL policies can prevent clients using older TLS versions from establishing a connection. | K40: From Google Cloud Console If the TargetSSLProxy or TargetHttpsProxy does not have an SSL policy configured, create a new SSL policy. Otherwise, modify the existing insecure policy. 1. Navigate to the SSL Policies page by visiting: https://console.cloud.google.com/net-security/sslpolicies 2. Click on the name of the insecure policy to go to its SSL policy details page. 3. Click EDIT. 4. Set Minimum TLS version to TLS 1.2. 5. Set Profile to Modern or Restricted. 6. Alternatively, if teh user selects the profile Custom, make sure that the following features are disabled: TLS_RSA_WITH_AES_128_GCM_SHA256 TLS_RSA_WITH_AES_256_GCM_SHA384 TLS_RSA_WITH_AES_128_CBC_SHA TLS_RSA_WITH_AES_256_CBC_SHA TLS_RSA_WITH_3DES_EDE_CBC_SHA From Google Cloud CLI 1. For each insecure SSL policy, update it to use secure cyphers: gcloud compute ssl-policies update NAME [--profile COMPATIBLE|MODERN|RESTRICTED|CUSTOM] --min-tls-version 1.2 [--custom-features FEATURES] 2. If the target proxy has a GCP default SSL policy, use the following command corresponding to the proxy type to update it. gcloud compute target-ssl-proxies update TARGET_SSL_PROXY_NAME --ssl-policy SSL_POLICY_NAME gcloud compute target-https-proxies update TARGET_HTTPS_POLICY_NAME --ssl-policy SSL_POLICY_NAME Default Value: The GCP default SSL policy is the least secure setting: Min TLS 1.0 and Compatible profile | L40: 1. https://cloud.google.com/load-balancing/docs/use-ssl-policies 2. https://nvlpubs.nist.gov/nistpubs/SpecialPublications/NIST.SP.800-52r2.pdf | M40: v | N40: ארגוני | O40: v
B41: 3.1 | C41: Data | D41: Protect | E41: הצפנת נתונים רגישים בתנועה | F41: Encrypt sensitive data in transit. Example implementations can include: Transport Layer Security (TLS) and Open Secure Shell (OpenSSH). | G41: 4.3 Ensure “Block Project-Wide SSH Keys” Is Enabled for VM Instances (Automated) | H41: It is recommended to use Instance specific SSH key(s) instead of using common/shared project-wide SSH key(s) to access Instances. | I41: 4.3 | J41: Project-wide SSH keys are stored in Compute/Project-meta-data. Project wide SSH keys can be used to login into all the instances within project. Using project-wide SSH keys eases the SSH key management but if compromised, poses the security risk which can impact all the instances within project. It is recommended to use Instance specific SSH keys which can limit the attack surface if the SSH keys are compromised. Impact: Users already having Project-wide ssh key pairs and using third party SSH clients will lose access to the impacted Instances. For Project users using gcloud or GCP Console based SSH option, no manual key creation and distribution is required and will be handled by GCE (Google Compute Engine) itself. To access Instance using third party SSH clients Instance specific SSH key pairs need to be created and distributed to the required users. | K41: From Google Cloud Console 1. Go to the VM instances page by visiting: https://console.cloud.google.com/compute/instances. It will list all the instances in your project. 2. Click on the name of the Impacted instance 3. Click Edit in the toolbar 4. Under SSH Keys, go to the Block project-wide SSH keys checkbox 5. To block users with project-wide SSH keys from connecting to this instance, select Block project-wide SSH keys 6. Click Save at the bottom of the page 7. Repeat steps for every impacted Instance From Google Cloud CLI To block project-wide public SSH keys, set the metadata value to TRUE: gcloud compute instances add-metadata <INSTANCE_NAME> --metadata block-project-ssh-keys=TRUE Default Value: By Default Block Project-wide SSH keys is not enabled. | L41: 1. https://cloud.google.com/compute/docs/instances/adding-removing-ssh-keys 2. https://cloud.google.com/sdk/gcloud/reference/topic/formats | M41: v | N41: מערכת | O41: -
B42: 3.1 | C42: Data | D42: Protect | E42: הצפנת נתונים רגישים בתנועה | F42: Encrypt sensitive data in transit. Example implementations can include: Transport Layer Security (TLS) and Open Secure Shell (OpenSSH). | G42: 4.10 Ensure That App Engine Applications Enforce HTTPS Connections (Manual) | H42: In order to maintain the highest level of security all connections to an application should be secure by default. | I42: 4.10 | J42: Insecure HTTP connections maybe subject to eavesdropping which can expose sensitive data. Impact: All connections to appengine will automatically be redirected to the HTTPS endpoint ensuring that all connections are secured by TLS. | K42: Add a line to the app.yaml file controlling the application which enforces secure connections. For example handlers: - url: /.* **secure: always** redirect_http_response_code: 301 script: auto [https://cloud.google.com/appengine/docs/standard/python3/config/appref] Default Value: By default both HTTP and HTTP are supported | L42: 1. https://cloud.google.com/appengine/docs/standard/python3/config/appref 2. https://cloud.google.com/appengine/docs/flexible/nodejs/configuring-your-app-with-app-yaml | M42: v | N42: מערכת | O42: -
B43: 3.1 | C43: Data | D43: Protect | E43: הצפנת נתונים רגישים בתנועה | F43: Encrypt sensitive data in transit. Example implementations can include: Transport Layer Security (TLS) and Open Secure Shell (OpenSSH). | G43: 6.4 Ensure That the Cloud SQL Database Instance Requires All Incoming Connections To Use SSL (Automated) | H43: It is recommended to enforce all incoming connections to SQL database instance to use SSL. | I43: 6.4 | J43: SQL database connections if successfully trapped (MITM); can reveal sensitive data like credentials, database queries, query outputs etc. For security, it is recommended to always use SSL encryption when connecting to your instance. This recommendation is applicable for Postgresql, MySql generation 1, MySql generation 2 and SQL Server 2017 instances. Impact: After enforcing SSL connection, existing client will not be able to communicate with SQL server unless configured with appropriate client-certificates to communicate to SQL database instance. | K43: From Google Cloud Console 1. Go to https://console.cloud.google.com/sql/instances. 2. Click on an instance name to see its configuration overview. 3. In the left-side panel, select Connections. 4. In the SSL connections section, click Allow only SSL connections. 5. Under Configure SSL server certificates click Create new certificate. 6. Under Configure SSL client certificates click Create a client certificate. 7. Follow the instructions shown to learn how to connect to your instance. From Google Cloud CLI To enforce SSL encryption for an instance run the command: gcloud sql instances patch <INSTANCE_NAME> --require-ssl Note: RESTART is required for type MySQL Generation 1 Instances (backendType: FIRST_GEN) to get this configuration in effect. Default Value: By default parameter settings: ipConfiguration: requireSsl is not set which is equivalent to requireSsl:false. | L43: 1. https://cloud.google.com/sql/docs/postgres/configure-ssl-instance/ | M43: v | N43: מערכת | O43: -
B44: 3.11 | C44: Data | D44: Protect | E44: הצפנת נתונים רגישים במנוחה | F44: Encrypt sensitive data at rest on servers, applications, and databases containing sensitive data. Storage-layer encryption, also known as server-side encryption, meets the minimum requirement of this Safeguard. Additional encryption methods may include application-layer encryption, also known as client-side encryption, where access to the data storage device(s) does not permit access to the plain-text data. | G44: 1.10 Ensure KMS Encryption Keys Are Rotated Within a Period of 90 Days (Automated) | H44: Google Cloud Key Management Service stores cryptographic keys in a hierarchical structure designed for useful and elegant access control management. The format for the rotation schedule depends on the client library that is used. For the gcloud command-line tool, the next rotation time must be in ISO or RFC3339 format, and the rotation period must be in the form INTEGER[UNIT], where units can be one of seconds (s), minutes (m), hours (h) or days (d). Additional Information: • Key rotation does NOT re-encrypt already encrypted data with the newly generated key version. If you suspect unauthorized use of a key, you should re-encrypt the data protected by that key and then disable or schedule destruction of the prior key version. • It is not recommended to rely solely on irregular rotation, but rather to use irregular rotation if needed in conjunction with a regular rotation schedule. | I44: 1.10 | J44: Set a key rotation period and starting time. A key can be created with a specified rotation period, which is the time between when new key versions are generated automatically. A key can also be created with a specified next rotation time. A key is a named object representing a cryptographic key used for a specific purpose. The key material, the actual bits used for encryption, can change over time as new key versions are created. A key is used to protect some corpus of data. A collection of files could be encrypted with the same key and people with decrypt permissions on that key would be able to decrypt those files. Therefore, it's necessary to make sure the rotation period is set to a specific time. Impact: After a successful key rotation, the older key version is required in order to decrypt the data encrypted by that previous key version. | K44: From Google Cloud Console 1. Go to Cryptographic Keys by visiting: https://console.cloud.google.com/security/kms. 2. Click on the specific key ring 3. From the list of keys, choose the specific key and Click on Right side pop up the blade (3 dots). 4. Click on Edit rotation period. 5. On the pop-up window, Select a new rotation period in days which should be less than 90 and then choose Starting on date (date from which the rotation period begins). From Google Cloud CLI 1. Update and schedule rotation by ROTATION_PERIOD and NEXT_ROTATION_TIME for each key: gcloud kms keys update new --keyring=KEY_RING --location=LOCATION --next-rotation-time=NEXT_ROTATION_TIME --rotation-period=ROTATION_PERIOD Default Value: By default, KMS encryption keys are rotated every 90 days. | L44: 1. https://cloud.google.com/kms/docs/key-rotation#frequency_of_key_rotation 2. https://cloud.google.com/kms/docs/re-encrypt-data | M44: v | N44: מערכת | O44: -
B45: 3.11 | C45: Data | D45: Protect | E45: הצפנת נתונים רגישים במנוחה | F45: Encrypt sensitive data at rest on servers, applications, and databases containing sensitive data. Storage-layer encryption, also known as server-side encryption, meets the minimum requirement of this Safeguard. Additional encryption methods may include application-layer encryption, also known as client-side encryption, where access to the data storage device(s) does not permit access to the plain-text data. | G45: 1.17 Ensure that Dataproc Cluster is encrypted using Customer-Managed Encryption Key (Automated) | H45: When you use Dataproc, cluster and job data is stored on Persistent Disks (PDs) associated with the Compute Engine VMs in your cluster and in a Cloud Storage staging bucket. This PD and bucket data is encrypted using a Google-generated data encryption key (DEK) and key encryption key (KEK). The CMEK feature allows you to create, use, and revoke the key encryption key (KEK). Google still controls the data encryption key (DEK). | I45: 1.17 | J45: "Cloud services offer the ability to protect data related to those services using encryption keys managed by the customer within Cloud KMS. These encryption keys are called customer-managed encryption keys (CMEK). When you protect data in Google Cloud services with CMEK, the CMEK key is within your control. Impact: Using Customer Managed Keys involves additional overhead in maintenance by administrators. | K45: From Google Cloud Console 1. Login to the GCP Console and navigate to the Dataproc Cluster page by visiting https://console.cloud.google.com/dataproc/clusters. 2. Select the project from the projects dropdown list. 3. On the Dataproc Cluster page, click on the Create Cluster to create a new cluster with Customer managed encryption keys. 4. On Create a cluster page, perform below steps: • Inside Set up cluster section perform below steps: In the Name textbox, provide a name for your cluster. o From Location select the location in which you want to deploy a cluster. o Configure other configurations as per your requirements. • Inside Configure Nodes and Customize cluster section configure the settings as per your requirements. • Inside Manage security section, perform below steps: o From Encryption, select Customer-managed key. o Select a customer-managed key from dropdown list. o Ensure that the selected KMS Key have Cloud KMS CryptoKey Encrypter/Decrypter role assign to Dataproc Cluster service account ("serviceAccount:service-<project_number>@compute-system.iam.gserviceaccount.com"). o Click on Create to create a cluster. • Once the cluster is created migrate all your workloads from the older cluster to the new cluster and delete the old cluster by performing the below steps: o On the Clusters page, select the old cluster and click on Delete cluster. o On the Confirm deletion window, click on Confirm to delete the cluster. o Repeat step above for other Dataproc clusters available in the selected project. • Change the project from the project dropdown list and repeat the remediation procedure for other Dataproc clusters available in other projects. From Google Cloud CLI Before creating cluster ensure that the selected KMS Key have Cloud KMS CryptoKey Encrypter/Decrypter role assign to Dataproc Cluster service account ("serviceAccount:service-<project_number>@compute-system.iam.gserviceaccount.com"). Run clusters create command to create new cluster with customer-managed key: gcloud dataproc clusters create <cluster_name> --region=us-central1 --gce-pd-kms-key=<key_resource_name> The above command will create a new cluster in the selected region. Once the cluster is created migrate all your workloads from the older cluster to the new cluster and Run clusters delete command to delete cluster: gcloud dataproc clusters delete <cluster_name> --region=us-central1 Repeat step no. 1 to create a new Dataproc cluster. Change the project by running the below command and repeat the remediation procedure for other projects: gcloud config set project <project_ID>" | L45: 1. https://cloud.google.com/docs/security/encryption/default-encryption | M45: v | N45: מערכת | O45: -
B46: 3.11 | C46: Data | D46: Protect | E46: הצפנת נתונים רגישים במנוחה | F46: Encrypt sensitive data at rest on servers, applications, and databases containing sensitive data. Storage-layer encryption, also known as server-side encryption, meets the minimum requirement of this Safeguard. Additional encryption methods may include application-layer encryption, also known as client-side encryption, where access to the data storage device(s) does not permit access to the plain-text data. | G46: 1.18 Ensure Secrets are Not Stored in Cloud Functions Environment Variables by Using Secret Manager (Manual) | H46: Google Cloud Functions allow you to host serverless code that is executed when an event is triggered, without the requiring the management a host operating system. These functions can also store environment variables to be used by the code that may contain authentication or other information that needs to remain confidential. Default Value: By default Secret Manager is not enabled. Additional Information: There are slight additional costs to using the Secret Manager API. Review the documentation to determine your organizations' needs. | I46: 1.18 | J46: It is recommended to use the Secret Manager, because environment variables are stored unencrypted, and accessible for all users who have access to the code. Impact: There should be no impact on the Cloud Function. There are minor costs after 10,000 requests a month to the Secret Manager API as well for a high use of other functions. Modifying the Cloud Function to use the Secret Manager may prevent it running to completion. | K46: Enable Secret Manager API for your Project From Google Cloud Console 1. Within the project you wish to enable, select the Navigation hamburger menu in the top left. Hover over 'APIs & Services' to under the heading 'Serverless', then select 'Enabled APIs & Services' in the menu that opens up. 2. Click the button '+ Enable APIS and Services' 3. In the Search bar, search for 'Secret Manager API' and select it. 4. Click the blue box that says 'Enable'. From Google Cloud CLI 1. Within the project you wish to enable the API in, run the following command. gcloud services enable Secret Manager API Reviewing Environment Variables That Should Be Migrated to Secret Manager From Google Cloud Console 1. Log in to the Google Cloud Web Portal (https://console.cloud.google.com/) 2. Go to Cloud Functions 3. Click on a function name from the list 4. Click on Edit and review the Runtime environment for variables that should be secrets. Leave this list open for the next step. From Google Cloud CLI 1. To view a list of your cloud functions run gcloud functions list 2. For each cloud function run the following command. gcloud functions describe <function_name> 3. Review the settings of the buildEnvironmentVariables and environmentVariables. Keep this information for the next step. Migrating Environment Variables to Secrets within the Secret Manager From Google Cloud Console 1. Go to the Secret Manager page in the Cloud Console. 2. On the Secret Manager page, click Create Secret. 3. On the Create secret page, under Name, enter the name of the Environment Variable you are replacing. This will then be the Secret Variable you will reference in your code. 4. You will also need to add a version. This is the actual value of the variable that will be referenced from the code. To add a secret version when creating the initial secret, in the Secret value field, enter the value from the Environment Variable you are replacing. 5. Leave the Regions section unchanged. 6. Click the Create secret button. 7. Repeat for all Environment Variables From Google Cloud CLI 1. Run the following command with the Environment Variable name you are replacing in the <secret-id>. It is most secure to point this command to a file with the Environment Variable value located in it, as if you entered it via command line it would show up in your shell’s command history. gcloud secrets create <secret-id> --data-file="/path/to/file.txt" Granting your Runtime's Service Account Access to Secrets From Google Cloud Console 1. Within the project containing your runtime login with account that has the 'roles/secretmanager.secretAccessor' permission. 2. Select the Navigation hamburger menu in the top left. Hover over 'Security' to under the then select 'Secret Manager' in the menu that opens up. 3. Click the name of a secret listed in this screen. 4. If it is not already open, click Show Info Panel in this screen to open the panel. 5.In the info panel, click Add principal. 6.In the New principals field, enter the service account your function uses for its identity. (If you need help locating or updating your runtime's service account, please see the 'docs/securing/function-identity#runtime_service_account' reference.) 5. In the Select a role dropdown, choose Secret Manager and then Secret Manager Secret Accessor. From Google Cloud CLI As of the time of writing, using Google CLI to list Runtime variables is only in beta. Because this is likely to change we are not including it here. Modifying the Code to use the Secrets in Secret Manager From Google Cloud Console This depends heavily on which language your runtime is in. For the sake of the brevity of this recommendation, please see the '/docs/creating-and-accessing-secrets#access' reference for language specific instructions. From Google Cloud CLI This depends heavily on which language your runtime is in. For the sake of the brevity of this recommendation, please see the' /docs/creating-and-accessing-secrets#access' reference for language specific instructions. Deleting the Insecure Environment Variables - Be certain to do this step last. Removing variables from code actively referencing them will prevent it from completing successfully. From Google Cloud Console 1. Select the Navigation hamburger menu in the top left. Hover over 'Security' then select 'Secret Manager' in the menu that opens up. 2. Click the name of a function. Click Edit. 3. Click Runtime, build and connections settings to expand the advanced configuration options. 4. Click 'Security’. Hover over the secret you want to remove, then click 'Delete'. 5. Click Next. Click Deploy. The latest version of the runtime will now reference the secrets in Secret Manager. From Google Cloud CLI gcloud functions deploy <Function name>--remove-env-vars <env vars> If you need to find the env vars to remove, they are from the step where ‘gcloud functions describe <function_name>’ was run. | L46: 1. https://cloud.google.com/functions/docs/configuring/env-var#managing_secrets 2. https://cloud.google.com/secret-manager/docs/overview | M46: v | N46: מערכת | O46: -
B47: 3.11 | C47: Data | D47: Protect | E47: הצפנת נתונים רגישים במנוחה | F47: Encrypt sensitive data at rest on servers, applications, and databases containing sensitive data. Storage-layer encryption, also known as server-side encryption, meets the minimum requirement of this Safeguard. Additional encryption methods may include application-layer encryption, also known as client-side encryption, where access to the data storage device(s) does not permit access to the plain-text data. | G47: 4.7 Ensure VM Disks for Critical VMs Are Encrypted With Customer-Supplied Encryption Keys (CSEK) (Automated) | H47: Customer-Supplied Encryption Keys (CSEK) are a feature in Google Cloud Storage and Google Compute Engine. If you supply your own encryption keys, Google uses your key to protect the Google-generated keys used to encrypt and decrypt your data. By default, Google Compute Engine encrypts all data at rest. Compute Engine handles and manages this encryption for you without any additional actions on your part. However, if you wanted to control and manage this encryption yourself, you can provide your own encryption keys. | I47: 4.7 | J47: By default, Google Compute Engine encrypts all data at rest. Compute Engine handles and manages this encryption for you without any additional actions on your part. However, if you wanted to control and manage this encryption yourself, you can provide your own encryption keys. If you provide your own encryption keys, Compute Engine uses your key to protect the Google-generated keys used to encrypt and decrypt your data. Only users who can provide the correct key can use resources protected by a customer-supplied encryption key. Google does not store your keys on its servers and cannot access your protected data unless you provide the key. This also means that if you forget or lose your key, there is no way for Google to recover the key or to recover any data encrypted with the lost key. At least business critical VMs should have VM disks encrypted with CSEK. Impact: If you lose your encryption key, you will not be able to recover the data. | K47: Currently there is no way to update the encryption of an existing disk. Therefore you should create a new disk with Encryption set to Customer supplied. From Google Cloud Console 1. Go to Compute Engine Disks by visiting: https://console.cloud.google.com/compute/disks. 2. Click CREATE DISK. 3. Set Encryption type to Customer supplied, 4. Provide the Key in the box. 5. Select Wrapped key. 6. Click Create. From Google Cloud CLI In the gcloud compute tool, encrypt a disk using the --csek-key-file flag during instance creation. If you are using an RSA-wrapped key, use the gcloud beta component: gcloud compute instances create <INSTANCE_NAME> --csek-key-file <example-file.json> To encrypt a standalone persistent disk: gcloud compute disks create <DISK_NAME> --csek-key-file <example-file.json> Default Value: By default, VM disks are encrypted with Google-managed keys. They are not encrypted with Customer-Supplied Encryption Keys. | L47: 1. https://cloud.google.com/compute/docs/disks/customer-supplied-encryption#encrypt_a_new_persistent_disk_with_your_own_keys 2. https://cloud.google.com/compute/docs/reference/rest/v1/disks/get 3. https://cloud.google.com/compute/docs/disks/customer-supplied-encryption#key_file | M47: v | N47: מערכת | O47: -
B48: 3.11 | C48: Data | D48: Protect | E48: הצפנת נתונים רגישים במנוחה | F48: Encrypt sensitive data at rest on servers, applications, and databases containing sensitive data. Storage-layer encryption, also known as server-side encryption, meets the minimum requirement of this Safeguard. Additional encryption methods may include application-layer encryption, also known as client-side encryption, where access to the data storage device(s) does not permit access to the plain-text data. | G48: 4.11 Ensure That Compute Instances Have Confidential Computing Enabled (Automated) | H48: Google Cloud encrypts data at-rest and in-transit, but customer data must be decrypted for processing. Confidential Computing is a breakthrough technology which encrypts data in-use—while it is being processed. Confidential Computing environments keep data encrypted in memory and elsewhere outside the central processing unit (CPU). Confidential VMs leverage the Secure Encrypted Virtualization (SEV) feature of AMD EPYC™ CPUs. Customer data will stay encrypted while it is used, indexed, queried, or trained on. Encryption keys are generated in hardware, per VM, and not exportable. Thanks to built-in hardware optimizations of both performance and security, there is no significant performance penalty to Confidential Computing workloads. | I48: 4.11 | J48: Confidential Computing enables customers' sensitive code and other data encrypted in memory during processing. Google does not have access to the encryption keys. Confidential VM can help alleviate concerns about risk related to either dependency on Google infrastructure or Google insiders' access to customer data in the clear. Impact: • Confidential Computing for Compute instances does not support live migration. Unlike regular Compute instances, Confidential VMs experience disruptions during maintenance events like a software or hardware update. • Additional charges may be incurred when enabling this security feature. See https://cloud.google.com/compute/confidential-vm/pricing for more info. | K48: Confidential Computing can only be enabled when an instance is created. You must delete the current instance and create a new one. From Google Cloud Console 1. Go to the VM instances page by visiting: https://console.cloud.google.com/compute/instances. 2. Click CREATE INSTANCE. 3. Fill out the desired configuration for your instance. 4. Under the Confidential VM service section, check the option Enable the Confidential Computing service on this VM instance. 5. Click Create. From Google Cloud CLI Create a new instance with Confidential Compute enabled. gcloud compute instances create <INSTANCE_NAME> --zone <ZONE> --confidential-compute --maintenance-policy=TERMINATE Default Value: By default, Confidential Computing is disabled for Compute instances. | L48: 1. https://cloud.google.com/compute/confidential-vm/docs/creating-cvm-instance 2. https://cloud.google.com/compute/confidential-vm/docs/about-cvm 3. https://cloud.google.com/confidential-computing 4. https://cloud.google.com/blog/products/identity-security/introducing-google-cloud-confidential-computing-with-confidential-vms | M48: v | N48: מערכת | O48: -
B49: 3.11 | C49: Data | D49: Protect | E49: הצפנת נתונים רגישים במנוחה | F49: Encrypt sensitive data at rest on servers, applications, and databases containing sensitive data. Storage-layer encryption, also known as server-side encryption, meets the minimum requirement of this Safeguard. Additional encryption methods may include application-layer encryption, also known as client-side encryption, where access to the data storage device(s) does not permit access to the plain-text data. | G49: 7.2 Ensure That All BigQuery Tables Are Encrypted With Customer-Managed Encryption Key (CMEK) (Automated) | H49: BigQuery by default encrypts the data as rest by employing Envelope Encryption using Google managed cryptographic keys. The data is encrypted using the data encryption keys and data encryption keys themselves are further encrypted using key encryption keys. This is seamless and do not require any additional input from the user. However, if you want to have greater control, Customer-managed encryption keys (CMEK) can be used as encryption key management solution for BigQuery Data Sets. If CMEK is used, the CMEK is used to encrypt the data encryption keys instead of using google-managed encryption keys. | I49: 7.2 | J49: BigQuery by default encrypts the data as rest by employing Envelope Encryption using Google managed cryptographic keys. This is seamless and does not require any additional input from the user. For greater control over the encryption, customer-managed encryption keys (CMEK) can be used as encryption key management solution for BigQuery tables. The CMEK is used to encrypt the data encryption keys instead of using google-managed encryption keys. BigQuery stores the table and CMEK association and the encryption/decryption is done automatically. Applying the Default Customer-managed keys on BigQuery data sets ensures that all the new tables created in the future will be encrypted using CMEK but existing tables need to be updated to use CMEK individually. Note: Google does not store your keys on its servers and cannot access your protected data unless you provide the key. This also means that if you forget or lose your key, there is no way for Google to recover the key or to recover any data encrypted with the lost key. Impact: Using Customer-managed encryption keys (CMEK) will incur additional labor-hour investment to create, protect, and manage the keys. | K49: From Google Cloud CLI Use the following command to copy the data. The source and the destination needs to be same in case copying to the original table. bq cp --destination_kms_key <customer_managed_key> source_dataset.source_table destination_dataset.destination_table Default Value: Google Managed keys are used as key encryption keys. | L49: 1. https://cloud.google.com/bigquery/docs/customer-managed-encryption | M49: v | N49: מערכת | O49: -
B50: 3.11 | C50: Data | D50: Protect | E50: הצפנת נתונים רגישים במנוחה | F50: Encrypt sensitive data at rest on servers, applications, and databases containing sensitive data. Storage-layer encryption, also known as server-side encryption, meets the minimum requirement of this Safeguard. Additional encryption methods may include application-layer encryption, also known as client-side encryption, where access to the data storage device(s) does not permit access to the plain-text data. | G50: 7.3 Ensure That a Default Customer-Managed Encryption Key (CMEK) Is Specified for All BigQuery Data Sets (Automated) | H50: BigQuery by default encrypts the data as rest by employing Envelope Encryption using Google managed cryptographic keys. The data is encrypted using the data encryption keys and data encryption keys themselves are further encrypted using key encryption keys. This is seamless and do not require any additional input from the user. However, if you want to have greater control, Customer-managed encryption keys (CMEK) can be used as encryption key management solution for BigQuery Data Sets. | I50: 7.3 | J50: BigQuery by default encrypts the data as rest by employing Envelope Encryption using Google managed cryptographic keys. This is seamless and does not require any additional input from the user. For greater control over the encryption, customer-managed encryption keys (CMEK) can be used as encryption key management solution for BigQuery Data Sets. Setting a Default Customer-managed encryption key (CMEK) for a data set ensure any tables created in future will use the specified CMEK if none other is provided. Note: Google does not store your keys on its servers and cannot access your protected data unless you provide the key. This also means that if you forget or lose your key, there is no way for Google to recover the key or to recover any data encrypted with the lost key. Impact: Using Customer-managed encryption keys (CMEK) will incur additional labor-hour investment to create, protect, and manage the keys. | K50: From Google Cloud CLI The default CMEK for existing data sets can be updated by specifying the default key in the EncryptionConfiguration.kmsKeyName field when calling the datasets.insert or datasets.patch methods Default Value: Google Managed keys are used as key encryption keys. | L50: 1. https://cloud.google.com/bigquery/docs/customer-managed-encryption | M50: v | N50: מערכת | O50: -
B51: 3.11 | C51: Data | D51: Protect | E51: הצפנת נתונים רגישים במנוחה | F51: Encrypt sensitive data at rest on servers, applications, and databases containing sensitive data. Storage-layer encryption, also known as server-side encryption, meets the minimum requirement of this Safeguard. Additional encryption methods may include application-layer encryption, also known as client-side encryption, where access to the data storage device(s) does not permit access to the plain-text data. | G51: 1.7 Ensure User-Managed/External Keys for Service Accounts Are Rotated Every 90 Days or Fewer (Automated) | H51: Service Account keys consist of a key ID (Private_key_Id) and Private key, which are used to sign programmatic requests users make to Google cloud services accessible to that particular service account. It is recommended that all Service Account keys are regularly rotated. Additional Information: For user-managed Service Account key(s), key management is entirely the user's responsibility. | I51: 1.7 | J51: Rotating Service Account keys will reduce the window of opportunity for an access key that is associated with a compromised or terminated account to be used. Service Account keys should be rotated to ensure that data cannot be accessed with an old key that might have been lost, cracked, or stolen. Each service account is associated with a key pair managed by Google Cloud Platform (GCP). It is used for service-to-service authentication within GCP. Google rotates the keys daily. GCP provides the option to create one or more user-managed (also called external key pairs) key pairs for use from outside GCP (for example, for use with Application Default Credentials). When a new key pair is created, the user is required to download the private key (which is not retained by Google). With external keys, users are responsible for keeping the private key secure and other management operations such as key rotation. External keys can be managed by the IAM API, gcloud command-line tool, or the Service Accounts page in the Google Cloud Platform Console. GCP facilitates up to 10 external service account keys per service account to facilitate key rotation. Impact: Rotating service account keys will break communication for dependent applications. Dependent applications need to be configured manually with the new key ID displayed in the Service account keys section and the private key downloaded by the user. | K51: From Google Cloud Console Delete any external (user-managed) Service Account Key older than 90 days: 1. Go to APIs & Services\Credentials using https://console.cloud.google.com/apis/credentials 2. In the Section Service Account Keys, for every external (user-managed) service account key where creation date is greater than or equal to the past 90 days, click Delete Bin Icon to Delete Service Account key Create a new external (user-managed) Service Account Key for a Service Account: 1. Go to APIs & Services\Credentials using https://console.cloud.google.com/apis/credentials 2. Click Create Credentials and Select Service Account Key. 3. Choose the service account in the drop-down list for which an External (user-managed) Service Account key needs to be created. 4. Select the desired key type format among JSON or P12. 5. Click Create. It will download the private key. Keep it safe. 6. Click Close if prompted. 7. The site will redirect to the APIs & Services\Credentials page. Make a note of the new ID displayed in the Service account keys section. Default Value: GCP does not provide an automation option for External (user-managed) Service key rotation. | L51: 1. https://cloud.google.com/iam/docs/understanding-service-accounts#managing_service_account_keys 2. https://cloud.google.com/sdk/gcloud/reference/iam/service-accounts/keys/list 3. https://cloud.google.com/iam/docs/service-accounts | M51: v | N51: מערכת | O51: -
B52: 3.12 | C52: Network | D52: Protect | E52: פלח עיבוד נתונים ואחסון בהתבסס על רגישות המידע | F52: Segment data processing and storage based on the sensitivity of the data. Do not process sensitive data on enterprise assets intended for lower sensitivity data. | G52: - | H52: - | I52: - | J52: - | K52: - | L52: - | N52: ארגוני | O52: -
B53: - | C53: - | D53: - | E53: תצורה מאובטחת של נכסים ותוכנה ארגוניים | F53: Establish and maintain the secure configuration of enterprise assets (end-user devices, including portable and mobile; network devices; non-computing/IoT devices; and servers) and software (operating systems and applications). | G53: - | H53: - | I53: - | J53: - | K53: - | L53: - | M53: - | N53: - | O53: -
B54: 4.1 | C54: Applications | D54: Protect | E54: הקמה ותחזוקה של תהליך תצורה מאובטח | F54: Establish and maintain a secure configuration process for enterprise assets (end-user devices, including portable and mobile, non-computing/IoT devices, and servers) and software (operating systems and applications). Review and update documentation annually, or when significant enterprise changes occur that could impact this Safeguard. | G54: 6.3.3 Ensure 'user Connections' Database Flag for Cloud Sql Sql Server Instance Is Set to a Non-limiting Value (Automated) | H54: It is recommended to check the user connections for a Cloud SQL SQL Server instance to ensure that it is not artificially limiting connections. | I54: 6.3.3 | J54: The user connections option specifies the maximum number of simultaneous user connections that are allowed on an instance of SQL Server. The actual number of user connections allowed also depends on the version of SQL Server that you are using, and also the limits of your application or applications and hardware. SQL Server allows a maximum of 32,767 user connections. Because user connections is by default a self-configuring value, with SQL Server adjusting the maximum number of user connections automatically as needed, up to the maximum value allowable. For example, if only 10 users are logged in, 10 user connection objects are allocated. In most cases, you do not have to change the value for this option. The default is 0, which means that the maximum (32,767) user connections are allowed. However if there is a number defined here that limits connections, SQL Server will not allow anymore above this limit. If the connections are at the limit, any new requests will be dropped, potentially causing lost data or outages for those using the database. Impact: Setting custom flags via command line on certain instances will cause all omitted flags to be reset to defaults. This may cause you to lose custom flags and could result in unforeseen complications or instance restarts. Because of this, it is recommended you apply these flags changes during a period of low usage. | K54: From Google Cloud Console 1. Go to the Cloud SQL Instances page in the Google Cloud Console by visiting https://console.cloud.google.com/sql/instances. 2. Select the SQL Server instance for which you want to enable to database flag. 3. Click Edit. 4. Scroll down to the Flags section. 5. To set a flag that has not been set on the instance before, click Add item, choose the flag user connections from the drop-down menu, and set its value to your organization recommended value. 6. Click Save to save your changes. 7. Confirm your changes under Flags on the Overview page. From Google Cloud CLI 1. Configure the user connections database flag for every Cloud SQL SQL Server database instance using the below command. gcloud sql instances patch <INSTANCE_NAME> --database-flags "user connections=[0-32,767]" Note : This command will overwrite all database flags previously set. To keep those and add new ones, include the values for all flags you want set on the instance; any flag not specifically included is set to its default value. For flags that do not take a value, specify the flag name followed by an equals sign ("="). Default Value: By default user connections is set to '0' which does not limit the number of connections, giving the server free reign to facilitate a max of 32,767 connections. | L54: 1. https://cloud.google.com/sql/docs/sqlserver/flags 2. https://docs.microsoft.com/en-us/sql/database-engine/configure-windows/configure-the-user-connections-server-configuration-option?view=sql-server-ver15 3. https://www.stigviewer.com/stig/ms_sql_server_2016_instance/2018-03-09/finding/V-79119 | M54: v | N54: מערכת | O54: -
B55: 4.1 | C55: Applications | D55: Protect | E55: הקמה ותחזוקה של תהליך תצורה מאובטח | F55: Establish and maintain a secure configuration process for enterprise assets (end-user devices, including portable and mobile, non-computing/IoT devices, and servers) and software (operating systems and applications). Review and update documentation annually, or when significant enterprise changes occur that could impact this Safeguard. | G55: 6.3.4 Ensure 'user options' database flag for Cloud SQL SQL Server instance is not configured (Automated) | H55: It is recommended that, user options database flag for Cloud SQL SQL Server instance should not be configured. | I55: 6.3.4 | J55: The user options option specifies global defaults for all users. A list of default query processing options is established for the duration of a user's work session. The user options option allows you to change the default values of the SET options (if the server's default settings are not appropriate). A user can override these defaults by using the SET statement. You can configure user options dynamically for new logins. After you change the setting of user options, new login sessions use the new setting; current login sessions are not affected. This recommendation is applicable to SQL Server database instances. Impact: Setting custom flags via command line on certain instances will cause all omitted flags to be reset to defaults. This may cause you to lose custom flags and could result in unforeseen complications or instance restarts. Because of this, it is recommended you apply these flags changes during a period of low usage. | K55: From Google Cloud Console 1. Go to the Cloud SQL Instances page in the Google Cloud Console by visiting https://console.cloud.google.com/sql/instances. 2. Select the SQL Server instance for which you want to enable to database flag. 3. Click Edit. 4. Scroll down to the Flags section. 5. Click the X next user options flag shown 6. Click Save to save your changes. 7. Confirm your changes under Flags on the Overview page. From Google Cloud CLI 1. List all Cloud SQL database Instances gcloud sql instances list 2. Clear the user options database flag for every Cloud SQL SQL Server database instance using either of the below commands. 1.Clearing all flags to their default value gcloud sql instances patch <INSTANCE_NAME> --clear-database-flags OR 2. To clear only `user options` database flag, configure the database flag by overriding the `user options`. Exclude `user options` flag and its value, and keep all other flags you want to configure. gcloud sql instances patch <INSTANCE_NAME> --database-flags [FLAG1=VALUE1,FLAG2=VALUE2] Note : This command will overwrite all database flags previously set. To keep those and add new ones, include the values for all flags you want set on the instance; any flag not specifically included is set to its default value. For flags that do not take a value, specify the flag name followed by an equals sign ("="). Default Value: By default 'user options' is not configured. | L55: 1. https://cloud.google.com/sql/docs/sqlserver/flags 2. https://docs.microsoft.com/en-us/sql/database-engine/configure-windows/configure-the-user-options-server-configuration-option?view=sql-server-ver15 3. https://www.stigviewer.com/stig/ms_sql_server_2016_instance/2018-03-09/finding/V-79335 | M55: v | N55: מערכת | O55: -
B56: 4.1 | C56: Applications | D56: Protect | E56: הקמה ותחזוקה של תהליך תצורה מאובטח | F56: Establish and maintain a secure configuration process for enterprise assets (end-user devices, including portable and mobile, non-computing/IoT devices, and servers) and software (operating systems and applications). Review and update documentation annually, or when significant enterprise changes occur that could impact this Safeguard. | G56: 6.3.6 Ensure '3625 (trace flag)' database flag for all Cloud SQL Server instances is set to 'on' (Automated) | H56: It is recommended to set 3625 (trace flag) database flag for Cloud SQL SQL Server instance to on. | I56: 6.3.6 | J56: Microsoft SQL Trace Flags are frequently used to diagnose performance issues or to debug stored procedures or complex computer systems, but they may also be recommended by Microsoft Support to address behavior that is negatively impacting a specific workload. All documented trace flags and those recommended by Microsoft Support are fully supported in a production environment when used as directed. 3625(trace log) Limits the amount of information returned to users who are not members of the sysadmin fixed server role, by masking the parameters of some error messages using '******'. Setting this in a Google Cloud flag for the instance allows for security through obscurity and prevents the disclosure of sensitive information, hence this is recommended to set this flag globally to on to prevent the flag having been left off, or changed by bad actors. This recommendation is applicable to SQL Server database instances. Impact: Changing flags on a database may cause it to be restarted. The best time to do this is at a time where there is low usage. | K56: From Google Cloud Console 1. Go to the Cloud SQL Instances page in the Google Cloud Console by visiting https://console.cloud.google.com/sql/instances. 2. Select the SQL Server instance for which you want to enable to database flag. 3. Click Edit. 4. Scroll down to the Flags section. 5. To set a flag that has not been set on the instance before, click Add item, choose the flag 3625 from the drop-down menu, and set its value to on. 6. Click Save to save your changes. 7. Confirm your changes under Flags on the Overview page. From Google Cloud CLI 1. Configure the 3625 database flag for every Cloud SQL SQL Server database instance using the below command. gcloud sql instances patch <INSTANCE_NAME> --database-flags "3625=on" Note : This command will overwrite all database flags previously set. To keep those and add new ones, include the values for all flags you want set on the instance; any flag not specifically included is set to its default value. For flags that do not take a value, specify the flag name followed by an equals sign ("="). Default Value: MySQL implementations by default have trace flags turned off, as they are used for logging purposes. | L56: 1. https://cloud.google.com/sql/docs/sqlserver/flags 2. https://docs.microsoft.com/en-us/sql/t-sql/database-console-commands/dbcc-traceon-trace-flags-transact-sql?view=sql-server-ver15#trace-flags 3. https://github.com/ktaranov/sqlserver-kit/blob/master/SQL%20Server%20Trace%20Flag.md | M56: v | N56: מערכת | O56: -
B57: 4.2 | C57: Network | D57: Protect | E57: הקמה ותחזוקה של תהליך תצורה מאובטח עבור תשתית רשת | F57: Establish and maintain a secure configuration process for network devices. Review and update documentation annually, or when significant enterprise changes occur that could impact this Safeguard. | G57: 3.1 Ensure That the Default Network Does Not Exist in a Project (Automated) | H57: To prevent use of default network, a project should not have a default network. | I57: 3.1 | J57: Rationale: The default network has a preconfigured network configuration and automatically generates the following insecure firewall rules: • default-allow-internal: Allows ingress connections for all protocols and ports among instances in the network. • default-allow-ssh: Allows ingress connections on TCP port 22(SSH) from any source to any instance in the network. • default-allow-rdp: Allows ingress connections on TCP port 3389(RDP) from any source to any instance in the network. • default-allow-icmp: Allows ingress ICMP traffic from any source to any instance in the network. These automatically created firewall rules do not get audit logged and cannot be configured to enable firewall rule logging. Furthermore, the default network is an auto mode network, which means that its subnets use the same predefined range of IP addresses, and as a result, it's not possible to use Cloud VPN or VPC Network Peering with the default network. Based on organization security and networking requirements, the organization should create a new network and delete the default network. Impact: When an organization deletes the default network, it may need to migrate or service onto a new network. | K57: From Google Cloud Console 1. Go to the VPC networks page by visiting: https://console.cloud.google.com/networking/networks/list. 2. Click the network named default. 3. On the network detail page, click EDIT. 4. Click DELETE VPC NETWORK. 5. If needed, create a new network to replace the default network. From Google Cloud CLI For each Google Cloud Platform project, 1. Delete the default network: gcloud compute networks delete default 2. If needed, create a new network to replace it: gcloud compute networks create NETWORK_NAME Prevention: The user can prevent the default network and its insecure default firewall rules from being created by setting up an Organization Policy to Skip default network creation at https://console.cloud.google.com/iam-admin/orgpolicies/compute-skipDefaultNetworkCreation. Default Value: By default, for each project, a default network is created. | L57: 1. https://cloud.google.com/compute/docs/networking#firewall_rules 2. https://cloud.google.com/compute/docs/reference/latest/networks/insert 3. https://cloud.google.com/compute/docs/reference/latest/networks/delete 4. https://cloud.google.com/vpc/docs/firewall-rules-logging 5. https://cloud.google.com/vpc/docs/vpc#default-network 6. https://cloud.google.com/sdk/gcloud/reference/compute/networks/delete | M57: v | N57: ארגוני | O57: v
